Workbook

Sheet MAIN (Anterior)
D2: PMS LIST - ELECTROMECHANICAL ENGINEERING | P2: TOTAL DOCUMENTS
P3: =SUM(Q7,Q8,Q17,Q18,Q27,Q32,Q40,Q36,Q23,Q22,Q12,Q13) -> 6616
C5: Instrução de manutenção /Maintenance instruction
C6: Electrical Maintenance Instructions | H6: Mechanical Maintenance Instructions | L6: Normative and Managerial Maintenance Instructions | Q6: TOTAL
B7: Total Instruções CTGBr "Por" | C7: =COUNTIFS(IM!G5:G161,"x",IM!B5:B161,"Instruções Manutenção Elétrica") -> 29 | H7: =COUNTIFS(IM!G5:G161,"x",IM!B5:B161,"Instruções Manutenção Mecânica") -> 29 | L7: =COUNTIFS(IM!G5:G161,"x",IM!B5:B161,"Instruções Manutenção Normativas e Gerenciais") -> 32 | Q7: =SUM(C7:P7) -> 90
B8: Total Instructions CTGBr "Eng" | C8: =COUNTIFS(IM!H5:H161,"x",IM!B5:B161,"Instruções Manutenção Elétrica") -> 12 | H8: =COUNTIFS(IM!H5:H161,"x",IM!B5:B161,"Instruções Manutenção Mecânica") -> 8 | L8: =COUNTIFS(IM!H5:H161,"x",IM!B5:B161,"Instruções Manutenção Normativas e Gerenciais") -> 20 | Q8: =SUM(C8:P8) -> 40
C10: Instrução de operaçaõ/Operating instruction
C11: Instruções de operação local | J11: Instruções de operação sistêmica | Q11: TOTAL
B12: Total Instruções CTGBr "Por" | C12: =COUNTIFS(IO!F5:F276,"X",IO!B5:B276,"Instruções de operação local") -> 8 | J12: =COUNTIFS(IO!F5:F276,"X",IO!B5:B276,"Instruções de operação sistêmica") -> 76 | Q12: =SUM(C12:P12) -> 84
B13: Total Instructions CTGBr "Eng" | C13: =COUNTIFS(IO!G5:G276,"X",IO!B5:B276,"Instruções de operação local") -> 6 | J13: =COUNTIFS(IO!G5:G276,"X",IO!B5:B276,"Instruções de operação sistêmica") -> 63 | Q13: =SUM(C13:P13) -> 69
C15: Guia de manutenção/Maintenance guide
C16: JUR | D16: CHV | E16: SAG | F16: CN1 | G16: CN2 | H16: CPV | I16: TAQ | J16: ROS | K16: PLM | L16: RET | M16: ILS | N16: JUP | O16: STO | P16: GAR | Q16: TOTAL
B17: Total Guias CTGBr "Por" | C17: =COUNTIFS(GM!$H$5:$H$1014,"X",GM!$C$5:$C$1014,"JUR") -> 50 | D17: =COUNTIFS(GM!$H$5:$H$1014,"X",GM!$C$5:$C$1014,"chv") -> 49 | E17: =COUNTIFS(GM!$H$5:$H$1014,"X",GM!$C$5:$C$1014,"sag") -> 45 | F17: =COUNTIFS(GM!$H$5:$H$1014,"X",GM!$C$5:$C$1014,"cn1") -> 49 | G17: =COUNTIFS(GM!$H$5:$H$1014,"X",GM!$C$5:$C$1014,"cn2") -> 49 | H17: =COUNTIFS(GM!$H$5:$H$1014,"X",GM!$C$5:$C$1014,"cpv") -> 48 | I17: =COUNTIFS(GM!$H$5:$H$1014,"X",GM!$C$5:$C$1014,"taq") -> 48 | J17: =COUNTIFS(GM!$H$5:$H$1014,"X",GM!$C$5:$C$1014,"ROS") -> 49 | K17: =COUNTIFS(GM!$H$5:$H$1014,"X",GM!$C$5:$C$1014,"PLM") -> 41 | L17: =COUNTIFS(GM!$H$5:$H$1014,"X",GM!$C$5:$C$1014,"RET") -> 41 | M17: =COUNTIFS(GM!$H$5:$H$1014,"X",GM!$C$5:$C$1014,"ILS") -> 62 | N17: =COUNTIFS(GM!$H$5:$H$1014,"X",GM!$C$5:$C$1014,"JUP") -> 64 | O17: =COUNTIFS(GM!$H$5:$H$1014,"X",GM!$C$5:$C$1014,"STO") -> 48 | P17: =COUNTIFS(GM!$H$5:$H$1014,"X",GM!$C$5:$C$1014,"GAR") -> 58 | Q17: =SUM(C17:P17) -> 701
B18: Total Guides CTGBr "Eng" | C18: =COUNTIFS(GM!$I$5:$I$1014,"X",GM!$C$5:$C$1014,"JUR") -> 47 | D18: =COUNTIFS(GM!$I$5:$I$1014,"X",GM!$C$5:$C$1014,"CHV") -> 46 | E18: =COUNTIFS(GM!$I$5:$I$1014,"X",GM!$C$5:$C$1014,"SAG") -> 42 | F18: =COUNTIFS(GM!$I$5:$I$1014,"X",GM!$C$5:$C$1014,"CN1") -> 45 | G18: =COUNTIFS(GM!$I$5:$I$1014,"X",GM!$C$5:$C$1014,"CN2") -> 45 | H18: =COUNTIFS(GM!$I$5:$I$1014,"X",GM!$C$5:$C$1014,"CPV") -> 44 | I18: =COUNTIFS(GM!$I$5:$I$1014,"X",GM!$C$5:$C$1014,"TAQ") -> 44 | J18: =COUNTIFS(GM!$I$5:$I$1014,"X",GM!$C$5:$C$1014,"ROS") -> 45 | K18: =COUNTIFS(GM!$I$5:$I$1014,"X",GM!$C$5:$C$1014,"PLM") -> 38 | L18: =COUNTIFS(GM!$I$5:$I$1014,"X",GM!$C$5:$C$1014,"RET") -> 38 | M18: =COUNTIFS(GM!$I$5:$I$1014,"X",GM!$C$5:$C$1014,"ILS") -> 58 | N18: =COUNTIFS(GM!$I$5:$I$1014,"X",GM!$C$5:$C$1014,"JUP") -> 60 | O18: =COUNTIFS(GM!$I$5:$I$1014,"X",GM!$C$5:$C$1014,"STO") -> 44 | P18: =COUNTIFS(GM!$I$5:$I$1014,"X",GM!$C$5:$C$1014,"GAR") -> 52 | Q18: =SUM(C18:P18) -> 648
C20: Guia de operação/Operation guide
C21: JUR | D21: CHV | E21: SAG | F21: CN1 | G21: CN2 | H21: CPV | I21: TAQ | J21: ROS | K21: PLM | L21: RET | M21: ILS | N21: JUP | O21: STO | P21: GAR | Q21: TOTAL
B22: Total Guias CTGBr "Por" | C22: =COUNTIFS(GO!G16:G457,"X",GO!C16:C457,"JUR") -> 0 | D22: =COUNTIFS(GO!G16:G457,"X",GO!C16:C457,"CHV") -> 5 | E22: =COUNTIFS(GO!G16:G457,"X",GO!C16:C457,"SAG") -> 8 | F22: =COUNTIFS(GO!G16:G457,"X",GO!C16:C457,"CN1") -> 7 | G22: =COUNTIFS(GO!G16:G457,"X",GO!C16:C457,"CN2") -> 7 | H22: =COUNTIFS(GO!G16:G457,"X",GO!C16:C457,"CPV") -> 8 | I22: =COUNTIFS(GO!G16:G457,"X",GO!C16:C457,"TAQ") -> 8 | J22: =COUNTIFS(GO!G16:G457,"X",GO!C16:C457,"ROS") -> 9 | K22: =COUNTIFS(GO!G16:G457,"X",GO!C16:C457,"PLM") -> 8 | L22: =COUNTIFS(GO!G16:G457,"X",GO!C16:C457,"RET") -> 8 | M22: =COUNTIFS(GO!G16:G457,"X",GO!C16:C457,"ILS") -> 73 | N22: =COUNTIFS(GO!G16:G457,"X",GO!C16:C457,"JUP") -> 41 | O22: =COUNTIFS(GO!G16:G457,"X",GO!C16:C457,"STO") -> 9 | P22: =COUNTIFS(GO!G16:G457,"X",GO!C16:C457,"GAR") -> 4 | Q22: =SUM(C22:P22) -> 195
B23: Total Guides CTGBr "Eng" | C23: =COUNTIFS(GO!H16:H457,"X",GO!C16:C457,"JUR") -> 0 | D23: =COUNTIFS(GO!H16:H457,"X",GO!C16:C457,"CHV") -> 2 | E23: =COUNTIFS(GO!H16:H457,"X",GO!C16:C457,"SAG") -> 4 | F23: =COUNTIFS(GO!H16:H457,"X",GO!C16:C457,"CN1") -> 4 | G23: =COUNTIFS(GO!H16:H457,"X",GO!C16:C457,"CN2") -> 4 | H23: =COUNTIFS(GO!H16:H457,"X",GO!C16:C457,"CPV") -> 3 | I23: =COUNTIFS(GO!H16:H457,"X",GO!C16:C457,"TAQ") -> 3 | J23: =COUNTIFS(GO!H16:H457,"X",GO!C16:C457,"ROS") -> 4 | K23: =COUNTIFS(GO!H16:H457,"X",GO!C16:C457,"PLM") -> 4 | L23: =COUNTIFS(GO!H16:H457,"X",GO!C16:C457,"RET") -> 4 | M23: =COUNTIFS(GO!H16:H457,"X",GO!C16:C457,"ILS") -> 22 | N23: =COUNTIFS(GO!H16:H457,"X",GO!C16:C457,"JUP") -> 3 | O23: =COUNTIFS(GO!H16:H457,"X",GO!C16:C457,"STO") -> 9 | P23: =COUNTIFS(GO!H16:H457,"X",GO!C16:C457,"GAR") -> 4 | Q23: =SUM(C23:P23) -> 70
C25: Protocolo/Protocol
C26: JUR | D26: CHV | E26: SAG | F26: CN1 | G26: CN2 | H26: CPV | I26: TAQ | J26: ROS | K26: PLM | L26: RET | M26: ILS | N26: JUP | O26: STO | P26: GAR | Q26: TOTAL
B27: Total Protocolos CTGBr | C27: =COUNTIFS(PR!F5:F4771,"x",PR!A5:A4771,"JUR") -> 298 | D27: =COUNTIFS(PR!F5:F4771,"x",PR!A5:A4771,"CHV") -> 290 | E27: =COUNTIFS(PR!F5:F4771,"x",PR!A5:A4771,"SAG") -> 281 | F27: =COUNTIFS(PR!F5:F4771,"x",PR!A5:A4771,"CN1") -> 296 | G27: =COUNTIFS(PR!F5:F4771,"x",PR!A5:A4771,"CN2") -> 293 | H27: =COUNTIFS(PR!F5:F4771,"x",PR!A5:A4771,"CPV") -> 286 | I27: =COUNTIFS(PR!F5:F4771,"x",PR!A5:A4771,"TAQ") -> 311 | J27: =COUNTIFS(PR!F5:F4771,"x",PR!A5:A4771,"ROS") -> 308 | K27: =COUNTIFS(PR!F5:F4771,"x",PR!A5:A4771,"PLM") -> 252 | L27: =COUNTIFS(PR!F5:F4771,"x",PR!A5:A4771,"RET") -> 252 | M27: =COUNTIFS(PR!F5:F4771,"x",PR!A5:A4771,"ILS") -> 315 | N27: =COUNTIFS(PR!F5:F4771,"x",PR!A5:A4771,"JUP") -> 324 | O27: =COUNTIFS(PR!F5:F4771,"x",PR!A5:A4771,"STO") -> 273 | P27: =COUNTIFS(PR!F5:F4771,"x",PR!A5:A4771,"GAR") -> 306 | Q27: =SUM(C27:P27) -> 4085
B28: Total Protocols CTGBr "Eng" | C28: =COUNTIFS(PR!G5:G4771,"x",PR!A5:A4771,"JUR") -> 8 | D28: =COUNTIFS(PR!G5:G4771,"x",PR!A5:A4771,"CHV") -> 8 | E28: =COUNTIFS(PR!G5:G4771,"x",PR!A5:A4771,"SAG") -> 7 | F28: =COUNTIFS(PR!G5:G4771,"x",PR!A5:A4771,"CN1") -> 8 | G28: =COUNTIFS(PR!G5:G4771,"x",PR!A5:A4771,"CN2") -> 8 | H28: =COUNTIFS(PR!G5:G4771,"x",PR!A5:A4771,"CPV") -> 8 | I28: =COUNTIFS(PR!G5:G4771,"x",PR!A5:A4771,"TAQ") -> 8 | J28: =COUNTIFS(PR!G5:G4771,"x",PR!A5:A4771,"ROS") -> 8 | K28: =COUNTIFS(PR!G5:G4771,"x",PR!A5:A4771,"PLM") -> 8 | L28: =COUNTIFS(PR!G5:G4771,"x",PR!A5:A4771,"RET") -> 8 | M28: =COUNTIFS(PR!G5:G4771,"x",PR!A5:A4771,"ILS") -> 10 | N28: =COUNTIFS(PR!G5:G4771,"x",PR!A5:A4771,"JUP") -> 8 | O28: =COUNTIFS(PR!G5:G4771,"x",PR!A5:A4771,"STO") -> 8 | P28: =COUNTIFS(PR!G5:G4771,"x",PR!A5:A4771,"GAR") -> 8 | Q28: =SUM(C28:P28) -> 113
C30: Manual de manutenção/Maintenance manual
C31: JUR | D31: CHV | E31: SAG | F31: CN1 | G31: CN2 | H31: CPV | I31: TAQ | J31: ROS | K31: PLM | L31: RET | M31: ILS | N31: JUP | O31: STO | P31: GAR | Q31: TOTAL
B32: Total Manuals CTGBr | C32: =COUNTIFS(MM!M7:M642,"Publicado",MM!C7:C642,"JUR") -> 21 | D32: =COUNTIFS(MM!M7:M642,"Publicado",MM!C7:C642,"CHV") -> 19 | E32: =COUNTIFS(MM!M7:M642,"Publicado",MM!C7:C642,"SAG") -> 25 | F32: =COUNTIFS(MM!M7:M642,"Publicado",MM!C7:C642,"CN1") -> 30 | G32: =COUNTIFS(MM!M7:M642,"Publicado",MM!C7:C642,"CN2") -> 33 | H32: =COUNTIFS(MM!M7:M642,"Publicado",MM!C7:C642,"CPV") -> 31 | I32: =COUNTIFS(MM!M7:M642,"Publicado",MM!C7:C642,"TAQ") -> 20 | J32: =COUNTIFS(MM!M7:M642,"Publicado",MM!C7:C642,"ROS") -> 28 | K32: =COUNTIFS(MM!M7:M642,"Publicado",MM!C7:C642,"PLM") -> 16 | L32: =COUNTIFS(MM!M7:M642,"Publicado",MM!C7:C642,"RET") -> 15 | M32: =COUNTIFS(MM!M7:M642,"Publicado",MM!C7:C642,"ILS") -> 119 | N32: =COUNTIFS(MM!M7:M642,"Publicado",MM!C7:C642,"JUP") -> 43 | O32: =COUNTIFS(MM!M7:M642,"Publicado",MM!C7:C642,"STO") -> 4 | P32: =COUNTIFS(MM!M7:M642,"Publicado",MM!C7:C642,"GAR") -> 38 | Q32: =SUM(C32:P32) -> 442
C34: Manual de operação/Operation Manual
C35: JUR | D35: CHV | E35: SAG | F35: CN1 | G35: CN2 | H35: CPV | I35: TAQ | J35: ROS | K35: PLM | L35: RET | M35: ILS | N35: JUP | O35: STO | P35: GAR | Q35: TOTAL
B36: Total Manuals CTGBr | C36: =COUNTIFS(MO!K110:K659,"Publicado",MO!C110:C659,"JUR") -> 0 | D36: =COUNTIFS(MO!K110:K659,"Publicado",MO!C110:C659,"CHV") -> 0 | E36: =COUNTIFS(MO!K110:K659,"Publicado",MO!C110:C659,"SAG") -> 0 | F36: =COUNTIFS(MO!K110:K659,"Publicado",MO!C110:C659,"CN1") -> 0 | G36: =COUNTIFS(MO!K110:K659,"Publicado",MO!C110:C659,"CN2") -> 0 | H36: =COUNTIFS(MO!K110:K659,"Publicado",MO!C110:C659,"CPV") -> 16 | I36: =COUNTIFS(MO!K110:K659,"Publicado",MO!C110:C659,"TAQ") -> 21 | J36: =COUNTIFS(MO!K110:K659,"Publicado",MO!C110:C659,"ROS") -> 19 | K36: =COUNTIFS(MO!K110:K659,"Publicado",MO!C110:C659,"PLM") -> 25 | L36: =COUNTIFS(MO!K110:K659,"Publicado",MO!C110:C659,"RET") -> 25 | M36: =COUNTIFS(MO!K110:K659,"Publicado",MO!C110:C659,"ILS") -> 11 | N36: =COUNTIFS(MO!K110:K659,"Publicado",MO!C110:C659,"JUP") -> 27 | O36: =COUNTIFS(MO!K110:K659,"Publicado",MO!C110:C659,"STO") -> 10 | P36: =COUNTIFS(MO!K110:K659,"Publicado",MO!C110:C659,"GAR") -> 0 | Q36: =SUM(C36:P36) -> 154
C38: Política/Politic
C39: Políticas "Por" | J39: Politics "Eng" | Q39: TOTAL
B40: Total Politics CTGBr | C40: =COUNTIFS(POL!E5:E83,"X") -> 19 | J40: =COUNTIFS(POL!F5:F83,"X") -> 19 | Q40: =SUM(C40:P40) -> 38

Sheet MAIN
D2: PMS LIST - ELECTROMECHANICAL ENGINEERING | P2: TOTAL DOCUMENTS
P3: =SUM(U7,U17,U32,U36,U22,U12,C41) -> 1894
C5: Instrução de manutenção /Maintenance instruction
C6: Electrical Maintenance Instructions | H6: Mechanical Maintenance Instructions | L6: Normative and Managerial Maintenance Instructions | U6: TOTAL
B7: Total Instruções CTGBr "Por" | C7: =COUNTIFS(IM!G5:G199,"x",IM!B5:B199,"Instruções Manutenção Elétrica") -> 29 | H7: =COUNTIFS(IM!G5:G199,"x",IM!B5:B199,"Instruções Manutenção Mecânica") -> 29 | L7: =COUNTIFS(IM!G5:G199,"x",IM!B5:B199,"Instruções Manutenção Normativas e Gerenciais") -> 32 | U7: =SUM(C7:P7) -> 90 | V7: =U7-U8 -> 50
B8: Total Instructions CTGBr "Eng" | C8: =COUNTIFS(IM!H5:H199,"x",IM!B5:B199,"Instruções Manutenção Elétrica") -> 12 | H8: =COUNTIFS(IM!H5:H199,"x",IM!B5:B199,"Instruções Manutenção Mecânica") -> 8 | L8: =COUNTIFS(IM!H5:H199,"x",IM!B5:B199,"Instruções Manutenção Normativas e Gerenciais") -> 20 | U8: =SUM(C8:P8) -> 40
C10: Instrução de operaçaõ/Operating instruction
C11: Instruções de operação local | J11: Instruções de operação sistêmica | U11: TOTAL
B12: Total Instruções CTGBr "Por" | C12: =COUNTIFS(IO!F5:F276,"X",IO!B5:B276,"Instruções de operação local") -> 8 | J12: =COUNTIFS(IO!F5:F276,"X",IO!B5:B276,"Instruções de operação sistêmica") -> 76 | U12: =SUM(C12:P12) -> 84 | V12: =U12-U13 -> 15
B13: Total Instructions CTGBr "Eng" | C13: =COUNTIFS(IO!G5:G276,"X",IO!B5:B276,"Instruções de operação local") -> 6 | J13: =COUNTIFS(IO!G5:G276,"X",IO!B5:B276,"Instruções de operação sistêmica") -> 63 | U13: =SUM(C13:P13) -> 69
C15: Guia de manutenção/Maintenance guide
C16: JUR | D16: CHV | E16: SAG | F16: CN1 | G16: CN2 | H16: CPV | I16: TAQ | J16: ROS | K16: PLM | L16: RET | M16: ILS | N16: JUP | O16: STO | P16: GAR | Q16: ARN | R16: SDP | S16: COG | T16: UHE | U16: TOTAL
B17: Total Guias CTGBr "Por" | C17: =COUNTIFS(GM!$H$5:$H$1014,"X",GM!$C$5:$C$1014,"JUR") -> 50 | D17: =COUNTIFS(GM!$H$5:$H$1014,"X",GM!$C$5:$C$1014,"chv") -> 49 | E17: =COUNTIFS(GM!$H$5:$H$1014,"X",GM!$C$5:$C$1014,"SAG") -> 45 | F17: =COUNTIFS(GM!$H$5:$H$1014,"X",GM!$C$5:$C$1014,"CN1") -> 49 | G17: =COUNTIFS(GM!$H$5:$H$1014,"X",GM!$C$5:$C$1014,"CN2") -> 49 | H17: =COUNTIFS(GM!$H$5:$H$1014,"X",GM!$C$5:$C$1014,"CPV") -> 48 | I17: =COUNTIFS(GM!$H$5:$H$1014,"X",GM!$C$5:$C$1014,"TAQ") -> 48 | J17: =COUNTIFS(GM!$H$5:$H$1014,"X",GM!$C$5:$C$1014,"ROS") -> 49 | K17: =COUNTIFS(GM!$H$5:$H$1014,"X",GM!$C$5:$C$1014,"PLM") -> 41 | L17: =COUNTIFS(GM!$H$5:$H$1014,"X",GM!$C$5:$C$1014,"RET") -> 41 | M17: =COUNTIFS(GM!$H$5:$H$1014,"X",GM!$C$5:$C$1014,"ILS") -> 62 | N17: =COUNTIFS(GM!$H$5:$H$1014,"X",GM!$C$5:$C$1014,"JUP") -> 64 | O17: =COUNTIFS(GM!$H$5:$H$1014,"X",GM!$C$5:$C$1014,"STO") -> 48 | P17: =COUNTIFS(GM!$H$5:$H$1014,"X",GM!$C$5:$C$1014,"GAR") -> 58 | Q17: =COUNTIFS(GM!$H$5:$H$1014,"X",GM!$C$5:$C$1014,"ARN") -> 21 | R17: =COUNTIFS(GM!$H$5:$H$1014,"X",GM!$C$5:$C$1014,"SDP") -> 28 | S17: =COUNTIFS(GM!$H$5:$H$1014,"X",GM!$C$5:$C$1014,"COG") -> 1 | T17: =COUNTIFS(GM!$H$5:$H$1014,"X",GM!$C$5:$C$1014,"UHE") -> 0 | U17: =SUM(C17:T17) -> 751 | V17: =U17-U18 -> 53
B18: Total Guides CTGBr "Eng" | C18: =COUNTIFS(GM!$I$5:$I$1014,"X",GM!$C$5:$C$1014,"JUR") -> 47 | D18: =COUNTIFS(GM!$I$5:$I$1014,"X",GM!$C$5:$C$1014,"CHV") -> 46 | E18: =COUNTIFS(GM!$I$5:$I$1014,"X",GM!$C$5:$C$1014,"SAG") -> 42 | F18: =COUNTIFS(GM!$I$5:$I$1014,"X",GM!$C$5:$C$1014,"CN1") -> 45 | G18: =COUNTIFS(GM!$I$5:$I$1014,"X",GM!$C$5:$C$1014,"CN2") -> 45 | H18: =COUNTIFS(GM!$I$5:$I$1014,"X",GM!$C$5:$C$1014,"CPV") -> 44 | I18: =COUNTIFS(GM!$I$5:$I$1014,"X",GM!$C$5:$C$1014,"TAQ") -> 44 | J18: =COUNTIFS(GM!$I$5:$I$1014,"X",GM!$C$5:$C$1014,"ROS") -> 45 | K18: =COUNTIFS(GM!$I$5:$I$1014,"X",GM!$C$5:$C$1014,"PLM") -> 38 | L18: =COUNTIFS(GM!$I$5:$I$1014,"X",GM!$C$5:$C$1014,"RET") -> 38 | M18: =COUNTIFS(GM!$I$5:$I$1014,"X",GM!$C$5:$C$1014,"ILS") -> 58 | N18: =COUNTIFS(GM!$I$5:$I$1014,"X",GM!$C$5:$C$1014,"JUP") -> 60 | O18: =COUNTIFS(GM!$I$5:$I$1014,"X",GM!$C$5:$C$1014,"STO") -> 44 | P18: =COUNTIFS(GM!$I$5:$I$1014,"X",GM!$C$5:$C$1014,"GAR") -> 52 | Q18: =COUNTIFS(GM!$I$5:$I$1014,"X",GM!$C$5:$C$1014,"ARN") -> 21 | R18: =COUNTIFS(GM!$I$5:$I$1014,"X",GM!$C$5:$C$1014,"SDP") -> 28 | S18: =COUNTIFS(GM!$I$5:$I$1014,"X",GM!$C$5:$C$1014,"COG") -> 1 | T18: =COUNTIFS(GM!$I$5:$I$1014,"X",GM!$C$5:$C$1014,"UHE") -> 0 | U18: =SUM(C18:T18) -> 698
C20: Guia de operação/Operation guide
C21: JUR | D21: CHV | E21: SAG | F21: CN1 | G21: CN2 | H21: CPV | I21: TAQ | J21: ROS | K21: PLM | L21: RET | M21: ILS | N21: JUP | O21: STO | P21: GAR | Q21: ARN | R21: SDP | S21: COG | T21: UHE | U21: TOTAL
B22: Total Guias CTGBr "Por" | C22: =COUNTIFS(GO!G5:G457,"X",GO!C5:C457,"JUR") -> 8 | D22: =COUNTIFS(GO!G5:G457,"X",GO!C5:C457,"CHV") -> 8 | E22: =COUNTIFS(GO!G5:G457,"X",GO!C5:C457,"SAG") -> 8 | F22: =COUNTIFS(GO!G5:G457,"X",GO!C5:C457,"CN1") -> 7 | G22: =COUNTIFS(GO!G5:G457,"X",GO!C5:C457,"CN2") -> 7 | H22: =COUNTIFS(GO!G5:G457,"X",GO!C5:C457,"CPV") -> 8 | I22: =COUNTIFS(GO!G5:G457,"X",GO!C5:C457,"TAQ") -> 8 | J22: =COUNTIFS(GO!G5:G457,"X",GO!C5:C457,"ROS") -> 9 | K22: =COUNTIFS(GO!G5:G457,"X",GO!C5:C457,"PLM") -> 8 | L22: =COUNTIFS(GO!G5:G457,"X",GO!C5:C457,"RET") -> 8 | M22: =COUNTIFS(GO!G5:G457,"X",GO!C5:C457,"ILS") -> 73 | N22: =COUNTIFS(GO!G5:G457,"X",GO!C5:C457,"JUP") -> 41 | O22: =COUNTIFS(GO!G5:G457,"X",GO!C5:C457,"STO") -> 9 | P22: =COUNTIFS(GO!G5:G457,"X",GO!C5:C457,"GAR") -> 4 | Q22: =COUNTIFS(GO!G5:G457,"X",GO!C5:C457,"ARN") -> 3 | R22: =COUNTIFS(GO!G5:G457,"X",GO!C5:C457,"SDP") -> 0 | S22: =COUNTIFS(GO!G5:G457,"X",GO!C5:C457,"COG") -> 3 | T22: =COUNTIFS(GO!G5:G457,"X",GO!C5:C457,"UHE") -> 0 | U22: =SUM(C22:T22) -> 212 | V22: =U22-U23 -> 129
B23: Total Guides CTGBr "Eng" | C23: =COUNTIFS(GO!H5:H457,"X",GO!C5:C457,"JUR") -> 4 | D23: =COUNTIFS(GO!H5:H457,"X",GO!C5:C457,"CHV") -> 5 | E23: =COUNTIFS(GO!H5:H457,"X",GO!C5:C457,"SAG") -> 4 | F23: =COUNTIFS(GO!H5:H457,"X",GO!C5:C457,"CN1") -> 4 | G23: =COUNTIFS(GO!H5:H457,"X",GO!C5:C457,"CN2") -> 4 | H23: =COUNTIFS(GO!H5:H457,"X",GO!C5:C457,"CPV") -> 3 | I23: =COUNTIFS(GO!H5:H457,"X",GO!C5:C457,"TAQ") -> 3 | J23: =COUNTIFS(GO!H5:H457,"X",GO!C5:C457,"ROS") -> 4 | K23: =COUNTIFS(GO!H5:H457,"X",GO!C5:C457,"PLM") -> 4 | L23: =COUNTIFS(GO!H5:H457,"X",GO!C5:C457,"RET") -> 4 | M23: =COUNTIFS(GO!H5:H457,"X",GO!C5:C457,"ILS") -> 22 | N23: =COUNTIFS(GO!H5:H457,"X",GO!C5:C457,"JUP") -> 3 | O23: =COUNTIFS(GO!H5:H457,"X",GO!C5:C457,"STO") -> 9 | P23: =COUNTIFS(GO!H5:H457,"X",GO!C5:C457,"GAR") -> 4 | Q23: =COUNTIFS(GO!H5:H457,"X",GO!C5:C457,"ARN") -> 3 | R23: =COUNTIFS(GO!H5:H457,"X",GO!C5:C457,"SDP") -> 0 | S23: =COUNTIFS(GO!H5:H457,"X",GO!C5:C457,"COG") -> 3 | T23: =COUNTIFS(GO!H5:H457,"X",GO!C5:C457,"UHE") -> 0 | U23: =SUM(C23:T23) -> 83
C25: Protocolo/Protocol
C26: JUR | D26: CHV | E26: SAG | F26: CN1 | G26: CN2 | H26: CPV | I26: TAQ | J26: ROS | K26: PLM | L26: RET | M26: ILS | N26: JUP | O26: STO | P26: GAR | Q26: ARN | R26: SDP | S26: COG | T26: UHE | U26: TOTAL
B27: Total Protocolos CTGBr | C27: =COUNTIFS(PR!F5:F4771,"x",PR!A5:A4771,"JUR") -> 298 | D27: =COUNTIFS(PR!F5:F4771,"x",PR!A5:A4771,"CHV") -> 290 | E27: =COUNTIFS(PR!F5:F4771,"x",PR!A5:A4771,"SAG") -> 281 | F27: =COUNTIFS(PR!F5:F4771,"x",PR!A5:A4771,"CN1") -> 296 | G27: =COUNTIFS(PR!F5:F4771,"x",PR!A5:A4771,"CN2") -> 293 | H27: =COUNTIFS(PR!F5:F4771,"x",PR!A5:A4771,"CPV") -> 286 | I27: =COUNTIFS(PR!F5:F4771,"x",PR!A5:A4771,"TAQ") -> 311 | J27: =COUNTIFS(PR!F5:F4771,"x",PR!A5:A4771,"ROS") -> 308 | K27: =COUNTIFS(PR!F5:F4771,"x",PR!A5:A4771,"PLM") -> 252 | L27: =COUNTIFS(PR!F5:F4771,"x",PR!A5:A4771,"RET") -> 252 | M27: =COUNTIFS(PR!F5:F4771,"x",PR!A5:A4771,"ILS") -> 315 | N27: =COUNTIFS(PR!F5:F4771,"x",PR!A5:A4771,"JUP") -> 324 | O27: =COUNTIFS(PR!F5:F4771,"x",PR!A5:A4771,"STO") -> 273 | P27: =COUNTIFS(PR!F5:F4771,"x",PR!A5:A4771,"GAR") -> 306 | Q27: =COUNTIFS(PR!F5:F4771,"x",PR!A5:A4771,"ARN") -> 70 | R27: =COUNTIFS(PR!F5:F4771,"x",PR!A5:A4771,"SDP") -> 14 | S27: =COUNTIFS(PR!F5:F4771,"x",PR!A5:A4771,"COG") -> 0 | T27: =COUNTIFS(PR!F5:F4771,"x",PR!A5:A4771,"UHE") -> 0 | U27: =SUM(C27:T27) -> 4169 | V27: =U27-U28 -> 4054
B28: Total Protocols CTGBr "Eng" | C28: =COUNTIFS(PR!G5:G4771,"x",PR!A5:A4771,"JUR") -> 8 | D28: =COUNTIFS(PR!G5:G4771,"x",PR!A5:A4771,"CHV") -> 8 | E28: =COUNTIFS(PR!G5:G4771,"x",PR!A5:A4771,"SAG") -> 7 | F28: =COUNTIFS(PR!G5:G4771,"x",PR!A5:A4771,"CN1") -> 8 | G28: =COUNTIFS(PR!G5:G4771,"x",PR!A5:A4771,"CN2") -> 8 | H28: =COUNTIFS(PR!G5:G4771,"x",PR!A5:A4771,"CPV") -> 8 | I28: =COUNTIFS(PR!G5:G4771,"x",PR!A5:A4771,"TAQ") -> 8 | J28: =COUNTIFS(PR!G5:G4771,"x",PR!A5:A4771,"ROS") -> 8 | K28: =COUNTIFS(PR!G5:G4771,"x",PR!A5:A4771,"PLM") -> 8 | L28: =COUNTIFS(PR!G5:G4771,"x",PR!A5:A4771,"RET") -> 8 | M28: =COUNTIFS(PR!G5:G4771,"x",PR!A5:A4771,"ILS") -> 10 | N28: =COUNTIFS(PR!G5:G4771,"x",PR!A5:A4771,"JUP") -> 8 | O28: =COUNTIFS(PR!G5:G4771,"x",PR!A5:A4771,"STO") -> 8 | P28: =COUNTIFS(PR!G5:G4771,"x",PR!A5:A4771,"GAR") -> 8 | Q28: =COUNTIFS(PR!G5:G4771,"x",PR!A5:A4771,"ARN") -> 1 | R28: =COUNTIFS(PR!G5:G4771,"x",PR!A5:A4771,"SDP") -> 1 | S28: =COUNTIFS(PR!G5:G4771,"x",PR!A5:A4771,"COG") -> 0 | T28: =COUNTIFS(PR!G5:G4771,"x",PR!A5:A4771,"UHE") -> 0 | U28: =SUM(C28:T28) -> 115
C30: Manual de manutenção/Maintenance manual
C31: JUR | D31: CHV | E31: SAG | F31: CN1 | G31: CN2 | H31: CPV | I31: TAQ | J31: ROS | K31: PLM | L31: RET | M31: ILS | N31: JUP | O31: STO | P31: GAR | Q31: ARN | R31: SDP | S31: COG | T31: UHE | U31: TOTAL
B32: Total Manuals CTGBr | C32: =COUNTIFS(MM!M6:M798,"Publicado",MM!C6:C798,"JUR") -> 21 | D32: =COUNTIFS(MM!M6:M798,"Publicado",MM!C6:C798,"CHV") -> 19 | E32: =COUNTIFS(MM!M6:M798,"Publicado",MM!C6:C798,"SAG") -> 25 | F32: =COUNTIFS(MM!M6:M798,"Publicado",MM!C6:C798,"CN1") -> 32 | G32: =COUNTIFS(MM!M6:M798,"Publicado",MM!C6:C798,"CN2") -> 33 | H32: =COUNTIFS(MM!M6:M798,"Publicado",MM!C6:C798,"CPV") -> 41 | I32: =COUNTIFS(MM!M6:M798,"Publicado",MM!C6:C798,"TAQ") -> 24 | J32: =COUNTIFS(MM!M6:M798,"Publicado",MM!C6:C798,"ROS") -> 40 | K32: =COUNTIFS(MM!M6:M798,"Publicado",MM!C6:C798,"PLM") -> 16 | L32: =COUNTIFS(MM!M6:M798,"Publicado",MM!C6:C798,"RET") -> 15 | M32: =COUNTIFS(MM!M6:M798,"Publicado",MM!C6:C798,"ILS") -> 120 | N32: =COUNTIFS(MM!M6:M798,"Publicado",MM!C6:C798,"JUP") -> 47 | O32: =COUNTIFS(MM!M6:M798,"Publicado",MM!C6:C798,"STO") -> 4 | P32: =COUNTIFS(MM!M6:M798,"Publicado",MM!C6:C798,"GAR") -> 38 | Q32: =COUNTIFS(MM!M6:M798,"Publicado",MM!C6:C798,"ARN") -> 0 | R32: =COUNTIFS(MM!M6:M798,"Publicado",MM!C6:C798,"SDP") -> 0 | S32: =COUNTIFS(MM!M6:M798,"Publicado",MM!C6:C798,"COG") -> 2 | T32: =COUNTIFS(MM!M6:M798,"Publicado",MM!C6:C798,"UHE") -> 3 | U32: =SUM(C32:T32) -> 480
C34: Manual de operação/Operation Manual
C35: JUR | D35: CHV | E35: SAG | F35: CN1 | G35: CN2 | H35: CPV | I35: TAQ | J35: ROS | K35: PLM | L35: RET | M35: ILS | N35: JUP | O35: STO | P35: GAR | Q35: ARN | R35: SDP | S35: COG | T35: UHE | U35: TOTAL
B36: Total Manuais CTGBr "Por" | C36: =COUNTIFS(MO!K6:K600,"Publicado",MO!C6:C600,"JUR") -> 20 | D36: =COUNTIFS(MO!K6:K600,"Publicado",MO!C6:C600,"CHV") -> 28 | E36: =COUNTIFS(MO!K6:K600,"Publicado",MO!C6:C600,"SAG") -> 21 | F36: =COUNTIFS(MO!K6:K600,"Publicado",MO!C6:C600,"CN1") -> 19 | G36: =COUNTIFS(MO!K6:K600,"Publicado",MO!C6:C600,"CN2") -> 16 | H36: =COUNTIFS(MO!K6:K600,"Publicado",MO!C6:C600,"CPV") -> 16 | I36: =COUNTIFS(MO!K6:K600,"Publicado",MO!C6:C600,"TAQ") -> 21 | J36: =COUNTIFS(MO!K6:K600,"Publicado",MO!C6:C600,"ROS") -> 19 | K36: =COUNTIFS(MO!K6:K600,"Publicado",MO!C6:C600,"PLM") -> 25 | L36: =COUNTIFS(MO!K6:K600,"Publicado",MO!C6:C600,"RET") -> 25 | M36: =COUNTIFS(MO!K6:K600,"Publicado",MO!C6:C600,"ILS") -> 11 | N36: =COUNTIFS(MO!K6:K600,"Publicado",MO!C6:C600,"JUP") -> 27 | O36: =COUNTIFS(MO!K6:K600,"Publicado",MO!C6:C600,"STO") -> 10 | P36: =COUNTIFS(MO!K6:K600,"Publicado",MO!C6:C600,"GAR") -> 0 | Q36: =COUNTIFS(MO!K6:K600,"Publicado",MO!C6:C600,"ARN") -> 0 | R36: =COUNTIFS(MO!K6:K600,"Publicado",MO!C6:C600,"SDP") -> 0 | S36: =COUNTIFS(MO!K6:K600,"Publicado",MO!C6:C600,"COG") -> 0 | T36: =COUNTIFS(MO!K6:K600,"Publicado",MO!C6:C600,"UHE") -> 0 | U36: =SUM(C36:T36) -> 258
B37: Total Manuals CTGBr "Eng" | C37: =COUNTIFS(MO!M6:M600,"X",MO!C6:C600,"JUR") -> 20 | D37: =COUNTIFS(MO!M6:M600,"X",MO!C6:C600,"CHV") -> 28 | E37: =COUNTIFS(MO!M6:M600,"X",MO!C6:C600,"SAG") -> 21 | F37: =COUNTIFS(MO!M6:M600,"X",MO!C6:C600,"CN1") -> 19 | G37: =COUNTIFS(MO!M6:M600,"X",MO!C6:C600,"CN2") -> 16 | H37: =COUNTIFS(MO!M6:M600,"X",MO!C6:C600,"CPV") -> 0 | I37: =COUNTIFS(MO!M6:M600,"X",MO!C6:C600,"TAQ") -> 0 | J37: =COUNTIFS(MO!M6:M600,"X",MO!C6:C600,"ROS") -> 0 | K37: =COUNTIFS(MO!M6:M600,"X",MO!C6:C600,"PLM") -> 25 | L37: =COUNTIFS(MO!M6:M600,"X",MO!C6:C600,"RET") -> 25 | M37: =COUNTIFS(MO!M6:M600,"X",MO!C6:C600,"ILS") -> 0 | N37: =COUNTIFS(MO!M6:M600,"X",MO!C6:C600,"JUP") -> 0 | O37: =COUNTIFS(MO!M6:M600,"X",MO!C6:C600,"STO") -> 10 | P37: =COUNTIFS(MO!M6:M600,"X",MO!C6:C600,"GAR") -> 0 | Q37: =COUNTIFS(MO!M6:M600,"X",MO!C6:C600,"ARN") -> 0 | R37: =COUNTIFS(MO!M6:M600,"X",MO!C6:C600,"SDP") -> 0 | S37: =COUNTIFS(MO!M6:M600,"X",MO!C6:C600,"COG") -> 0 | T37: =COUNTIFS(MO!M6:M600,"X",MO!C6:C600,"UHE") -> 0 | U37: =SUM(C37:T37) -> 164
C39: Política/Politic
C40: Políticas "Por" | J40: Politics "Eng" | U40: TOTAL
B41: Total Politics CTGBr | C41: =COUNTIFS(POL!E5:E83,"X") -> 19 | J41: =COUNTIFS(POL!F5:F83,"X") -> 19 | U41: =SUM(C41:T41) -> 38

Sheet POL
A1: POL - POLÍTICAS PMS (PMS POLICIES)
I2: TOTAL
D3: Area | E3: =COUNTIF(E4:E80,"X") -> 19 | F3: =COUNTIF(F4:F80,"X") -> 19 | I3: =COUNTIF(I4:I4983,"Publicado") -> 18 | L3: Em dia | M3: Alerta | N3: Vencido | Q3: =TODAY() -> 46198
A4: NÚMERO | B4: DESCRIÇÃO | E4: Por. | F4: Ing. | G4: Data aprovação | H4: Data Vencimento | I4: Status | J4: Status validade | K4: =TODAY() -> 46198 | Q4: Dias que falta para vencer
A5: POL-PMS-001 | B5: Política de Gestão da Produção e Inovação | C5: Production and Technology Management Policy | D5: Engenharia Eletromecânica | E5: X | F5: X | G5: 45895 | H5: =G5+1096 -> 46991 | I5: Publicado | J5: =IF(K5="","",IF(K5>1095,"Vencido",IF(K5>910,"Alerta",IF(K5>820,"Alerta",IF(K5>730,"Alerta",IF(K5>=0,"Em dia","Vencido")))))) -> Em dia | K5: =$K$4-G5 -> 303 | Q5: =H5-$Q$3 -> 793
A6: POL-PMS-002 | B6: Política de Gestão dos Padrões Técnicos | C6: Technical Standards Management Policy | D6: Engenharia Eletromecânica | E6: X | F6: X | G6: 45895 | H6: =G6+1096 -> 46991 | I6: Publicado | J6: =IF(K6="","",IF(K6>1095,"Vencido",IF(K6>910,"Alerta",IF(K6>820,"Alerta",IF(K6>730,"Alerta",IF(K6>=0,"Em dia","Vencido")))))) -> Em dia | K6: =$K$4-G6 -> 303 | Q6: =H6-$Q$3 -> 793
A7: POL-PMS-003 | B7: Procedimento de gestão operacional das UHEs | C7: Operation Management Procedure | D7: Engenharia Eletromecânica | E7: X | F7: X | G7: 43952 | H7: =G7+1096 -> 45048 | I7: Publicado | J7: =IF(K7="","",IF(K7>1095,"Vencido",IF(K7>910,"Alerta",IF(K7>820,"Alerta",IF(K7>730,"Alerta",IF(K7>=0,"Em dia","Vencido")))))) -> Vencido | K7: =$K$4-G7 -> 2246 | Q7: =H7-$Q$3 -> -1150
A8: POL-PMS-004 | B8: Gestão da manutenção e modernização das UHEs | C8: Maintenance and Modernization Management | D8: Engenharia Eletromecânica | E8: X | F8: X | G8: 45202 | H8: =G8+1096 -> 46298 | I8: Publicado | J8: =IF(K8="","",IF(K8>1095,"Vencido",IF(K8>910,"Alerta",IF(K8>820,"Alerta",IF(K8>730,"Alerta",IF(K8>=0,"Em dia","Vencido")))))) -> Alerta | K8: =$K$4-G8 -> 996 | Q8: =H8-$Q$3 -> 100
A9: POL-PMS-005 | B9: Gerenciamento de Saúde e Segurança na Operação e Manutenção | C9: Safe Operation Maintenance Management | D9: Segurança | E9: X | F9: X | G9: 45202 | H9: =G9+1096 -> 46298 | I9: Publicado | J9: =IF(K9="","",IF(K9>1095,"Vencido",IF(K9>910,"Alerta",IF(K9>820,"Alerta",IF(K9>730,"Alerta",IF(K9>=0,"Em dia","Vencido")))))) -> Alerta | K9: =$K$4-G9 -> 996 | Q9: =H9-$Q$3 -> 100
A10: POL-PMS-006 | B10: Investigação de Acidentes e Incidentes | C10: Accidents and Incident Investigation | D10: Engenharia Eletromecânica | I10: Cancelada | J10: =IF(K10="","",IF(K10>1095,"Vencido",IF(K10>910,"Alerta",IF(K10>820,"Alerta",IF(K10>730,"Alerta",IF(K10>=0,"Em dia","Vencido")))))) -> Vencido | K10: =$K$4-G10 -> 46198
A11: POL-PMS-007 | B11: Identificação e Controle de Riscos Ocultos | C11: Hidden Risk Identification Control | D11: Engenharia Eletromecânica | E11: X | F11: X | G11: 45202 | H11: =G11+1096 -> 46298 | I11: Publicado | J11: =IF(K11="","",IF(K11>1095,"Vencido",IF(K11>910,"Alerta",IF(K11>820,"Alerta",IF(K11>730,"Alerta",IF(K11>=0,"Em dia","Vencido")))))) -> Alerta | K11: =$K$4-G11 -> 996 | Q11: =H11-$Q$3 -> 100
A12: POL-PMS-010 | B12: Gestão das alterações de projeto | C12: Management of Design changes | D12: Engenharia Eletromecânica | E12: X | F12: X | G12: 45202 | H12: =G12+1096 -> 46298 | I12: Publicado | J12: =IF(K12="","",IF(K12>1095,"Vencido",IF(K12>910,"Alerta",IF(K12>820,"Alerta",IF(K12>730,"Alerta",IF(K12>=0,"Em dia","Vencido")))))) -> Alerta | K12: =$K$4-G12 -> 996 | Q12: =H12-$Q$3 -> 100
A13: POL-PMS-011 | B13: Política de Gestão da Calibração dos instrumentos | C13: Instruments Calibration Management Policy | D13: Engenharia Eletromecânica | E13: X | F13: X | G13: 43983 | H13: =G13+1096 -> 45079 | I13: Publicado | J13: =IF(K13="","",IF(K13>1095,"Vencido",IF(K13>910,"Alerta",IF(K13>820,"Alerta",IF(K13>730,"Alerta",IF(K13>=0,"Em dia","Vencido")))))) -> Vencido | K13: =$K$4-G13 -> 2215 | Q13: =H13-$Q$3 -> -1119
A14: POL-PMS-012 | B14: Política de Segurança Cibernética para o Ambiente SCADA | C14: Cybersecurity Policy for the Scada Environment | D14: Engenharia Eletromecânica | E14: X | F14: X | G14: 44187 | H14: =G14+1096 -> 45283 | I14: Publicado | J14: =IF(K14="","",IF(K14>1095,"Vencido",IF(K14>910,"Alerta",IF(K14>820,"Alerta",IF(K14>730,"Alerta",IF(K14>=0,"Em dia","Vencido")))))) -> Vencido | K14: =$K$4-G14 -> 2011 | Q14: =H14-$Q$3 -> -915
A15: POL-PMS-014 | B15: Gerenciamento de Projetos da Engenharia | C15: Engineering Projects Management | D15: Engenharia CAPEX | E15: X | F15: X | G15: 45686 | H15: =G15+1096 -> 46782 | I15: Publicado | J15: =IF(K15="","",IF(K15>1095,"Vencido",IF(K15>910,"Alerta",IF(K15>820,"Alerta",IF(K15>730,"Alerta",IF(K15>=0,"Em dia","Vencido")))))) -> Em dia | K15: =$K$4-G15 -> 512 | P15: =G15+1080 -> 46766 | Q15: =H15-$Q$3 -> 584
A16: POL-PMS-015 | B16: Gestão de Mudanças de Escopo em Projetos de Engenharia | C16: Scope Changes Management for Engineering Projects | D16: Engenharia CAPEX | E16: X | F16: X | G16: 45686 | H16: =G16+1096 -> 46782 | I16: Publicado | J16: =IF(K16="","",IF(K16>1095,"Vencido",IF(K16>910,"Alerta",IF(K16>820,"Alerta",IF(K16>730,"Alerta",IF(K16>=0,"Em dia","Vencido")))))) -> Em dia | K16: =$K$4-G16 -> 512 | P16: =G16+1080 -> 46766 | Q16: =H16-$Q$3 -> 584
A17: POL-PMS-016 | B17: Comissionamento e Entrega de Ativos | C17: Commissioning and Assets Handover | D17: Engenharia CAPEX | E17: X | F17: X | G17: 45686 | H17: =G17+1096 -> 46782 | I17: Publicado | J17: =IF(K17="","",IF(K17>1095,"Vencido",IF(K17>910,"Alerta",IF(K17>820,"Alerta",IF(K17>730,"Alerta",IF(K17>=0,"Em dia","Vencido")))))) -> Em dia | K17: =$K$4-G17 -> 512 | Q17: =H17-$Q$3 -> 584
A18: POL-PMS-017 | B18: Abertura e Encerramento de Projetos | C18: Opening and Closure of Engineering Projects | D18: Engenharia CAPEX | E18: X | F18: X | G18: 45686 | H18: =G18+1096 -> 46782 | I18: Publicado | J18: =IF(K18="","",IF(K18>1095,"Vencido",IF(K18>910,"Alerta",IF(K18>820,"Alerta",IF(K18>730,"Alerta",IF(K18>=0,"Em dia","Vencido")))))) -> Em dia | K18: =$K$4-G18 -> 512 | P18: =G18+1080 -> 46766 | Q18: =H18-$Q$3 -> 584
A19: POL-PMS-018 | B19: Gestão de Riscos dos Projetos da Engenharia | C19: Engineering Project Risk Management – | D19: Engenharia CAPEX | E19: X | F19: X | G19: 45686 | H19: =G19+1096 -> 46782 | I19: Publicado | J19: =IF(K19="","",IF(K19>1095,"Vencido",IF(K19>910,"Alerta",IF(K19>820,"Alerta",IF(K19>730,"Alerta",IF(K19>=0,"Em dia","Vencido")))))) -> Em dia | K19: =$K$4-G19 -> 512 | P19: =G19+1080 -> 46766 | Q19: =H19-$Q$3 -> 584
A20: POL-PMS-019 | B20: Lições Aprendidas – Projetos da Engenharia | C20: Lessons Learned – Engineering projects | D20: Engenharia CAPEX | E20: X | F20: X | G20: 45686 | H20: =G20+1096 -> 46782 | I20: Publicado | J20: =IF(K20="","",IF(K20>1095,"Vencido",IF(K20>910,"Alerta",IF(K20>820,"Alerta",IF(K20>730,"Alerta",IF(K20>=0,"Em dia","Vencido")))))) -> Em dia | K20: =$K$4-G20 -> 512 | P20: =G20+1080 -> 46766 | Q20: =H20-$Q$3 -> 584
A21: POL-PMS-020 | B21: Monitoramento e Controle de Cronogramas de Projetos de Engenharia | C21: Monitoring and Control of Project Schedules | D21: Engenharia CAPEX | E21: X | F21: X | I21: Cancelada | J21: =IF(K21="","",IF(K21>1095,"Vencido",IF(K21>910,"Alerta",IF(K21>820,"Alerta",IF(K21>730,"Alerta",IF(K21>=0,"Em dia","Vencido")))))) -> Vencido | K21: =$K$4-G21 -> 46198 | P21: =G21+1080 -> 1080
A22: POL-PMS-021 | B22: Politica de Gestão Orçamentária de Projetos CAPEX da Engenharia | C22: Engineering Capex Project Budget Management Policy | D22: Engenharia CAPEX | E22: X | F22: X | G22: 45769 | H22: =G22+1096 -> 46865 | I22: Publicado | J22: =IF(K22="","",IF(K22>1095,"Vencido",IF(K22>910,"Alerta",IF(K22>820,"Alerta",IF(K22>730,"Alerta",IF(K22>=0,"Em dia","Vencido")))))) -> Em dia | K22: =$K$4-G22 -> 429 | P22: =G22+1080 -> 46849 | Q22: =H22-$Q$3 -> 667
A23: PRD-SST-004 | B23: Gestão Equipamento e Ferramentas de Segurança | C23: Equipment Safety and Safety Tools Management | D23: Segurança | E23: X | F23: X | G23: 45274 | H23: =G23+1096 -> 46370 | I23: Publicado | J23: =IF(K23="","",IF(K23>1095,"Vencido",IF(K23>910,"Alerta",IF(K23>820,"Alerta",IF(K23>730,"Alerta",IF(K23>=0,"Em dia","Vencido")))))) -> Alerta | K23: =$K$4-G23 -> 924 | P23: =G23+1080 -> 46354 | Q23: =H23-$Q$3 -> 172
A24: PRD-SST-005 | B24: Cód de Gerenciamento de Despesas de Saúde e Segurança | C24: Expenses Management Code HSE | D24: Segurança | E24: X | F24: X | G24: 45379 | H24: =G24+1096 -> 46475 | I24: Publicado | J24: =IF(K24="","",IF(K24>1095,"Vencido",IF(K24>910,"Alerta",IF(K24>820,"Alerta",IF(K24>730,"Alerta",IF(K24>=0,"Em dia","Vencido")))))) -> Alerta | K24: =$K$4-G24 -> 819 | P24: =G24+1080 -> 46459 | Q24: =H24-$Q$3 -> 277

Sheet IM
B2: IM - INSTRUÇÕES DE MANUTENÇÃO (MAINTENANCE INSTRUCTIONS)
G3: =COUNTIF(G4:G300,"X") -> 90 | H3: =COUNTIF(H4:H300,"X") -> 40 | S3: =TODAY() -> 46198
B4: TIPO/TYPE | C4: NUMERO / NUMBER | D4: DESCRIÇÃO | E4: DESCRIPTION | F4: ÁREA | G4: Por. | H4: Ing. | I4: Data aprovação | J4: Data Vencimento | K4: Status | L4: Status data | M4: Revisão/Novo | N4: =TODAY() -> 46198 | S4: Dias que falta para vencer
B5: Instruções Manutenção Normativas e Gerenciais | C5: IM-ENG-001 | D5: Diretrizes da Manutenção | E5: Maintenance Guidelines | F5: ENGENHARIA CONFIABILIDADE E PERFORMANCE | G5: X | H5: X | I5: 45595 | J5: =I5+1096 -> 46691 | K5: Publicado | L5: =IF(N5="","",IF(N5>1095,"Vencido",IF(N5>910,"Alerta",IF(N5>820,"Alerta",IF(N5>730,"Alerta",IF(N5>=0,"Em dia","Vencido")))))) -> Em dia | N5: =$N$4-I5 -> 603 | S5: =J5-$S$3 -> 493
B6: Instruções Manutenção Normativas e Gerenciais | C6: IM-ENG-002 | D6: Instrução Treinam Tec Prod Eletric e Mec | E6: Training policy for electrical and mechanical technicians | F6: ENGENHARIA CONFIABILIDADE E PERFORMANCE | G6: X | I6: 45202 | J6: =I6+1096 -> 46298 | K6: Publicado | L6: =IF(N6="","",IF(N6>1095,"Vencido",IF(N6>910,"Alerta",IF(N6>820,"Alerta",IF(N6>730,"Alerta",IF(N6>=0,"Em dia","Vencido")))))) -> Alerta | N6: =$N$4-I6 -> 996 | S6: =J6-$S$3 -> 100
B7: Instruções Manutenção Normativas e Gerenciais | C7: IM-ENG-003 | D7: Procedimento analise e comunic deslig. forçado UG | E7: Procedure for analyzing and reporting forced outages | F7: ENGENHARIA CONFIABILIDADE E PERFORMANCE | G7: X | H7: X | I7: 45895 | J7: =I7+1096 -> 46991 | K7: Publicado | L7: =IF(N7="","",IF(N7>1095,"Vencido",IF(N7>910,"Alerta",IF(N7>820,"Aviso",IF(N7>730,"Comunicado",IF(N7>=0,"Em dia","Vencido")))))) -> Em dia | N7: =$N$4-I7 -> 303 | S7: =J7-$S$3 -> 793
B8: Instruções Manutenção Elétrica | C8: IM-ENG-004 | D8: Medição de Aterramento | E8: Procedure for inspection of ligthning arrester and grounding systems | F8: ENGENHARIA ELÉTRICA | G8: X | I8: 45202 | J8: =I8+1096 -> 46298 | K8: Publicado | L8: =IF(N8="","",IF(N8>1095,"Vencido",IF(N8>910,"Alerta",IF(N8>820,"Alerta",IF(N8>730,"Alerta",IF(N8>=0,"Em dia","Vencido")))))) -> Alerta | N8: =$N$4-I8 -> 996 | S8: =J8-$S$3 -> 100
B9: Instruções Manutenção Mecânica | C9: IM-ENG-005 | D9: Vasos de Pressão | E9: Procedure for testing pressure vessels | F9: ENGENHARIA MECÂNICA | G9: X | H9: X | I9: 45895 | J9: =I9+1096 -> 46991 | K9: Publicado | L9: =IF(N9="","",IF(N9>1095,"Vencido",IF(N9>910,"Alerta",IF(N9>820,"Aviso",IF(N9>730,"Comunicado",IF(N9>=0,"Em dia","Vencido")))))) -> Em dia | N9: =$N$4-I9 -> 303 | S9: =J9-$S$3 -> 793
B10: Instruções Manutenção Normativas e Gerenciais | C10: IM-ENG-006 | D10: Utilização do Maximo 7.6 | E10: Work Order - Quick Reference Manual (MAXIMO®) | F10: ENGENHARIA CONFIABILIDADE E PERFORMANCE | G10: X | H10: X | I10: 45595 | J10: =I10+1096 -> 46691 | K10: Publicado | L10: =IF(N10="","",IF(N10>1095,"Vencido",IF(N10>910,"Alerta",IF(N10>820,"Aviso",IF(N10>730,"Comunicado",IF(N10>=0,"Em dia","Vencido")))))) -> Em dia | N10: =$N$4-I10 -> 603 | S10: =J10-$S$3 -> 493
B11: Instruções Manutenção Mecânica | C11: IM-ENG-007 | D11: Procedimento para recuperar Cavitação | E11: Procedures for recovering Cavitation | F11: ENGENHARIA MECÂNICA | G11: X | H11: X | I11: 44914 | J11: =I11+1096 -> 46010 | K11: Publicado | L11: =IF(N11="","",IF(N11>1095,"Vencido",IF(N11>910,"Alerta",IF(N11>820,"Alerta",IF(N11>730,"Alerta",IF(N11>=0,"Em dia","Vencido")))))) -> Vencido | N11: =$N$4-I11 -> 1284 | S11: =J11-$S$3 -> -188
B12: Instruções Manutenção Elétrica | C12: IM-ENG-008 | D12: Teste de Chama em Reles Buchholz | E12: Procedure to perform Flame Test (relay Buchhoz) | F12: ENGENHARIA ELÉTRICA | G12: X | I12: 45538 | J12: =I12+1096 -> 46634 | K12: Publicado | L12: =IF(N12="","",IF(N12>1095,"Vencido",IF(N12>910,"Alerta",IF(N12>820,"Aviso",IF(N12>730,"Comunicado",IF(N12>=0,"Em dia","Vencido")))))) -> Em dia | N12: =$N$4-I12 -> 660 | S12: =J12-$S$3 -> 436
B13: Instruções Manutenção Elétrica | C13: IM-ENG-009 | D13: Ensaio de Isolação em Geradores e Motores | E13: Insulation Testing in Generators and Engines | F13: ENGENHARIA ELÉTRICA | I13: - | K13: Cancelada | N13: =$N$4-I13 -> #VALUE!
B14: Instruções Manutenção Normativas e Gerenciais | C14: IM-ENG-010 | D14: Procedimento de Impedimento Para Intervenções no Gerador | E14: Procedure to isolate generator during maintenance | F14: ENGENHARIA CONFIABILIDADE E PERFORMANCE | I14: - | K14: Cancelada | N14: =$N$4-I14 -> #VALUE!
B15: Instruções Manutenção Elétrica | C15: IM-ENG-013 | D15: Ensaios de Termovisão | E15: Procedure for Thermovison testings | F15: ENGENHARIA ELÉTRICA | G15: X | H15: X | I15: 45595 | J15: =I15+1096 -> 46691 | K15: Publicado | L15: =IF(N15="","",IF(N15>1095,"Vencido",IF(N15>910,"Alerta",IF(N15>820,"Aviso",IF(N15>730,"Comunicado",IF(N15>=0,"Em dia","Vencido")))))) -> Em dia | N15: =$N$4-I15 -> 603 | S15: =J15-$S$3 -> 493
B16: Instruções Manutenção Normativas e Gerenciais | C16: IM-ENG-014 | D16: Gerenciamento Grandes Manutenções | E16: Procedure for manage major maintenances | F16: ENGENHARIA CONFIABILIDADE E PERFORMANCE | G16: X | I16: 44868 | J16: =I16+1096 -> 45964 | K16: Publicado | L16: =IF(N16="","",IF(N16>1095,"Vencido",IF(N16>910,"Alerta",IF(N16>820,"Alerta",IF(N16>730,"Alerta",IF(N16>=0,"Em dia","Vencido")))))) -> Vencido | N16: =$N$4-I16 -> 1330 | S16: =J16-$S$3 -> -234
B17: Instruções Manutenção Normativas e Gerenciais | C17: IM-ENG-015 | D17: Auditoria Processos OeM | E17: Audit Processes O&M | F17: ENGENHARIA CONFIABILIDADE E PERFORMANCE | G17: X | H17: X | I17: 44631 | J17: =I17+1096 -> 45727 | K17: Publicado | L17: =IF(N17="","",IF(N17>1095,"Vencido",IF(N17>910,"Alerta",IF(N17>820,"Alerta",IF(N17>730,"Alerta",IF(N17>=0,"Em dia","Vencido")))))) -> Vencido | N17: =$N$4-I17 -> 1567 | R17: =I17+1080 -> 45711 | S17: =J17-$S$3 -> -471
B18: Instruções Manutenção Mecânica | C18: IM-ENG-016 | D18: Utilização do Nível Ótico N3 | E18: Use of Optical Level N3 | F18: ENGENHARIA MECÂNICA | G18: X | I18: 45202 | J18: =I18+1096 -> 46298 | K18: Publicado | L18: =IF(N18="","",IF(N18>1095,"Vencido",IF(N18>910,"Alerta",IF(N18>820,"Alerta",IF(N18>730,"Alerta",IF(N18>=0,"Em dia","Vencido")))))) -> Alerta | N18: =$N$4-I18 -> 996 | S18: =J18-$S$3 -> 100
B19: Instruções Manutenção Elétrica | C19: IM-ENG-017 | D19: Coleta e Análise de Óleo Isolante | E19: Procedures to take sample of isolating oil | F19: ENGENHARIA ELÉTRICA | G19: X | H19: X | I19: 45743 | J19: =I19+1096 -> 46839 | K19: Publicado | L19: =IF(N19="","",IF(N19>1095,"Vencido",IF(N19>910,"Alerta",IF(N19>820,"Aviso",IF(N19>730,"Comunicado",IF(N19>=0,"Em dia","Vencido")))))) -> Em dia | N19: =$N$4-I19 -> 455 | S19: =J19-$S$3 -> 641
B20: Instruções Manutenção Mecânica | C20: IM-ENG-018 | D20: Monitoramento e tratam oleo lubrific | E20: Lubrication Oil Condition Monitoring | F20: ENGENHARIA MECÂNICA | G20: X | H20: x | I20: 45895 | J20: =I20+1096 -> 46991 | K20: Publicado | L20: =IF(N20="","",IF(N20>1095,"Vencido",IF(N20>910,"Alerta",IF(N20>820,"Aviso",IF(N20>730,"Comunicado",IF(N20>=0,"Em dia","Vencido")))))) -> Em dia | N20: =$N$4-I20 -> 303 | S20: =J20-$S$3 -> 793
B21: Instruções Manutenção Elétrica | C21: IM-ENG-019 | D21: Conjunto de Aterramento Temporário para Manutenção | E21: Temporary grounding set for maintenance | F21: ENGENHARIA ELÉTRICA | G21: X | H21: X | I21: 45462 | J21: =I21+1096 -> 46558 | K21: Publicado | L21: =IF(N21="","",IF(N21>1095,"Vencido",IF(N21>910,"Alerta",IF(N21>820,"Aviso",IF(N21>730,"Comunicado",IF(N21>=0,"Em dia","Vencido")))))) -> Comunicado | N21: =$N$4-I21 -> 736 | R21: =I21+1080 -> 46542 | S21: =J21-$S$3 -> 360
B22: Instruções Manutenção Normativas e Gerenciais | C22: IM-ENG-020 | D22: Manutenções Preventivas Periódicas 0 | E22: Periodic Preventive Maintenance type 0 | F22: ENGENHARIA CONFIABILIDADE E PERFORMANCE | G22: X | I22: 44868 | J22: =I22+1096 -> 45964 | K22: Publicado | L22: =IF(N22="","",IF(N22>1095,"Vencido",IF(N22>910,"Alerta",IF(N22>820,"Alerta",IF(N22>730,"Alerta",IF(N22>=0,"Em dia","Vencido")))))) -> Vencido | N22: =$N$4-I22 -> 1330 | S22: =J22-$S$3 -> -234
B23: Instruções Manutenção Normativas e Gerenciais | C23: IM-ENG-021 | D23: Manutenções Preventivas Periódicas 1 | E23: Periodic Preventive Maintenance type 1 | F23: ENGENHARIA CONFIABILIDADE E PERFORMANCE | G23: X | I23: 44868 | J23: =I23+1096 -> 45964 | K23: Publicado | L23: =IF(N23="","",IF(N23>1095,"Vencido",IF(N23>910,"Alerta",IF(N23>820,"Alerta",IF(N23>730,"Alerta",IF(N23>=0,"Em dia","Vencido")))))) -> Vencido | N23: =$N$4-I23 -> 1330 | S23: =J23-$S$3 -> -234
B24: Instruções Manutenção Normativas e Gerenciais | C24: IM-ENG-022 | D24: Manutenções Preventivas Periódicas 2 | E24: Periodic Preventive Maintenance type 2 | F24: ENGENHARIA CONFIABILIDADE E PERFORMANCE | G24: X | I24: 44868 | J24: =I24+1096 -> 45964 | K24: Publicado | L24: =IF(N24="","",IF(N24>1095,"Vencido",IF(N24>910,"Alerta",IF(N24>820,"Alerta",IF(N24>730,"Alerta",IF(N24>=0,"Em dia","Vencido")))))) -> Vencido | N24: =$N$4-I24 -> 1330 | S24: =J24-$S$3 -> -234
B25: Instruções Manutenção Mecânica | C25: IM-ENG-023 | D25: Sistema de Ar Comprimido | E25: Procedures for maintenance air compressed equipments | F25: ENGENHARIA MECÂNICA | G25: X | I25: 45202 | J25: =I25+1096 -> 46298 | K25: Publicado | L25: =IF(N25="","",IF(N25>1095,"Vencido",IF(N25>910,"Alerta",IF(N25>820,"Alerta",IF(N25>730,"Alerta",IF(N25>=0,"Em dia","Vencido")))))) -> Alerta | N25: =$N$4-I25 -> 996 | S25: =J25-$S$3 -> 100
B26: Instruções Manutenção Elétrica | C26: IM-ENG-026 | D26: Formulário com Medidas de Segurança | E26: Safety risk control measures | F26: ENGENHARIA ELÉTRICA | G26: X | H26: X | I26: 45462 | J26: =I26+1096 -> 46558 | K26: Publicado | L26: =IF(N26="","",IF(N26>1095,"Vencido",IF(N26>910,"Alerta",IF(N26>820,"Aviso",IF(N26>730,"Comunicado",IF(N26>=0,"Em dia","Vencido")))))) -> Comunicado | N26: =$N$4-I26 -> 736 | R26: =I26+1080 -> 46542 | S26: =J26-$S$3 -> 360
B27: Instruções Manutenção Normativas e Gerenciais | C27: IM-ENG-028 | D27: Procedimento para alteração de set points parâmetros e ordem de ajustes | E27: Procedure for changing set points, parameters and order of adjustments | F27: ENGENHARIA CONFIABILIDADE E PERFORMANCE | G27: X | H27: X | I27: 45202 | J27: =I27+1096 -> 46298 | K27: Publicado | L27: =IF(N27="","",IF(N27>1095,"Vencido",IF(N27>910,"Alerta",IF(N27>820,"Alerta",IF(N27>730,"Alerta",IF(N27>=0,"Em dia","Vencido")))))) -> Alerta | N27: =$N$4-I27 -> 996 | S27: =J27-$S$3 -> 100
B28: Instruções Manutenção Mecânica | C28: IM-ENG-030 | D28: Dispositivos de Içamento | E28: Procedures for the use of lifting accessories | F28: ENGENHARIA MECÂNICA | G28: X | I28: 45202 | J28: =I28+1096 -> 46298 | K28: Publicado | L28: =IF(N28="","",IF(N28>1095,"Vencido",IF(N28>910,"Alerta",IF(N28>820,"Alerta",IF(N28>730,"Alerta",IF(N28>=0,"Em dia","Vencido")))))) -> Alerta | N28: =$N$4-I28 -> 996 | S28: =J28-$S$3 -> 100
B29: Instruções Manutenção Elétrica | C29: IM-ENG-031 | D29: Ensaios em Alto Potencial | E29: Procedures to perform high potencial tests | F29: ENGENHARIA ELÉTRICA | I29: - | K29: Cancelada | N29: =$N$4-I29 -> #VALUE!
B30: Instruções Manutenção Mecânica | C30: IM-ENG-032 | D30: Ensaios com Ultra-Som | E30: Procedures for Ultrasoud tests | F30: ENGENHARIA MECÂNICA | G30: X | I30: 45202 | J30: =I30+1096 -> 46298 | K30: Publicado | L30: =IF(N30="","",IF(N30>1095,"Vencido",IF(N30>910,"Alerta",IF(N30>820,"Alerta",IF(N30>730,"Alerta",IF(N30>=0,"Em dia","Vencido")))))) -> Alerta | N30: =$N$4-I30 -> 996 | S30: =J30-$S$3 -> 100
B31: Instruções Manutenção Elétrica | C31: IM-ENG-033 | D31: Ensaio de Corona Visual em Enrolamentos Estatóricos | E31: Visual Corona Testing on Stator Windings | F31: ENGENHARIA ELÉTRICA | G31: X | H31: x | I31: 46107 | J31: =I31+1096 -> 47203 | K31: Publicado | L31: =IF(N31="","",IF(N31>1095,"Vencido",IF(N31>910,"Alerta",IF(N31>820,"Aviso",IF(N31>730,"Comunicado",IF(N31>=0,"Em dia","Vencido")))))) -> Em dia | N31: =$N$4-I31 -> 91 | R31: =I31+1080 -> 47187 | S31: =J31-$S$3 -> 1005
B32: Instruções Manutenção Elétrica | C32: IM-ENG-034 | D32: Ensaios de Rendimento em Geradores Síncronos | E32: Performance tests on synchronous generators | F32: ENGENHARIA ELÉTRICA | G32: X | H32: X | I32: 45202 | J32: =I32+1096 -> 46298 | K32: Publicado | L32: =IF(N32="","",IF(N32>1095,"Vencido",IF(N32>910,"Alerta",IF(N32>820,"Alerta",IF(N32>730,"Alerta",IF(N32>=0,"Em dia","Vencido")))))) -> Alerta | N32: =$N$4-I32 -> 996 | S32: =J32-$S$3 -> 100
B33: Instruções Manutenção Elétrica | C33: IM-ENG-035 | D33: Ensaios de fator de potência em hidrogerador | E33: Power Factor Test in Hydro Generators | F33: ENGENHARIA ELÉTRICA | G33: X | I33: 45274 | J33: =I33+1096 -> 46370 | K33: Publicado | L33: =IF(N33="","",IF(N33>1095,"Vencido",IF(N33>910,"Alerta",IF(N33>820,"Alerta",IF(N33>730,"Alerta",IF(N33>=0,"Em dia","Vencido")))))) -> Alerta | N33: =$N$4-I33 -> 924 | S33: =J33-$S$3 -> 172
B34: Instruções Manutenção Elétrica | C34: IM-ENG-036 | D34: Ensaios e Verificações em Disjuntores | E34: Maintenance tests on H. V. circuit breaker | F34: ENGENHARIA ELÉTRICA | G34: X | I34: 45538 | J34: =I34+1096 -> 46634 | K34: Publicado | L34: =IF(N34="","",IF(N34>1095,"Vencido",IF(N34>910,"Alerta",IF(N34>820,"Aviso",IF(N34>730,"Comunicado",IF(N34>=0,"Em dia","Vencido")))))) -> Em dia | N34: =$N$4-I34 -> 660 | R34: =I34+1080 -> 46618 | S34: =J34-$S$3 -> 436
B35: Instruções Manutenção Elétrica | C35: IM-ENG-037 | D35: Pequenos reparos em geradores hidráulicos | E35: Minor repairs on hydraulic generators | F35: ENGENHARIA ELÉTRICA | G35: X | H35: X | I35: 45839 | J35: =I35+1096 -> 46935 | K35: Publicado | L35: =IF(N35="","",IF(N35>1095,"Vencido",IF(N35>910,"Alerta",IF(N35>820,"Aviso",IF(N35>730,"Comunicado",IF(N35>=0,"Em dia","Vencido")))))) -> Em dia | N35: =$N$4-I35 -> 359 | S35: =J35-$S$3 -> 737
B36: Instruções Manutenção Normativas e Gerenciais | C36: IM-ENG-038.1 | D36: Diagramas de padrões técnicos | E36: Diagrams of technical standard system | F36: ENGENHARIA CONFIABILIDADE E PERFORMANCE | G36: X | H36: X | I36: 45595 | J36: =I36+1096 -> 46691 | K36: Publicado | L36: =IF(N36="","",IF(N36>1095,"Vencido",IF(N36>910,"Alerta",IF(N36>820,"Aviso",IF(N36>730,"Comunicado",IF(N36>=0,"Em dia","Vencido")))))) -> Em dia | N36: =$N$4-I36 -> 603 | S36: =J36-$S$3 -> 493
B37: Instruções Manutenção Normativas e Gerenciais | C37: IM-ENG-038.2 | D37: Princípios e regras para elaboração de padrões técnicos | E37: Principles and rules for developing technical standards | F37: ENGENHARIA CONFIABILIDADE E PERFORMANCE | G37: X | H37: X | I37: 45595 | J37: =I37+1096 -> 46691 | K37: Publicado | L37: =IF(N37="","",IF(N37>1095,"Vencido",IF(N37>910,"Alerta",IF(N37>820,"Aviso",IF(N37>730,"Comunicado",IF(N37>=0,"Em dia","Vencido")))))) -> Em dia | N37: =$N$4-I37 -> 603 | S37: =J37-$S$3 -> 493
B38: Instruções Manutenção Normativas e Gerenciais | C38: IM-ENG-038.3 | D38: Padrões técnicos no nivel das UHEs | E38: Site level technical standards | F38: ENGENHARIA CONFIABILIDADE E PERFORMANCE | G38: X | H38: X | I38: 45595 | J38: =I38+1096 -> 46691 | K38: Publicado | L38: =IF(N38="","",IF(N38>1095,"Vencido",IF(N38>910,"Alerta",IF(N38>820,"Aviso",IF(N38>730,"Comunicado",IF(N38>=0,"Em dia","Vencido")))))) -> Em dia | N38: =$N$4-I38 -> 603 | S38: =J38-$S$3 -> 493
B39: Instruções Manutenção Normativas e Gerenciais | C39: IM-ENG-038.4 | D39: Procedimento Geração doc adm, relatórios e desenhos téc | E39: Generating technical reports and administrative documents | F39: ENGENHARIA CONFIABILIDADE E PERFORMANCE | G39: X | H39: X | I39: 45595 | J39: =I39+1096 -> 46691 | K39: Publicado | L39: =IF(N39="","",IF(N39>1095,"Vencido",IF(N39>910,"Alerta",IF(N39>820,"Aviso",IF(N39>730,"Comunicado",IF(N39>=0,"Em dia","Vencido")))))) -> Em dia | N39: =$N$4-I39 -> 603 | S39: =J39-$S$3 -> 493
B40: Instruções Manutenção Normativas e Gerenciais | C40: IM-ENG-038.5 | D40: Procedimento para arquivamento de documentos digitais | E40: Archiving Technical documents | F40: ENGENHARIA CONFIABILIDADE E PERFORMANCE | G40: X | H40: X | I40: 45595 | J40: =I40+1096 -> 46691 | K40: Publicado | L40: =IF(N40="","",IF(N40>1095,"Vencido",IF(N40>910,"Alerta",IF(N40>820,"Aviso",IF(N40>730,"Comunicado",IF(N40>=0,"Em dia","Vencido")))))) -> Em dia | N40: =$N$4-I40 -> 603 | S40: =J40-$S$3 -> 493
B41: Instruções Manutenção Elétrica | C41: IM-ENG-042 | D41: Manut Conexões Flex aparafusadas barram media tensão | E41: Maintenance of flexible power shunts installed in Medium Voltage | F41: ENGENHARIA ELÉTRICA | I41: - | K41: Cancelada | N41: =$N$4-I41 -> #VALUE!
B42: Instruções Manutenção Elétrica | C42: IM-ENG-043 | D42: Manutenção de Cabos de Alta Tensão Isolados a Óleo | E42: Maintenance of Oil Insulated High Voltage Cables | F42: ENGENHARIA ELÉTRICA | I42: - | K42: Cancelada | N42: =$N$4-I42 -> #VALUE!
B43: Instruções Manutenção Mecânica | C43: IM-ENG-046 | D43: Inspeção e Reparos em Trincas de Pás dos Hidrogeradores | E43: Procedures for inspect and repair cracks in wicket gates and turbine blades | F43: ENGENHARIA MECÂNICA | G43: X | I43: 45202 | J43: =I43+1096 -> 46298 | K43: Publicado | L43: =IF(N43="","",IF(N43>1095,"Vencido",IF(N43>910,"Alerta",IF(N43>820,"Alerta",IF(N43>730,"Alerta",IF(N43>=0,"Em dia","Vencido")))))) -> Alerta | N43: =$N$4-I43 -> 996 | S43: =J43-$S$3 -> 100
B44: Instruções Manutenção Elétrica | C44: IM-ENG-047 | D44: Manutenção, Ensaios, Transporte e Armazenagem de Buchas | E44: Medium and High Voltage Bushings - Maintenance, tests, transport and storage | F44: ENGENHARIA ELÉTRICA | G44: X | I44: 45202 | J44: =I44+1096 -> 46298 | K44: Publicado | L44: =IF(N44="","",IF(N44>1095,"Vencido",IF(N44>910,"Alerta",IF(N44>820,"Alerta",IF(N44>730,"Alerta",IF(N44>=0,"Em dia","Vencido")))))) -> Alerta | N44: =$N$4-I44 -> 996 | S44: =J44-$S$3 -> 100
B45: Instruções Manutenção Elétrica | C45: IM-ENG-048 | D45: Recepção, Inspeção e Armazenamento de Equipamentos de Alta Tensão | E45: Reception, Inspection and Storage of High Voltage Equipments | F45: ENGENHARIA ELÉTRICA | G45: X | I45: 45274 | J45: =I45+1096 -> 46370 | K45: Publicado | L45: =IF(N45="","",IF(N45>1095,"Vencido",IF(N45>910,"Alerta",IF(N45>820,"Alerta",IF(N45>730,"Alerta",IF(N45>=0,"Em dia","Vencido")))))) -> Alerta | N45: =$N$4-I45 -> 924 | S45: =J45-$S$3 -> 172
B46: Instruções Manutenção Mecânica | C46: IM-ENG-050 | D46: Grupo Diesel de Emergência | E46: Procedures for Maintenance of Emergency Diesel Generator | F46: ENGENHARIA MECÂNICA | G46: X | I46: 45202 | J46: =I46+1096 -> 46298 | K46: Publicado | L46: =IF(N46="","",IF(N46>1095,"Vencido",IF(N46>910,"Alerta",IF(N46>820,"Alerta",IF(N46>730,"Alerta",IF(N46>=0,"Em dia","Vencido")))))) -> Alerta | N46: =$N$4-I46 -> 996 | S46: =J46-$S$3 -> 100
B47: Instruções Manutenção Mecânica | C47: IM-ENG-051 | D47: Controle de Mexilhão Dourado | E47: Golden Mussel Control | F47: ENGENHARIA MECÂNICA | G47: X | I47: 45202 | J47: =I47+1096 -> 46298 | K47: Publicado | L47: =IF(N47="","",IF(N47>1095,"Vencido",IF(N47>910,"Alerta",IF(N47>820,"Alerta",IF(N47>730,"Alerta",IF(N47>=0,"Em dia","Vencido")))))) -> Alerta | N47: =$N$4-I47 -> 996 | S47: =J47-$S$3 -> 100
B48: Instruções Manutenção Elétrica | C48: IM-ENG-053 | D48: Ensaio de Isolação de Equipamentos | E48: Equipment Insulation Tests | F48: ENGENHARIA ELÉTRICA | G48: X | H48: X | I48: 45538 | J48: =I48+1096 -> 46634 | K48: Publicado | L48: =IF(N48="","",IF(N48>1095,"Vencido",IF(N48>910,"Alerta",IF(N48>820,"Aviso",IF(N48>730,"Comunicado",IF(N48>=0,"Em dia","Vencido")))))) -> Em dia | N48: =$N$4-I48 -> 660 | R48: =I48+1080 -> 46618 | S48: =J48-$S$3 -> 436
B49: Instruções Manutenção Elétrica | C49: IM-ENG-054 | D49: Fator Potência e Medida de Capacitância dos Hidrogeradores | E49: Power Factor and Capacitance Measurement of Hydrogenerators | F49: ENGENHARIA ELÉTRICA | I49: - | K49: Cancelada | N49: =$N$4-I49 -> #VALUE!
B50: Instruções Manutenção Mecânica | C50: IM-ENG-057 | D50: Vedação de Eixo | E50: Shaft Seal | F50: ENGENHARIA MECÂNICA | G50: X | I50: 45202 | J50: =I50+1096 -> 46298 | K50: Publicado | L50: =IF(N50="","",IF(N50>1095,"Vencido",IF(N50>910,"Alerta",IF(N50>820,"Alerta",IF(N50>730,"Alerta",IF(N50>=0,"Em dia","Vencido")))))) -> Alerta | N50: =$N$4-I50 -> 996 | S50: =J50-$S$3 -> 100
B51: Instruções Manutenção Mecânica | C51: IM-ENG-058 | D51: Líquidos Penetrantes | E51: Procedures for Penetrant test | F51: ENGENHARIA MECÂNICA | G51: X | I51: 45202 | J51: =I51+1096 -> 46298 | K51: Publicado | L51: =IF(N51="","",IF(N51>1095,"Vencido",IF(N51>910,"Alerta",IF(N51>820,"Alerta",IF(N51>730,"Alerta",IF(N51>=0,"Em dia","Vencido")))))) -> Alerta | N51: =$N$4-I51 -> 996 | S51: =J51-$S$3 -> 100
B52: Instruções Manutenção Elétrica | C52: IM-ENG-062 | D52: Reguladores De Tensão | E52: Voltage Regulators | F52: ENGENHARIA ELÉTRICA | I52: - | K52: Cancelada | N52: =$N$4-I52 -> #VALUE!
B53: Instruções Manutenção Elétrica | C53: IM-ENG-063 | D53: Ensaio no Sistema de Excitação | E53: Excitation System Test | F53: ENGENHARIA ELÉTRICA | I53: - | K53: Cancelada | N53: =$N$4-I53 -> #VALUE!
B54: Instruções Manutenção Normativas e Gerenciais | C54: IM-ENG-064 | D54: Sistema Preditivo de Coletas Online e Offline | E54: Procedures for use the online predictive system (MDM) | F54: ENGENHARIA CONFIABILIDADE E PERFORMANCE | G54: X | I54: 45202 | J54: =I54+1096 -> 46298 | K54: Publicado | L54: =IF(N54="","",IF(N54>1095,"Vencido",IF(N54>910,"Alerta",IF(N54>820,"Alerta",IF(N54>730,"Alerta",IF(N54>=0,"Em dia","Vencido")))))) -> Alerta | N54: =$N$4-I54 -> 996 | S54: =J54-$S$3 -> 100
B55: Instruções Manutenção Elétrica | C55: IM-ENG-065 | D55: Ensaios em equipamentos elétricos CA | E55: Tests on AC Electrical Equipment | F55: ENGENHARIA ELÉTRICA | G55: X | H55: X | I55: 45538 | J55: =I55+1096 -> 46634 | K55: Publicado | L55: =IF(N55="","",IF(N55>1095,"Vencido",IF(N55>910,"Alerta",IF(N55>820,"Aviso",IF(N55>730,"Comunicado",IF(N55>=0,"Em dia","Vencido")))))) -> Em dia | N55: =$N$4-I55 -> 660 | R55: =I55+1080 -> 46618 | S55: =J55-$S$3 -> 436
B56: Instruções Manutenção Elétrica | C56: IM-ENG-069 | D56: Ensaios em Transformadores de Potencial | E56: Potential Transformer Testings | F56: ENGENHARIA ELÉTRICA | G56: X | I56: 45538 | J56: =I56+1096 -> 46634 | K56: Publicado | L56: =IF(N56="","",IF(N56>1095,"Vencido",IF(N56>910,"Alerta",IF(N56>820,"Aviso",IF(N56>730,"Comunicado",IF(N56>=0,"Em dia","Vencido")))))) -> Em dia | N56: =$N$4-I56 -> 660 | R56: =I56+1080 -> 46618 | S56: =J56-$S$3 -> 436
B57: Instruções Manutenção Elétrica | C57: IM-ENG-070 | D57: Manutenção Preventiva de Retificadores e Baterias Ventiladas | E57: Procedure for maintenance of rectifiers and vented batteries | F57: ENGENHARIA ELÉTRICA | G57: X | I57: 45202 | J57: =I57+1096 -> 46298 | K57: Publicado | L57: =IF(N57="","",IF(N57>1095,"Vencido",IF(N57>910,"Alerta",IF(N57>820,"Alerta",IF(N57>730,"Alerta",IF(N57>=0,"Em dia","Vencido")))))) -> Alerta | N57: =$N$4-I57 -> 996 | S57: =J57-$S$3 -> 100
B58: Instruções Manutenção Elétrica | C58: IM-ENG-071 | D58: Manutenção Preventiva de Retificadores e Baterias Seladas | E58: Procedure for maintenance of rectifiers and sealed batteries | F58: ENGENHARIA ELÉTRICA | G58: X | I58: 45202 | J58: =I58+1096 -> 46298 | K58: Publicado | L58: =IF(N58="","",IF(N58>1095,"Vencido",IF(N58>910,"Alerta",IF(N58>820,"Alerta",IF(N58>730,"Alerta",IF(N58>=0,"Em dia","Vencido")))))) -> Alerta | N58: =$N$4-I58 -> 996 | S58: =J58-$S$3 -> 100
B59: Instruções Manutenção Mecânica | C59: IM-ENG-072 | D59: Proteção Anticorrosiva Equip Eletrom Usinas, Eclusas e SE | E59: Anticorrosive Protection Equip Eletrom Plants, Locks and SE | F59: ENGENHARIA MECÂNICA | G59: X | I59: 45202 | J59: =I59+1096 -> 46298 | K59: Publicado | L59: =IF(N59="","",IF(N59>1095,"Vencido",IF(N59>910,"Alerta",IF(N59>820,"Alerta",IF(N59>730,"Alerta",IF(N59>=0,"Em dia","Vencido")))))) -> Alerta | N59: =$N$4-I59 -> 996 | S59: =J59-$S$3 -> 100
B60: Instruções Manutenção Mecânica | C60: IM-ENG-074 | D60: Medição de Vazão | E60: Flow Measurement | F60: ENGENHARIA MECÂNICA | G60: X | I60: 45202 | J60: =I60+1096 -> 46298 | K60: Publicado | L60: =IF(N60="","",IF(N60>1095,"Vencido",IF(N60>910,"Alerta",IF(N60>820,"Alerta",IF(N60>730,"Alerta",IF(N60>=0,"Em dia","Vencido")))))) -> Alerta | N60: =$N$4-I60 -> 996 | S60: =J60-$S$3 -> 100
B61: Instruções Manutenção Normativas e Gerenciais | C61: IM-ENG-079 | D61: Código de Cores | E61: Equipment color code | F61: ENGENHARIA CONFIABILIDADE E PERFORMANCE | G61: X | I61: 45202 | J61: =I61+1096 -> 46298 | K61: Publicado | L61: =IF(N61="","",IF(N61>1095,"Vencido",IF(N61>910,"Alerta",IF(N61>820,"Alerta",IF(N61>730,"Alerta",IF(N61>=0,"Em dia","Vencido")))))) -> Alerta | N61: =$N$4-I61 -> 996 | S61: =J61-$S$3 -> 100
B62: Instruções Manutenção Mecânica | C62: IM-ENG-080 | D62: Procedimento de Pintura Para Combate ao Mexilhão Dourado | E62: Procedures for apply nonstick painting to control golden mussel | F62: ENGENHARIA MECÂNICA | G62: X | I62: 45202 | J62: =I62+1096 -> 46298 | K62: Publicado | L62: =IF(N62="","",IF(N62>1095,"Vencido",IF(N62>910,"Alerta",IF(N62>820,"Alerta",IF(N62>730,"Alerta",IF(N62>=0,"Em dia","Vencido")))))) -> Alerta | N62: =$N$4-I62 -> 996 | S62: =J62-$S$3 -> 100
B63: Instruções Manutenção Elétrica | C63: IM-ENG-089 | D63: Calibração de Transdutores e Grandezas Elétricas | E63: Procedure for calibration of electrical transducers | F63: ENGENHARIA ELÉTRICA | G63: X | I63: 45202 | J63: =I63+1096 -> 46298 | K63: Publicado | L63: =IF(N63="","",IF(N63>1095,"Vencido",IF(N63>910,"Alerta",IF(N63>820,"Alerta",IF(N63>730,"Alerta",IF(N63>=0,"Em dia","Vencido")))))) -> Alerta | N63: =$N$4-I63 -> 996 | S63: =J63-$S$3 -> 100
B64: Instruções Manutenção Mecânica | C64: IM-ENG-106 | D64: Centragem e Verticalidade | E64: Centering and Verticality of Vertical Generating Unit | F64: ENGENHARIA MECÂNICA | G64: X | I64: 45202 | J64: =I64+1096 -> 46298 | K64: Publicado | L64: =IF(N64="","",IF(N64>1095,"Vencido",IF(N64>910,"Alerta",IF(N64>820,"Alerta",IF(N64>730,"Alerta",IF(N64>=0,"Em dia","Vencido")))))) -> Alerta | N64: =$N$4-I64 -> 996 | S64: =J64-$S$3 -> 100
B65: Instruções Manutenção Elétrica | C65: IM-ENG-109 | D65: Determinação do Kt | E65: Determination of Kt | F65: ENGENHARIA ELÉTRICA | I65: - | K65: Cancelada | N65: =$N$4-I65 -> #VALUE!
B66: Instruções Manutenção Elétrica | C66: IM-ENG-110 | D66: Ensaios em Transformadores Reguladores e Reatores | E66: Procedures for electrical testing (transformers and bushings) | F66: ENGENHARIA ELÉTRICA | G66: X | I66: 45202 | J66: =I66+1096 -> 46298 | K66: Publicado | L66: =IF(N66="","",IF(N66>1095,"Vencido",IF(N66>910,"Alerta",IF(N66>820,"Alerta",IF(N66>730,"Alerta",IF(N66>=0,"Em dia","Vencido")))))) -> Alerta | N66: =$N$4-I66 -> 996 | S66: =J66-$S$3 -> 100
B67: Instruções Manutenção Elétrica | C67: IM-ENG-111 | D67: Concentricidade Circularidade dos Hidrogeradores | E67: Procedure to checkn circularity and concentricity of generators | F67: ENGENHARIA ELÉTRICA | G67: X | I67: 45202 | J67: =I67+1096 -> 46298 | K67: Publicado | L67: =IF(N67="","",IF(N67>1095,"Vencido",IF(N67>910,"Alerta",IF(N67>820,"Alerta",IF(N67>730,"Alerta",IF(N67>=0,"Em dia","Vencido")))))) -> Alerta | N67: =$N$4-I67 -> 996 | S67: =J67-$S$3 -> 100
B68: Instruções Manutenção Elétrica | C68: IM-ENG-125 | D68: Aplicação e manutenção de isoladores e cadeias de isolação | E68: Insulator chain Maintenance procedurte | F68: ENGENHARIA ELÉTRICA | G68: X | I68: 45538 | J68: =I68+1096 -> 46634 | K68: Publicado | L68: =IF(N68="","",IF(N68>1095,"Vencido",IF(N68>910,"Alerta",IF(N68>820,"Aviso",IF(N68>730,"Comunicado",IF(N68>=0,"Em dia","Vencido")))))) -> Em dia | N68: =$N$4-I68 -> 660 | R68: =I68+1080 -> 46618 | S68: =J68-$S$3 -> 436
B69: Instruções Manutenção Elétrica | C69: IM-ENG-140 | D69: Escovas de Carvão – Teoria e Utilização | E69: Carbon Brushes - Theory and maintenance | F69: ENGENHARIA ELÉTRICA | G69: X | H69: X | I69: 45506 | J69: =I69+1096 -> 46602 | K69: Publicado | L69: =IF(N69="","",IF(N69>1095,"Vencido",IF(N69>910,"Alerta",IF(N69>820,"Aviso",IF(N69>730,"Comunicado",IF(N69>=0,"Em dia","Vencido")))))) -> Em dia | N69: =$N$4-I69 -> 692 | R69: =I69+1080 -> 46586 | S69: =J69-$S$3 -> 404
B70: Instruções Manutenção Normativas e Gerenciais | C70: IM-ENG-141 | D70: Sistema de Monitoramento Online para UHEs | E70: Online monitoring system for HPPs | F70: ENGENHARIA CONFIABILIDADE E PERFORMANCE | G70: X | H70: X | I70: 45202 | J70: =I70+1096 -> 46298 | K70: Publicado | L70: =IF(N70="","",IF(N70>1095,"Vencido",IF(N70>910,"Alerta",IF(N70>820,"Alerta",IF(N70>730,"Alerta",IF(N70>=0,"Em dia","Vencido")))))) -> Alerta | N70: =$N$4-I70 -> 996 | S70: =J70-$S$3 -> 100
B71: Instruções Manutenção Mecânica | C71: IM-ENG-142 | D71: Monitoramento de Oscilações do Conjunto Rotativo de Unidades Geradoras | E71: Procedures for monitor generating unit vibration | F71: ENGENHARIA MECÂNICA | G71: X | I71: 45202 | J71: =I71+1096 -> 46298 | K71: Publicado | L71: =IF(N71="","",IF(N71>1095,"Vencido",IF(N71>910,"Alerta",IF(N71>820,"Alerta",IF(N71>730,"Alerta",IF(N71>=0,"Em dia","Vencido")))))) -> Alerta | N71: =$N$4-I71 -> 996 | S71: =J71-$S$3 -> 100
B72: Instruções Manutenção Mecânica | C72: IM-ENG-143 | D72: Análise de oscilação de máquinas usando o sistema MDM | E72: Machine oscillation analysis using the MDM system | F72: ENGENHARIA MECÂNICA | I72: - | K72: Desenvolvimento | N72: =$N$4-I72 -> #VALUE! | S72: =J72-$S$3 -> -46198
B73: Instruções Manutenção Mecânica | C73: IM-ENG-144 | D73: Vibracomp | F73: ENGENHARIA MECÂNICA | I73: - | K73: Desenvolvimento | N73: =$N$4-I73 -> #VALUE! | S73: =J73-$S$3 -> -46198
B74: Instruções Manutenção Mecânica | C74: IM-ENG-145 | D74: Medição do Entreferro do Gerador | E74: Measuring Generator Air Gap | F74: ENGENHARIA MECÂNICA | G74: X | I74: 44866 | J74: =I74+1096 -> 45962 | K74: Publicado | L74: =IF(N74="","",IF(N74>1095,"Vencido",IF(N74>910,"Alerta",IF(N74>820,"Alerta",IF(N74>730,"Alerta",IF(N74>=0,"Em dia","Vencido")))))) -> Vencido | N74: =$N$4-I74 -> 1332 | S74: =J74-$S$3 -> -236
B75: Instruções Manutenção Elétrica | C75: IM-ENG-148 | D75: Critérios de Recunhagem | E75: Procedure to identify loose wedges | F75: ENGENHARIA ELÉTRICA | G75: X | I75: 45538 | J75: =I75+1096 -> 46634 | K75: Publicado | L75: =IF(N75="","",IF(N75>1095,"Vencido",IF(N75>910,"Alerta",IF(N75>820,"Aviso",IF(N75>730,"Comunicado",IF(N75>=0,"Em dia","Vencido")))))) -> Em dia | N75: =$N$4-I75 -> 660 | R75: =I75+1080 -> 46618 | S75: =J75-$S$3 -> 436
B76: Instruções Manutenção Mecânica | C76: IM-ENG-159 | D76: Salvamento de Peixes Rio Paranapanema | E76: Procedures for rescue fishes in generating units (Rio Paranapanema) | F76: ENGENHARIA MECÂNICA | G76: X | I76: 45202 | J76: =I76+1096 -> 46298 | K76: Publicado | L76: =IF(N76="","",IF(N76>1095,"Vencido",IF(N76>910,"Alerta",IF(N76>820,"Alerta",IF(N76>730,"Alerta",IF(N76>=0,"Em dia","Vencido")))))) -> Alerta | N76: =$N$4-I76 -> 996 | S76: =J76-$S$3 -> 100
B77: Instruções Manutenção Mecânica | C77: IM-ENG-159 | D77: Salvamento de Peixes Rio Sapucai Mirim | E77: Procedures for rescue fishes in generating units (Rio Sapucai Mirim) | F77: ENGENHARIA MECÂNICA | G77: X | I77: 45202 | J77: =I77+1096 -> 46298 | K77: Publicado | L77: =IF(N77="","",IF(N77>1095,"Vencido",IF(N77>910,"Alerta",IF(N77>820,"Alerta",IF(N77>730,"Alerta",IF(N77>=0,"Em dia","Vencido")))))) -> Alerta | N77: =$N$4-I77 -> 996 | S77: =J77-$S$3 -> 100
B78: Instruções Manutenção Elétrica | C78: IM-ENG-160 | D78: Determinação da Linha Neutra de Excitatrizes Rotativas | E78: Determination of Neutral Line of Rotary Exciters | F78: ENGENHARIA ELÉTRICA | I78: - | K78: Cancelada | N78: =$N$4-I78 -> #VALUE!
B79: Instruções Manutenção Mecânica | C79: IM-ENG-170 | D79: Ensaios Sobre Metal Patente | E79: Procedures for testing bearing pads (babit) | F79: ENGENHARIA MECÂNICA | G79: X | I79: 45202 | J79: =I79+1096 -> 46298 | K79: Publicado | L79: =IF(N79="","",IF(N79>1095,"Vencido",IF(N79>910,"Alerta",IF(N79>820,"Alerta",IF(N79>730,"Alerta",IF(N79>=0,"Em dia","Vencido")))))) -> Alerta | N79: =$N$4-I79 -> 996 | S79: =J79-$S$3 -> 100
B80: Instruções Manutenção Mecânica | C80: IM-ENG-180 | D80: Manutenção em Trocadores de Calor | E80: Procedures for giving maintenance in heat exchangers | F80: ENGENHARIA MECÂNICA | G80: X | I80: 45202 | J80: =I80+1096 -> 46298 | K80: Publicado | L80: =IF(N80="","",IF(N80>1095,"Vencido",IF(N80>910,"Alerta",IF(N80>820,"Alerta",IF(N80>730,"Alerta",IF(N80>=0,"Em dia","Vencido")))))) -> Alerta | N80: =$N$4-I80 -> 996 | S80: =J80-$S$3 -> 100
B81: Instruções Manutenção Elétrica | C81: IM-ENG-185 | D81: Secagem dos Hidrogeradores | E81: Procedures for drying of generators | F81: ENGENHARIA ELÉTRICA | G81: X | I81: 45538 | J81: =I81+1096 -> 46634 | K81: Publicado | L81: =IF(N81="","",IF(N81>1095,"Vencido",IF(N81>910,"Alerta",IF(N81>820,"Aviso",IF(N81>730,"Comunicado",IF(N81>=0,"Em dia","Vencido")))))) -> Em dia | N81: =$N$4-I81 -> 660 | R81: =I81+1080 -> 46618 | S81: =J81-$S$3 -> 436
B82: Instruções Manutenção Elétrica | C82: IM-ENG-266 | D82: Ensaio em Transformadores de Corrente | E82: Procedures for CT Testings | F82: ENGENHARIA ELÉTRICA | G82: X | I82: 45565 | J82: =I82+1096 -> 46661 | K82: Publicado | L82: =IF(N82="","",IF(N82>1095,"Vencido",IF(N82>910,"Alerta",IF(N82>820,"Aviso",IF(N82>730,"Comunicado",IF(N82>=0,"Em dia","Vencido")))))) -> Em dia | N82: =$N$4-I82 -> 633 | R82: =I82+1080 -> 46645 | S82: =J82-$S$3 -> 463
B83: Instruções Manutenção Normativas e Gerenciais | C83: IM-ENG-267 | D83: Procedimento Para Aferição de Instrumentos | E83: Procedure for calibration of mesuring instruments | F83: ENGENHARIA CONFIABILIDADE E PERFORMANCE | G83: X | I83: 45202 | J83: =I83+1096 -> 46298 | K83: Publicado | L83: =IF(N83="","",IF(N83>1095,"Vencido",IF(N83>910,"Alerta",IF(N83>820,"Alerta",IF(N83>730,"Alerta",IF(N83>=0,"Em dia","Vencido")))))) -> Alerta | N83: =$N$4-I83 -> 996 | S83: =J83-$S$3 -> 100
B84: Instruções Manutenção Normativas e Gerenciais | C84: IM-ENG-268 | D84: Identificação de Equipamentos em Instalações | E84: Equipment identification | F84: ENGENHARIA CONFIABILIDADE E PERFORMANCE | G84: X | I84: 45959 | J84: =I84+1096 -> 47055 | K84: Publicado | L84: =IF(N84="","",IF(N84>1095,"Vencido",IF(N84>910,"Alerta",IF(N84>820,"Aviso",IF(N84>730,"Comunicado",IF(N84>=0,"Em dia","Vencido")))))) -> Em dia | N84: =$N$4-I84 -> 239 | R84: =I84+1080 -> 47039 | S84: =J84-$S$3 -> 857
B85: Instruções Manutenção Normativas e Gerenciais | C85: IM-ENG-269 | D85: Relatorio Mensal Desempenho Usinas | E85: Performance monthly report | F85: ENGENHARIA CONFIABILIDADE E PERFORMANCE | G85: X | I85: 45202 | J85: =I85+1096 -> 46298 | K85: Publicado | L85: =IF(N85="","",IF(N85>1095,"Vencido",IF(N85>910,"Alerta",IF(N85>820,"Alerta",IF(N85>730,"Alerta",IF(N85>=0,"Em dia","Vencido")))))) -> Alerta | N85: =$N$4-I85 -> 996 | S85: =J85-$S$3 -> 100
B86: Instruções Manutenção Mecânica | C86: IM-ENG-270 | D86: Medição de Espessura de Tubulação | E86: Procedure for measuring the thickness of the pipe | F86: ENGENHARIA MECÂNICA | G86: X | I86: 45202 | J86: =I86+1096 -> 46298 | K86: Publicado | L86: =IF(N86="","",IF(N86>1095,"Vencido",IF(N86>910,"Alerta",IF(N86>820,"Alerta",IF(N86>730,"Alerta",IF(N86>=0,"Em dia","Vencido")))))) -> Alerta | N86: =$N$4-I86 -> 996 | S86: =J86-$S$3 -> 100
B87: Instruções Manutenção Normativas e Gerenciais | C87: IM-ENG-280 | D87: Manutenção Preditiva | E87: Predictive Maintenance | F87: ENGENHARIA CONFIABILIDADE E PERFORMANCE | G87: X | H87: X | I87: 45895 | J87: =I87+1096 -> 46991 | K87: Publicado | L87: =IF(N87="","",IF(N87>1095,"Vencido",IF(N87>910,"Alerta",IF(N87>820,"Aviso",IF(N87>730,"Comunicado",IF(N87>=0,"Em dia","Vencido")))))) -> Em dia | N87: =$N$4-I87 -> 303 | S87: =J87-$S$3 -> 793
B88: Instruções Manutenção Normativas e Gerenciais | C88: IM-ENG-290 | D88: Manutenção Rotineira | E88: Routine Maintenance | F88: ENGENHARIA CONFIABILIDADE E PERFORMANCE | I88: - | K88: Cancelada | N88: =$N$4-I88 -> #VALUE!
B89: Instruções Manutenção Normativas e Gerenciais | C89: IM-ENG-300 | D89: Classificação de Risco de Ativos | E89: Asset Risk Rating | F89: ENGENHARIA CONFIABILIDADE E PERFORMANCE | I89: - | K89: Desenvolvimento | N89: =$N$4-I89 -> #VALUE! | S89: =J89-$S$3 -> -46198
B90: Instruções Manutenção Normativas e Gerenciais | C90: IM-ENG-301 | D90: Manutenções Preventivas Periódicas 0 - Renováveis | E90: Periodic Preventive Maintenance type 0 - Renewables | F90: ENGENHARIA CONFIABILIDADE E PERFORMANCE | I90: - | K90: Desenvolvimento | N90: =$N$4-I90 -> #VALUE! | S90: =J90-$S$3 -> -46198
B91: Instruções Manutenção Normativas e Gerenciais | C91: IM-ENG-302 | D91: Manutenções Preventivas Periódicas 1 - Renováveis | E91: Periodic Preventive Maintenance type 1 - Renewables | F91: ENGENHARIA CONFIABILIDADE E PERFORMANCE | I91: - | K91: Desenvolvimento | N91: =$N$4-I91 -> #VALUE! | S91: =J91-$S$3 -> -46198
B92: Instruções Manutenção Normativas e Gerenciais | C92: IM-ENG-303 | D92: Manutenções Preventivas Periódicas 2 - Renováveis | E92: Periodic Preventive Maintenance type 2 - Renewables | F92: ENGENHARIA CONFIABILIDADE E PERFORMANCE | I92: - | K92: Desenvolvimento | N92: =$N$4-I92 -> #VALUE! | S92: =J92-$S$3 -> -46198
B93: Instruções Manutenção Normativas e Gerenciais | C93: IM-ENG-310 | D93: Ensaio de Índice | E93: Index Test | F93: ENGENHARIA CONFIABILIDADE E PERFORMANCE | I93: - | K93: Cancelada | N93: =$N$4-I93 -> #VALUE!
B94: Instruções Manutenção Elétrica | C94: IM-ENG-320 | D94: Jumpeamento de barras ou bobinas multi-espiras estatóricas | E94: Jumping generator stator bars or coils | F94: ENGENHARIA ELÉTRICA | G94: X | I94: 45202 | J94: =I94+1096 -> 46298 | K94: Publicado | L94: =IF(N94="","",IF(N94>1095,"Vencido",IF(N94>910,"Alerta",IF(N94>820,"Alerta",IF(N94>730,"Alerta",IF(N94>=0,"Em dia","Vencido")))))) -> Alerta | N94: =$N$4-I94 -> 996 | S94: =J94-$S$3 -> 100
B95: Instruções Manutenção Mecânica | C95: IM-ENG-340 | D95: Vazão de ar geradores bulbo | E95: Bulb Generators Air Flow | F95: ENGENHARIA MECÂNICA | G95: X | I95: 45202 | J95: =I95+1096 -> 46298 | K95: Publicado | L95: =IF(N95="","",IF(N95>1095,"Vencido",IF(N95>910,"Alerta",IF(N95>820,"Alerta",IF(N95>730,"Alerta",IF(N95>=0,"Em dia","Vencido")))))) -> Alerta | N95: =$N$4-I95 -> 996 | S95: =J95-$S$3 -> 100
B96: Instruções Manutenção Normativas e Gerenciais | C96: IM-ENG-350 | D96: Gestão da Mudança | E96: Change management | F96: ENGENHARIA CONFIABILIDADE E PERFORMANCE | I96: - | K96: Desenvolvimento | N96: =$N$4-I96 -> #VALUE! | S96: =J96-$S$3 -> -46198
B97: Instruções Manutenção Normativas e Gerenciais | C97: IM-ENG-360 | D97: Comitê Técnico da CTG Brasil | E97: Establishing CTG Brasil Technical Committee | F97: ENGENHARIA CONFIABILIDADE E PERFORMANCE | G97: X | H97: X | I97: 45274 | J97: =I97+1096 -> 46370 | K97: Publicado | L97: =IF(N97="","",IF(N97>1095,"Vencido",IF(N97>910,"Alerta",IF(N97>820,"Alerta",IF(N97>730,"Alerta",IF(N97>=0,"Em dia","Vencido")))))) -> Alerta | N97: =$N$4-I97 -> 924 | S97: =J97-$S$3 -> 172
B98: Instruções Manutenção Normativas e Gerenciais | C98: IM-ENG-361 | D98: Gestão da avaliação e diagnóstico dos equipamentos | E98: Management of equipment evaluation and diagnosis | F98: ENGENHARIA CONFIABILIDADE E PERFORMANCE | G98: X | H98: X | I98: 45202 | J98: =I98+1096 -> 46298 | K98: Publicado | L98: =IF(N98="","",IF(N98>1095,"Vencido",IF(N98>910,"Alerta",IF(N98>820,"Alerta",IF(N98>730,"Alerta",IF(N98>=0,"Em dia","Vencido")))))) -> Alerta | N98: =$N$4-I98 -> 996 | S98: =J98-$S$3 -> 100
B99: Instruções Manutenção Normativas e Gerenciais | C99: IM-ENG-362 | D99: Avaliação da Condição dos equipamentos eletromecanicos | E99: Condition assessment of electromechanical equipment | F99: ENGENHARIA CONFIABILIDADE E PERFORMANCE | G99: X | H99: X | I99: 46009 | J99: =I99+1096 -> 47105 | K99: Publicado | L99: =IF(N99="","",IF(N99>1095,"Vencido",IF(N99>910,"Alerta",IF(N99>820,"Aviso",IF(N99>730,"Comunicado",IF(N99>=0,"Em dia","Vencido")))))) -> Em dia | N99: =$N$4-I99 -> 189 | S99: =J99-$S$3 -> 907
B100: Instruções Manutenção Normativas e Gerenciais | C100: IM-ENG-364 | D100: Armazenamento e conservação de materiais sobressalentes eletromecânicos | E100: Storage and conservation of electromechanical | F100: ENGENHARIA CONFIABILIDADE E PERFORMANCE | G100: X | H100: X | I100: 45274 | J100: =I100+1096 -> 46370 | K100: Publicado | L100: =IF(N100="","",IF(N100>1095,"Vencido",IF(N100>910,"Alerta",IF(N100>820,"Alerta",IF(N100>730,"Alerta",IF(N100>=0,"Em dia","Vencido")))))) -> Alerta | N100: =$N$4-I100 -> 924 | S100: =J100-$S$3 -> 172
B101: Instruções Manutenção Normativas e Gerenciais | C101: IM-ENG-365 | D101: Gestão de peças sobressalentes | E101: Spare parts management | F101: ENGENHARIA CONFIABILIDADE E PERFORMANCE | G101: X | H101: X | I101: 46009 | J101: =I101+1096 -> 47105 | K101: Publicado | L101: =IF(N101="","",IF(N101>1095,"Vencido",IF(N101>910,"Alerta",IF(N101>820,"Aviso",IF(N101>730,"Comunicado",IF(N101>=0,"Em dia","Vencido")))))) -> Em dia | N101: =$N$4-I101 -> 189 | S101: =J101-$S$3 -> 907
...

Sheet GM
B2: GM - GUIAS DE MANUTENÇÃO (MAINTENANCE GUIDES)
H3: =COUNTIF(H4:H795,"X") -> 751 | I3: =COUNTIF(I4:I1413,"X") -> 698 | P3: =TODAY() -> 46198
B4: UHE/HPP | C4: UHE/HPP | D4: NUMERO / NUMBER | E4: DESCRIÇÃO | F4: DESCRIPTION | G4: Area | H4: Por. | I4: Ing. | J4: Data | K4: Data Vencimento | L4: Status | M4: Status validade | N4: Revisão /novo | O4: =TODAY() -> 46198 | P4: Dias que falta para vencer
B5: 2 | C5: CHV | D5: 0 | E5: GM-CHV-00_Atividades antes e depois da MPP | F5: GM-CHV-00_Activities before and after MPP | G5: ENGENHARIA | H5: X | J5: 45202 | K5: =J5+1096 -> 46298 | L5: Publicado | M5: =IF(O5="","",IF(O5>1095,"Vencido",IF(O5>910,"Alerta",IF(O5>820,"Alerta",IF(O5>730,"Alerta",IF(O5>=0,"Em dia","Vencido")))))) -> Alerta | O5: =$O$4-J5 -> 996 | P5: =K5-$P$3 -> 100 | Q5: =IF(OR(C5="ARN",C5="SDP"),MID(E5,4,7),MID(E5,4,6)) -> CHV-00
B6: 2 | C6: CHV | D6: 1 | E6: GM-CHV-01_Turbina e equipamentos auxiliares | F6: GM-CHV-01_Turbine and its Auxiliary Equipment | G6: ENGENHARIA MECÂNICA | H6: X | I6: X | J6: 44739 | K6: =J6+1096 -> 45835 | L6: Publicado | M6: =IF(O6="","",IF(O6>1095,"Vencido",IF(O6>910,"Alerta",IF(O6>820,"Alerta",IF(O6>730,"Alerta",IF(O6>=0,"Em dia","Vencido")))))) -> Vencido | O6: =$O$4-J6 -> 1459 | P6: =K6-$P$3 -> -363 | Q6: =IF(OR(C6="ARN",C6="SDP"),MID(E6,4,7),MID(E6,4,6)) -> CHV-01
B7: 2 | C7: CHV | D7: 2 | E7: GM-CHV-02_Gerador e Equipamentos Auxiliares - Parte Mecânica | F7: GM-CHV-02_Generator Mechanical Part and Its Auxiliary Equipment | G7: ENGENHARIA MECÂNICA | H7: X | I7: X | J7: 44739 | K7: =J7+1096 -> 45835 | L7: Publicado | M7: =IF(O7="","",IF(O7>1095,"Vencido",IF(O7>910,"Alerta",IF(O7>820,"Alerta",IF(O7>730,"Alerta",IF(O7>=0,"Em dia","Vencido")))))) -> Vencido | O7: =$O$4-J7 -> 1459 | P7: =K7-$P$3 -> -363 | Q7: =IF(OR(C7="ARN",C7="SDP"),MID(E7,4,7),MID(E7,4,6)) -> CHV-02
B8: 2 | C8: CHV | D8: 3 | E8: GM-CHV-03_Gerador-Parte elétrica | F8: GM-CHV-03_Generator-Electric parts | G8: ENGENHARIA ELÉTRICA | H8: X | I8: X | J8: 45506 | K8: =J8+1096 -> 46602 | L8: Publicado | M8: =IF(O8="","",IF(O8>1095,"Vencido",IF(O8>910,"Alerta",IF(O8>820,"Alerta",IF(O8>730,"Alerta",IF(O8>=0,"Em dia","Vencido")))))) -> Em dia | O8: =$O$4-J8 -> 692 | P8: =K8-$P$3 -> 404 | Q8: =IF(OR(C8="ARN",C8="SDP"),MID(E8,4,7),MID(E8,4,6)) -> CHV-03
B9: 2 | C9: CHV | D9: 4 | E9: GM-CHV-04_Sistemas Auxiliares da Unidade Geradora | F9: GM-CHV-04_Generating Unit Auxiliary Control System | G9: ENGENHARIA ELÉTRICA | H9: X | I9: X | J9: 46104 | K9: =J9+1096 -> 47200 | L9: Publicado | M9: =IF(O9="","",IF(O9>1095,"Vencido",IF(O9>910,"Alerta",IF(O9>820,"Alerta",IF(O9>730,"Alerta",IF(O9>=0,"Em dia","Vencido")))))) -> Em dia | O9: =$O$4-J9 -> 94 | P9: =K9-$P$3 -> 1002 | Q9: =IF(OR(C9="ARN",C9="SDP"),MID(E9,4,7),MID(E9,4,6)) -> CHV-04
B10: 2 | C10: CHV | D10: 5 | E10: GM-CHV-05_Barramento de Saída do Gerador e Seus Acessórios | F10: GM-CHV-05_Generator Output Buses and Its Accessories | G10: ENGENHARIA ELÉTRICA | H10: X | I10: X | J10: 46104 | K10: =J10+1096 -> 47200 | L10: Publicado | M10: =IF(O10="","",IF(O10>1095,"Vencido",IF(O10>910,"Alerta",IF(O10>820,"Alerta",IF(O10>730,"Alerta",IF(O10>=0,"Em dia","Vencido")))))) -> Em dia | O10: =$O$4-J10 -> 94 | P10: =K10-$P$3 -> 1002 | Q10: =IF(OR(C10="ARN",C10="SDP"),MID(E10,4,7),MID(E10,4,6)) -> CHV-05
B11: 2 | C11: CHV | D11: 6 | E11: GM-CHV-06_Transformador Elevador | F11: GM-CHV-06_Step-up Transformer | G11: ENGENHARIA ELÉTRICA | H11: X | I11: X | J11: 46104 | K11: =J11+1096 -> 47200 | L11: Publicado | M11: =IF(O11="","",IF(O11>1095,"Vencido",IF(O11>910,"Alerta",IF(O11>820,"Alerta",IF(O11>730,"Alerta",IF(O11>=0,"Em dia","Vencido")))))) -> Em dia | O11: =$O$4-J11 -> 94 | P11: =K11-$P$3 -> 1002 | Q11: =IF(OR(C11="ARN",C11="SDP"),MID(E11,4,7),MID(E11,4,6)) -> CHV-06
B12: 2 | C12: CHV | D12: 7 | E12: GM-CHV-07_Transformadores a Seco | F12: GM-CHV-07_Dry-type Transformer | G12: ENGENHARIA ELÉTRICA | H12: X | I12: X | J12: 45959 | K12: =J12+1096 -> 47055 | L12: Publicado | M12: =IF(O12="","",IF(O12>1095,"Vencido",IF(O12>910,"Alerta",IF(O12>820,"Alerta",IF(O12>730,"Alerta",IF(O12>=0,"Em dia","Vencido")))))) -> Em dia | O12: =$O$4-J12 -> 239 | P12: =K12-$P$3 -> 857 | Q12: =IF(OR(C12="ARN",C12="SDP"),MID(E12,4,7),MID(E12,4,6)) -> CHV-07
B13: 2 | C13: CHV | D13: 8 | E13: GM-CHV-08_Equipamentos de Alta Tensão | F13: GM-CHV-08_High Voltage Equipment | G13: ENGENHARIA ELÉTRICA | H13: X | I13: X | J13: 45645 | K13: =J13+1096 -> 46741 | L13: Publicado | M13: =IF(O13="","",IF(O13>1095,"Vencido",IF(O13>910,"Alerta",IF(O13>820,"Alerta",IF(O13>730,"Alerta",IF(O13>=0,"Em dia","Vencido")))))) -> Em dia | O13: =$O$4-J13 -> 553 | P13: =K13-$P$3 -> 543 | Q13: =IF(OR(C13="ARN",C13="SDP"),MID(E13,4,7),MID(E13,4,6)) -> CHV-08
B14: 2 | C14: CHV | D14: 9 | E14: GM-CHV-09_Painéis de Média Tensão | F14: GM-CHV-09_Medium Voltage Switch Cabinet | G14: ENGENHARIA ELÉTRICA | H14: X | I14: X | J14: 45959 | K14: =J14+1096 -> 47055 | L14: Publicado | M14: =IF(O14="","",IF(O14>1095,"Vencido",IF(O14>910,"Alerta",IF(O14>820,"Alerta",IF(O14>730,"Alerta",IF(O14>=0,"Em dia","Vencido")))))) -> Em dia | O14: =$O$4-J14 -> 239 | P14: =K14-$P$3 -> 857 | Q14: =IF(OR(C14="ARN",C14="SDP"),MID(E14,4,7),MID(E14,4,6)) -> CHV-09
B15: 2 | C15: CHV | D15: 10 | E15: GM-CHV-10_Painéis de Baixa Tensão | F15: GM-CHV-10_Low Voltage Switch Cabinet | G15: ENGENHARIA ELÉTRICA | H15: X | I15: X | J15: 45959 | K15: =J15+1096 -> 47055 | L15: Publicado | M15: =IF(O15="","",IF(O15>1095,"Vencido",IF(O15>910,"Alerta",IF(O15>820,"Alerta",IF(O15>730,"Alerta",IF(O15>=0,"Em dia","Vencido")))))) -> Em dia | O15: =$O$4-J15 -> 239 | P15: =K15-$P$3 -> 857 | Q15: =IF(OR(C15="ARN",C15="SDP"),MID(E15,4,7),MID(E15,4,6)) -> CHV-10
B16: 2 | C16: CHV | D16: 11 | E16: GM-CHV-11_Cabos de Potência até 35kV | F16: GM-CHV-11_Power Cable Up to 35kV | G16: ENGENHARIA ELÉTRICA | H16: X | I16: X | J16: 46104 | K16: =J16+1096 -> 47200 | L16: Publicado | M16: =IF(O16="","",IF(O16>1095,"Vencido",IF(O16>910,"Alerta",IF(O16>820,"Alerta",IF(O16>730,"Alerta",IF(O16>=0,"Em dia","Vencido")))))) -> Em dia | O16: =$O$4-J16 -> 94 | P16: =K16-$P$3 -> 1002 | Q16: =IF(OR(C16="ARN",C16="SDP"),MID(E16,4,7),MID(E16,4,6)) -> CHV-11
B17: 2 | C17: CHV | D17: 12 | E17: GM-CHV-12_Estação de Operacão - Computador | F17: GM-CHV-12_Operation Station - Computer | G17: ENGENHARIA ELÉTRICA | H17: X | I17: X | J17: 46104 | K17: =J17+1096 -> 47200 | L17: Publicado | M17: =IF(O17="","",IF(O17>1095,"Vencido",IF(O17>910,"Alerta",IF(O17>820,"Alerta",IF(O17>730,"Alerta",IF(O17>=0,"Em dia","Vencido")))))) -> Em dia | O17: =$O$4-J17 -> 94 | P17: =K17-$P$3 -> 1002 | Q17: =IF(OR(C17="ARN",C17="SDP"),MID(E17,4,7),MID(E17,4,6)) -> CHV-12
... B33: 2 | C33: CHV | D33: 29 | E33: GM-CHV-29_Grade | F33: GM-CHV-29_Trash Rack | G33: ENGENHARIA MECÂNICA | H33: X | I33: X | J33: 45202 | K33: =J33+1096 -> 46298 | L33: Publicado | M33: =IF(O33="","",IF(O33>1095,"Vencido",IF(O33>910,"Alerta",IF(O33>820,"Alerta",IF(O33>730,"Alerta",IF(O33>=0,"Em dia","Vencido")))))) -> Alerta | O33: =$O$4-J33 -> 996 | P33: =K33-$P$3 -> 100 | Q33: =IF(OR(C33="ARN",C33="SDP"),MID(E33,4,7),MID(E33,4,6)) -> CHV-29
B34: 2 | C34: CHV | D34: 40 | E34: GM-CHV-40_Sistema de iluminação e pontos de tomada | F34: GM-CHV-40_Lighting system and outlet points | G34: ENGENHARIA ELÉTRICA | H34: X | J34: 45202 | K34: =J34+1096 -> 46298 | L34: Publicado | M34: =IF(O34="","",IF(O34>1095,"Vencido",IF(O34>910,"Alerta",IF(O34>820,"Alerta",IF(O34>730,"Alerta",IF(O34>=0,"Em dia","Vencido")))))) -> Alerta | O34: =$O$4-J34 -> 996 | P34: =K34-$P$3 -> 100 | Q34: =IF(OR(C34="ARN",C34="SDP"),MID(E34,4,7),MID(E34,4,6)) -> CHV-40
B35: 2 | C35: CHV | D35: 41 | E35: GM-CHV-41_Sistema Proteção Descargas Atmosféricas (SPDA) | F35: GM-CHV-41_Lightining Protection system | G35: ENGENHARIA ELÉTRICA | H35: X | J35: 45202 | K35: =J35+1096 -> 46298 | L35: Publicado | M35: =IF(O35="","",IF(O35>1095,"Vencido",IF(O35>910,"Alerta",IF(O35>820,"Alerta",IF(O35>730,"Alerta",IF(O35>=0,"Em dia","Vencido")))))) -> Alerta | O35: =$O$4-J35 -> 996 | P35: =K35-$P$3 -> 100 | Q35: =IF(OR(C35="ARN",C35="SDP"),MID(E35,4,7),MID(E35,4,6)) -> CHV-41
B36: 2 | C36: CHV | D36: 51 | E36: GM-CHV-51_Transformadores auxiliares imersos em óleo | F36: GM-CHV-51_Oil-immersed Auxiliary Transformer | G36: ENGENHARIA ELÉTRICA | H36: X | I36: X | J36: 45959 | K36: =J36+1096 -> 47055 | L36: Publicado | M36: =IF(O36="","",IF(O36>1095,"Vencido",IF(O36>910,"Alerta",IF(O36>820,"Alerta",IF(O36>730,"Alerta",IF(O36>=0,"Em dia","Vencido")))))) -> Em dia | O36: =$O$4-J36 -> 239 | P36: =K36-$P$3 -> 857 | Q36: =IF(OR(C36="ARN",C36="SDP"),MID(E36,4,7),MID(E36,4,6)) -> CHV-51
B37: 2 | C37: CHV | D37: 59 | E37: GM-CHV-59_Sistema_CFTV | F37: GM-CHV-59_CCTV System | G37: ENGENHARIA ELÉTRICA | H37: X | I37: X | J37: 45462 | K37: =J37+1096 -> 46558 | L37: Publicado | M37: =IF(O37="","",IF(O37>1095,"Vencido",IF(O37>910,"Alerta",IF(O37>820,"Alerta",IF(O37>730,"Alerta",IF(O37>=0,"Em dia","Vencido")))))) -> Alerta | O37: =$O$4-J37 -> 736 | P37: =K37-$P$3 -> 360 | Q37: =IF(OR(C37="ARN",C37="SDP"),MID(E37,4,7),MID(E37,4,6)) -> CHV-59
B38: 2 | C38: CHV | D38: 60 | E38: GM-CHV-60_Sistema anti incêndio | F38: GM-CHV-60_Firefighting System | G38: ENGENHARIA MECÂNICA | H38: X | I38: X | J38: 44819 | K38: =J38+1096 -> 45915 | L38: Publicado | M38: =IF(O38="","",IF(O38>1095,"Vencido",IF(O38>910,"Alerta",IF(O38>820,"Alerta",IF(O38>730,"Alerta",IF(O38>=0,"Em dia","Vencido")))))) -> Vencido | O38: =$O$4-J38 -> 1379 | P38: =K38-$P$3 -> -283 | Q38: =IF(OR(C38="ARN",C38="SDP"),MID(E38,4,7),MID(E38,4,6)) -> CHV-60
B39: 2 | C39: CHV | D39: 61 | E39: GM-CHV-61_Comporta de vertedouro | F39: GM-CHV-61_Spillway Gate | G39: ENGENHARIA MECÂNICA | H39: X | I39: X | J39: 44926 | K39: =J39+1096 -> 46022 | L39: Publicado | M39: =IF(O39="","",IF(O39>1095,"Vencido",IF(O39>910,"Alerta",IF(O39>820,"Alerta",IF(O39>730,"Alerta",IF(O39>=0,"Em dia","Vencido")))))) -> Vencido | O39: =$O$4-J39 -> 1272 | P39: =K39-$P$3 -> -176 | Q39: =IF(OR(C39="ARN",C39="SDP"),MID(E39,4,7),MID(E39,4,6)) -> CHV-61
B40: 2 | C40: CHV | D40: 62 | E40: GM-CHV-62_Comporta de emergência | F40: GM-CHV-62_Emergency Gate | G40: ENGENHARIA MECÂNICA | H40: X | I40: X | J40: 44926 | K40: =J40+1096 -> 46022 | L40: Publicado | M40: =IF(O40="","",IF(O40>1095,"Vencido",IF(O40>910,"Alerta",IF(O40>820,"Alerta",IF(O40>730,"Alerta",IF(O40>=0,"Em dia","Vencido")))))) -> Vencido | O40: =$O$4-J40 -> 1272 | P40: =K40-$P$3 -> -176 | Q40: =IF(OR(C40="ARN",C40="SDP"),MID(E40,4,7),MID(E40,4,6)) -> CHV-62
B41: 2 | C41: CHV | D41: 63 | E41: GM-CHV-63_Ponte rolante jusante | F41: GM-CHV-63_Downstream Bridge Crane | G41: ENGENHARIA MECÂNICA | H41: X | I41: X | J41: 44838 | K41: =J41+1096 -> 45934 | L41: Publicado | M41: =IF(O41="","",IF(O41>1095,"Vencido",IF(O41>910,"Alerta",IF(O41>820,"Alerta",IF(O41>730,"Alerta",IF(O41>=0,"Em dia","Vencido")))))) -> Vencido | O41: =$O$4-J41 -> 1360 | P41: =K41-$P$3 -> -264 | Q41: =IF(OR(C41="ARN",C41="SDP"),MID(E41,4,7),MID(E41,4,6)) -> CHV-63
B42: 2 | C42: CHV | D42: 64 | E42: GM-CHV-64_Valvula borboleta | F42: GM-CHV-64_Butterfly Valve | G42: ENGENHARIA MECÂNICA | H42: X | I42: X | J42: 45202 | K42: =J42+1096 -> 46298 | L42: Publicado | M42: =IF(O42="","",IF(O42>1095,"Vencido",IF(O42>910,"Alerta",IF(O42>820,"Alerta",IF(O42>730,"Alerta",IF(O42>=0,"Em dia","Vencido")))))) -> Alerta | O42: =$O$4-J42 -> 996 | P42: =K42-$P$3 -> 100 | Q42: =IF(OR(C42="ARN",C42="SDP"),MID(E42,4,7),MID(E42,4,6)) -> CHV-64
B43: 2 | C43: CHV | D43: 65 | E43: GM-CHV-65_Comporta vertedor Sistema hidráulico | F43: GM-CHV-65_Hydraulic Hoist | G43: ENGENHARIA MECÂNICA | H43: X | I43: X | J43: 45202 | K43: =J43+1096 -> 46298 | L43: Publicado | M43: =IF(O43="","",IF(O43>1095,"Vencido",IF(O43>910,"Alerta",IF(O43>820,"Alerta",IF(O43>730,"Alerta",IF(O43>=0,"Em dia","Vencido")))))) -> Alerta | O43: =$O$4-J43 -> 996 | P43: =K43-$P$3 -> 100 | Q43: =IF(OR(C43="ARN",C43="SDP"),MID(E43,4,7),MID(E43,4,6)) -> CHV-65
B44: 2 | C44: CHV | D44: 66 | E44: GM-CHV-66_Guincho | F44: GM-CHV-66_Winch | G44: ENGENHARIA MECÂNICA | H44: X | I44: X | J44: 45202 | K44: =J44+1096 -> 46298 | L44: Publicado | M44: =IF(O44="","",IF(O44>1095,"Vencido",IF(O44>910,"Alerta",IF(O44>820,"Alerta",IF(O44>730,"Alerta",IF(O44>=0,"Em dia","Vencido")))))) -> Alerta | O44: =$O$4-J44 -> 996 | P44: =K44-$P$3 -> 100 | Q44: =IF(OR(C44="ARN",C44="SDP"),MID(E44,4,7),MID(E44,4,6)) -> CHV-66
B45: 2 | C45: CHV | D45: 71 | E45: GM-CHV-71_Sistema de Manutenção Preditiva (MDM) | F45: GM-CHV-71_Predictive Maintenance System (MDM) | G45: ENGENHARIA CONFIABILIDADE E PERFORMANCE | H45: X | I45: X | J45: 45202 | K45: =J45+1096 -> 46298 | L45: Publicado | M45: =IF(O45="","",IF(O45>1095,"Vencido",IF(O45>910,"Alerta",IF(O45>820,"Alerta",IF(O45>730,"Alerta",IF(O45>=0,"Em dia","Vencido")))))) -> Alerta | O45: =$O$4-J45 -> 996 | P45: =K45-$P$3 -> 100 | Q45: =IF(OR(C45="ARN",C45="SDP"),MID(E45,4,7),MID(E45,4,6)) -> CHV-71
B46: 2 | C46: CHV | D46: 30.1 | E46: GM-CHV-30.1_Pórtico do vertedouro | F46: GM-CHV-30.1_Spillway Gantry Crane | G46: ENGENHARIA MECÂNICA | H46: X | I46: X | J46: 44838 | K46: =J46+1096 -> 45934 | L46: Publicado | M46: =IF(O46="","",IF(O46>1095,"Vencido",IF(O46>910,"Alerta",IF(O46>820,"Alerta",IF(O46>730,"Alerta",IF(O46>=0,"Em dia","Vencido")))))) -> Vencido | O46: =$O$4-J46 -> 1360 | P46: =K46-$P$3 -> -264 | Q46: =IF(OR(C46="ARN",C46="SDP"),MID(E46,4,7),MID(E46,4,6)) -> CHV-30
B47: 2 | C47: CHV | D47: 30.2 | E47: GM-CHV-30.2_Pórtico da tomada d`água | F47: GM-CHV-30.2_TDA Gantry Crane | G47: ENGENHARIA MECÂNICA | H47: X | I47: X | J47: 44838 | K47: =J47+1096 -> 45934 | L47: Publicado | M47: =IF(O47="","",IF(O47>1095,"Vencido",IF(O47>910,"Alerta",IF(O47>820,"Alerta",IF(O47>730,"Alerta",IF(O47>=0,"Em dia","Vencido")))))) -> Vencido | O47: =$O$4-J47 -> 1360 | P47: =K47-$P$3 -> -264 | Q47: =IF(OR(C47="ARN",C47="SDP"),MID(E47,4,7),MID(E47,4,6)) -> CHV-30
B48: 2 | C48: CHV | D48: 30.3 | E48: GM-CHV-30.3_200T Pórtico rolante | F48: GM-CHV-30.3_200t Gantry Crane | G48: ENGENHARIA MECÂNICA | H48: X | I48: X | J48: 44838 | K48: =J48+1096 -> 45934 | L48: Publicado | M48: =IF(O48="","",IF(O48>1095,"Vencido",IF(O48>910,"Alerta",IF(O48>820,"Alerta",IF(O48>730,"Alerta",IF(O48>=0,"Em dia","Vencido")))))) -> Vencido | O48: =$O$4-J48 -> 1360 | P48: =K48-$P$3 -> -264 | Q48: =IF(OR(C48="ARN",C48="SDP"),MID(E48,4,7),MID(E48,4,6)) -> CHV-30
B49: 2 | C49: CHV | D49: 31 | E49: GM-CHV-31_Ponte rolante | F49: GM-CHV-31_Bridge Crane | G49: ENGENHARIA MECÂNICA | H49: X | I49: X | J49: 44838 | K49: =J49+1096 -> 45934 | L49: Publicado | M49: =IF(O49="","",IF(O49>1095,"Vencido",IF(O49>910,"Alerta",IF(O49>820,"Alerta",IF(O49>730,"Alerta",IF(O49>=0,"Em dia","Vencido")))))) -> Vencido | O49: =$O$4-J49 -> 1360 | P49: =K49-$P$3 -> -264 | Q49: =IF(OR(C49="ARN",C49="SDP"),MID(E49,4,7),MID(E49,4,6)) -> CHV-31
B50: 2 | C50: CHV | D50: 32.1 | E50: GM-CHV-32.1_Ponte rolante auxiliar | F50: GM-CHV-32.1_Auxiliary Bridge Crane | G50: ENGENHARIA MECÂNICA | H50: X | I50: X | J50: 44838 | K50: =J50+1096 -> 45934 | L50: Publicado | M50: =IF(O50="","",IF(O50>1095,"Vencido",IF(O50>910,"Alerta",IF(O50>820,"Alerta",IF(O50>730,"Alerta",IF(O50>=0,"Em dia","Vencido")))))) -> Vencido | O50: =$O$4-J50 -> 1360 | P50: =K50-$P$3 -> -264 | Q50: =IF(OR(C50="ARN",C50="SDP"),MID(E50,4,7),MID(E50,4,6)) -> CHV-32
B51: 2 | C51: CHV | D51: 32.2 | E51: GM-CHV-32.2_Ponte rolante almoxarifado | F51: GM-CHV-32.2_Warehouse Bridge Crane | G51: ENGENHARIA MECÂNICA | H51: X | I51: X | J51: 44838 | K51: =J51+1096 -> 45934 | L51: Publicado | M51: =IF(O51="","",IF(O51>1095,"Vencido",IF(O51>910,"Alerta",IF(O51>820,"Alerta",IF(O51>730,"Alerta",IF(O51>=0,"Em dia","Vencido")))))) -> Vencido | O51: =$O$4-J51 -> 1360 | P51: =K51-$P$3 -> -264 | Q51: =IF(OR(C51="ARN",C51="SDP"),MID(E51,4,7),MID(E51,4,6)) -> CHV-32
B52: 2 | C52: CHV | D52: 32 | E52: GM-CHV-32_Ponte rolante auxiliar | F52: GM-CHV-32_Auxiliary Bridge Crane | G52: ENGENHARIA MECÂNICA | J52: - | L52: Cancelada | O52: =$O$4-J52 -> #VALUE! | P52: =K52-$P$3 -> -46198 | Q52: =IF(OR(C52="ARN",C52="SDP"),MID(E52,4,7),MID(E52,4,6)) -> CHV-32
B53: 2 | C53: CHV | D53: 34 | E53: GM-CHV-34_Depósito de óleo hidráulico-Eng | F53: GM-CHV-34_Hydraulic oil depot-Eng | G53: ENGENHARIA MECÂNICA | H53: X | I53: X | J53: 45202 | K53: =J53+1096 -> 46298 | L53: Publicado | M53: =IF(O53="","",IF(O53>1095,"Vencido",IF(O53>910,"Alerta",IF(O53>820,"Alerta",IF(O53>730,"Alerta",IF(O53>=0,"Em dia","Vencido")))))) -> Alerta | O53: =$O$4-J53 -> 996 | P53: =K53-$P$3 -> 100 | Q53: =IF(OR(C53="ARN",C53="SDP"),MID(E53,4,7),MID(E53,4,6)) -> CHV-34
B54: 2 | C54: CHV | D54: 35 | E54: GM-CHV-35_Conduto forçado - parte metálica | F54: GM-CHV-35_Hpenstock | G54: ENGENHARIA MECÂNICA | H54: X | I54: X | J54: 45274 | K54: =J54+1096 -> 46370 | L54: Publicado | M54: =IF(O54="","",IF(O54>1095,"Vencido",IF(O54>910,"Alerta",IF(O54>820,"Alerta",IF(O54>730,"Alerta",IF(O54>=0,"Em dia","Vencido")))))) -> Alerta | O54: =$O$4-J54 -> 924 | P54: =K54-$P$3 -> 172 | Q54: =IF(OR(C54="ARN",C54="SDP"),MID(E54,4,7),MID(E54,4,6)) -> CHV-35
B55: 4 | C55: CN1 | D55: 0 | E55: GM-CN1-00_Atividades antes e depois da MPP | F55: GM-CN1-00_Activities before and after MPP | G55: ENGENHARIA | H55: X | J55: 45202 | K55: =J55+1096 -> 46298 | L55: Publicado | M55: =IF(O55="","",IF(O55>1095,"Vencido",IF(O55>910,"Alerta",IF(O55>820,"Alerta",IF(O55>730,"Alerta",IF(O55>=0,"Em dia","Vencido")))))) -> Alerta | O55: =$O$4-J55 -> 996 | P55: =K55-$P$3 -> 100 | Q55: =IF(OR(C55="ARN",C55="SDP"),MID(E55,4,7),MID(E55,4,6)) -> CN1-00
B56: 4 | C56: CN1 | D56: 1 | E56: GM-CN1-01_Turbina e equipamentos auxiliares | F56: GM-CN1-01_Turbine and its Auxiliary Equipment | G56: ENGENHARIA MECÂNICA | H56: X | I56: X | J56: 44739 | K56: =J56+1096 -> 45835 | L56: Publicado | M56: =IF(O56="","",IF(O56>1095,"Vencido",IF(O56>910,"Alerta",IF(O56>820,"Alerta",IF(O56>730,"Alerta",IF(O56>=0,"Em dia","Vencido")))))) -> Vencido | O56: =$O$4-J56 -> 1459 | P56: =K56-$P$3 -> -363 | Q56: =IF(OR(C56="ARN",C56="SDP"),MID(E56,4,7),MID(E56,4,6)) -> CN1-01
B57: 4 | C57: CN1 | D57: 2 | E57: GM-CN1-02_Parte Mecanica Gerador e auxiliares | F57: GM-CN1-02_Generator Mechanical Part and Its Auxiliary Equipment | G57: ENGENHARIA MECÂNICA | H57: X | I57: X | J57: 44739 | K57: =J57+1096 -> 45835 | L57: Publicado | M57: =IF(O57="","",IF(O57>1095,"Vencido",IF(O57>910,"Alerta",IF(O57>820,"Alerta",IF(O57>730,"Alerta",IF(O57>=0,"Em dia","Vencido")))))) -> Vencido | O57: =$O$4-J57 -> 1459 | P57: =K57-$P$3 -> -363 | Q57: =IF(OR(C57="ARN",C57="SDP"),MID(E57,4,7),MID(E57,4,6)) -> CN1-02
B58: 4 | C58: CN1 | D58: 3 | E58: GM-CN1-03_Gerador-Parte elétrica | F58: GM-CN1-03_Generator-Electric parts | G58: ENGENHARIA ELÉTRICA | H58: X | I58: X | J58: 45506 | K58: =J58+1096 -> 46602 | L58: Publicado | M58: =IF(O58="","",IF(O58>1095,"Vencido",IF(O58>910,"Alerta",IF(O58>820,"Alerta",IF(O58>730,"Alerta",IF(O58>=0,"Em dia","Vencido")))))) -> Em dia | O58: =$O$4-J58 -> 692 | P58: =K58-$P$3 -> 404 | Q58: =IF(OR(C58="ARN",C58="SDP"),MID(E58,4,7),MID(E58,4,6)) -> CN1-03
B59: 4 | C59: CN1 | D59: 4 | E59: GM-CN1-04_Sistemas Auxiliares da Unidade Geradora | F59: GM-CN1-04_Generating Unit Auxiliary Control System | G59: ENGENHARIA ELÉTRICA | H59: X | I59: X | J59: 46107 | K59: =J59+1096 -> 47203 | L59: Publicado | M59: =IF(O59="","",IF(O59>1095,"Vencido",IF(O59>910,"Alerta",IF(O59>820,"Alerta",IF(O59>730,"Alerta",IF(O59>=0,"Em dia","Vencido")))))) -> Em dia | O59: =$O$4-J59 -> 91 | P59: =K59-$P$3 -> 1005 | Q59: =IF(OR(C59="ARN",C59="SDP"),MID(E59,4,7),MID(E59,4,6)) -> CN1-04
B60: 4 | C60: CN1 | D60: 5 | E60: GM-CN1-05_Barramento de Saída do Gerador e Seus Acessórios | F60: GM-CN1-05_Generator Output Buses and Its Accessories | G60: ENGENHARIA ELÉTRICA | H60: X | I60: X | J60: 46107 | K60: =J60+1096 -> 47203 | L60: Publicado | M60: =IF(O60="","",IF(O60>1095,"Vencido",IF(O60>910,"Alerta",IF(O60>820,"Alerta",IF(O60>730,"Alerta",IF(O60>=0,"Em dia","Vencido")))))) -> Em dia | O60: =$O$4-J60 -> 91 | P60: =K60-$P$3 -> 1005 | Q60: =IF(OR(C60="ARN",C60="SDP"),MID(E60,4,7),MID(E60,4,6)) -> CN1-05
B61: 4 | C61: CN1 | D61: 6 | E61: GM-CN1-06_Transformador Elevador | F61: GM-CN1-06_Step-up Transformer | G61: ENGENHARIA ELÉTRICA | H61: X | I61: X | J61: 46107 | K61: =J61+1096 -> 47203 | L61: Publicado | M61: =IF(O61="","",IF(O61>1095,"Vencido",IF(O61>910,"Alerta",IF(O61>820,"Alerta",IF(O61>730,"Alerta",IF(O61>=0,"Em dia","Vencido")))))) -> Em dia | O61: =$O$4-J61 -> 91 | P61: =K61-$P$3 -> 1005 | Q61: =IF(OR(C61="ARN",C61="SDP"),MID(E61,4,7),MID(E61,4,6)) -> CN1-06
B62: 4 | C62: CN1 | D62: 7 | E62: GM-CN1-07_Transformadores a Seco | F62: GM-CN1-07_Dry-type Transformer | G62: ENGENHARIA ELÉTRICA | H62: X | I62: X | J62: 45959 | K62: =J62+1096 -> 47055 | L62: Publicado | M62: =IF(O62="","",IF(O62>1095,"Vencido",IF(O62>910,"Alerta",IF(O62>820,"Alerta",IF(O62>730,"Alerta",IF(O62>=0,"Em dia","Vencido")))))) -> Em dia | O62: =$O$4-J62 -> 239 | P62: =K62-$P$3 -> 857 | Q62: =IF(OR(C62="ARN",C62="SDP"),MID(E62,4,7),MID(E62,4,6)) -> CN1-07
B63: 4 | C63: CN1 | D63: 8 | E63: GM-CN1-08_Equipamentos de Alta Tensão | F63: GM-CN1-08_High Voltage Equipment | G63: ENGENHARIA ELÉTRICA | H63: X | I63: X | J63: 45645 | K63: =J63+1096 -> 46741 | L63: Publicado | M63: =IF(O63="","",IF(O63>1095,"Vencido",IF(O63>910,"Alerta",IF(O63>820,"Alerta",IF(O63>730,"Alerta",IF(O63>=0,"Em dia","Vencido")))))) -> Em dia | O63: =$O$4-J63 -> 553 | P63: =K63-$P$3 -> 543 | Q63: =IF(OR(C63="ARN",C63="SDP"),MID(E63,4,7),MID(E63,4,6)) -> CN1-08
B64: 4 | C64: CN1 | D64: 9 | E64: GM-CN1-09_Painéis de Média Tensão | F64: GM-CN1-09_Medium Voltage Switch Cabinet | G64: ENGENHARIA ELÉTRICA | H64: X | I64: X | J64: 45959 | K64: =J64+1096 -> 47055 | L64: Publicado | M64: =IF(O64="","",IF(O64>1095,"Vencido",IF(O64>910,"Alerta",IF(O64>820,"Alerta",IF(O64>730,"Alerta",IF(O64>=0,"Em dia","Vencido")))))) -> Em dia | O64: =$O$4-J64 -> 239 | P64: =K64-$P$3 -> 857 | Q64: =IF(OR(C64="ARN",C64="SDP"),MID(E64,4,7),MID(E64,4,6)) -> CN1-09
B65: 4 | C65: CN1 | D65: 10 | E65: GM-CN1-10_Painéis de Baixa Tensão | F65: GM-CN1-10_Low Voltage Switch Cabinet | G65: ENGENHARIA ELÉTRICA | H65: X | I65: X | J65: 45959 | K65: =J65+1096 -> 47055 | L65: Publicado | M65: =IF(O65="","",IF(O65>1095,"Vencido",IF(O65>910,"Alerta",IF(O65>820,"Alerta",IF(O65>730,"Alerta",IF(O65>=0,"Em dia","Vencido")))))) -> Em dia | O65: =$O$4-J65 -> 239 | P65: =K65-$P$3 -> 857 | Q65: =IF(OR(C65="ARN",C65="SDP"),MID(E65,4,7),MID(E65,4,6)) -> CN1-10
B66: 4 | C66: CN1 | D66: 11 | E66: GM-CN1-11_Cabos de Potência até 35kV | F66: GM-CN1-11_Power Cable Up to 35kV | G66: ENGENHARIA ELÉTRICA | H66: X | I66: X | J66: 46107 | K66: =J66+1096 -> 47203 | L66: Publicado | M66: =IF(O66="","",IF(O66>1095,"Vencido",IF(O66>910,"Alerta",IF(O66>820,"Alerta",IF(O66>730,"Alerta",IF(O66>=0,"Em dia","Vencido")))))) -> Em dia | O66: =$O$4-J66 -> 91 | P66: =K66-$P$3 -> 1005 | Q66: =IF(OR(C66="ARN",C66="SDP"),MID(E66,4,7),MID(E66,4,6)) -> CN1-11
B67: 4 | C67: CN1 | D67: 12 | E67: GM-CN1-12_Estação de Operação | F67: GM-CN1-12_Host Computer | G67: ENGENHARIA ELÉTRICA | H67: X | I67: X | J67: 46107 | K67: =J67+1096 -> 47203 | L67: Publicado | M67: =IF(O67="","",IF(O67>1095,"Vencido",IF(O67>910,"Alerta",IF(O67>820,"Alerta",IF(O67>730,"Alerta",IF(O67>=0,"Em dia","Vencido")))))) -> Em dia | O67: =$O$4-J67 -> 91 | P67: =K67-$P$3 -> 1005 | Q67: =IF(OR(C67="ARN",C67="SDP"),MID(E67,4,7),MID(E67,4,6)) -> CN1-12
... B84: 4 | C84: CN1 | D84: 33 | E84: GM-CN1-33_Elevador | F84: GM-CN1-33_Elevator | G84: ENGENHARIA MECÂNICA | H84: X | I84: X | J84: 44739 | K84: =J84+1096 -> 45835 | L84: Publicado | M84: =IF(O84="","",IF(O84>1095,"Vencido",IF(O84>910,"Alerta",IF(O84>820,"Alerta",IF(O84>730,"Alerta",IF(O84>=0,"Em dia","Vencido")))))) -> Vencido | O84: =$O$4-J84 -> 1459 | P84: =K84-$P$3 -> -363 | Q84: =IF(OR(C84="ARN",C84="SDP"),MID(E84,4,7),MID(E84,4,6)) -> CN1-33
B85: 4 | C85: CN1 | D85: 40 | E85: GM-CN1-40_Sistema de iluminação e pontos de tomada | F85: GM-CN1-40_Lighting system and outlet points | G85: ENGENHARIA ELÉTRICA | H85: X | J85: 45202 | K85: =J85+1096 -> 46298 | L85: Publicado | M85: =IF(O85="","",IF(O85>1095,"Vencido",IF(O85>910,"Alerta",IF(O85>820,"Alerta",IF(O85>730,"Alerta",IF(O85>=0,"Em dia","Vencido")))))) -> Alerta | O85: =$O$4-J85 -> 996 | P85: =K85-$P$3 -> 100 | Q85: =IF(OR(C85="ARN",C85="SDP"),MID(E85,4,7),MID(E85,4,6)) -> CN1-40
B86: 4 | C86: CN1 | D86: 41 | E86: GM-CN1-41_Sistema Proteção Descargas Atmosféricas (SPDA) | F86: GM-CN1-41_Lightning protection system | G86: ENGENHARIA ELÉTRICA | H86: X | J86: 45202 | K86: =J86+1096 -> 46298 | L86: Publicado | M86: =IF(O86="","",IF(O86>1095,"Vencido",IF(O86>910,"Alerta",IF(O86>820,"Alerta",IF(O86>730,"Alerta",IF(O86>=0,"Em dia","Vencido")))))) -> Alerta | O86: =$O$4-J86 -> 996 | P86: =K86-$P$3 -> 100 | Q86: =IF(OR(C86="ARN",C86="SDP"),MID(E86,4,7),MID(E86,4,6)) -> CN1-41
B87: 4 | C87: CN1 | D87: 51 | E87: GM-CN1-51_Transformadores imersos a oleo ate 35kV | F87: GM-CN1-51_Oil-immersed Transformer up to 35kV | G87: ENGENHARIA ELÉTRICA | H87: X | I87: X | J87: 45959 | K87: =J87+1096 -> 47055 | L87: Publicado | M87: =IF(O87="","",IF(O87>1095,"Vencido",IF(O87>910,"Alerta",IF(O87>820,"Alerta",IF(O87>730,"Alerta",IF(O87>=0,"Em dia","Vencido")))))) -> Em dia | O87: =$O$4-J87 -> 239 | P87: =K87-$P$3 -> 857 | Q87: =IF(OR(C87="ARN",C87="SDP"),MID(E87,4,7),MID(E87,4,6)) -> CN1-51
B88: 4 | C88: CN1 | D88: 53 | E88: GM-CN1-53_Linha de transmissão aérea | F88: GM-CN1-53_Overhead Transmission Line | G88: ENGENHARIA ELÉTRICA | H88: X | I88: X | J88: 45743 | K88: =J88+1096 -> 46839 | L88: Publicado | M88: =IF(O88="","",IF(O88>1095,"Vencido",IF(O88>910,"Alerta",IF(O88>820,"Alerta",IF(O88>730,"Alerta",IF(O88>=0,"Em dia","Vencido")))))) -> Em dia | O88: =$O$4-J88 -> 455 | P88: =K88-$P$3 -> 641 | Q88: =IF(OR(C88="ARN",C88="SDP"),MID(E88,4,7),MID(E88,4,6)) -> CN1-53
B89: 4 | C89: CN1 | D89: 56 | E89: GM-CN1-56_Proteção de Barras | F89: GM-CN1-56_Busbar Protection | G89: ENGENHARIA ELÉTRICA | H89: X | I89: X | J89: 46107 | K89: =J89+1096 -> 47203 | L89: Publicado | M89: =IF(O89="","",IF(O89>1095,"Vencido",IF(O89>910,"Alerta",IF(O89>820,"Alerta",IF(O89>730,"Alerta",IF(O89>=0,"Em dia","Vencido")))))) -> Em dia | O89: =$O$4-J89 -> 91 | P89: =K89-$P$3 -> 1005 | Q89: =IF(OR(C89="ARN",C89="SDP"),MID(E89,4,7),MID(E89,4,6)) -> CN1-56
B90: 4 | C90: CN1 | D90: 57 | E90: GM-CN1-57_Proteção de Linha de Transmissão | F90: GM-CN1-57_Transmission Line Protection | G90: ENGENHARIA ELÉTRICA | H90: X | I90: X | J90: 46107 | K90: =J90+1096 -> 47203 | L90: Publicado | M90: =IF(O90="","",IF(O90>1095,"Vencido",IF(O90>910,"Alerta",IF(O90>820,"Alerta",IF(O90>730,"Alerta",IF(O90>=0,"Em dia","Vencido")))))) -> Em dia | O90: =$O$4-J90 -> 91 | P90: =K90-$P$3 -> 1005 | Q90: =IF(OR(C90="ARN",C90="SDP"),MID(E90,4,7),MID(E90,4,6)) -> CN1-57
B91: 4 | C91: CN1 | D91: 58 | E91: GM-CN1-58_Sistema de ventilação | F91: GM-CN1-58_Ventilation System | G91: ENGENHARIA MECÂNICA | H91: X | I91: X | J91: 44739 | K91: =J91+1096 -> 45835 | L91: Publicado | M91: =IF(O91="","",IF(O91>1095,"Vencido",IF(O91>910,"Alerta",IF(O91>820,"Alerta",IF(O91>730,"Alerta",IF(O91>=0,"Em dia","Vencido")))))) -> Vencido | O91: =$O$4-J91 -> 1459 | P91: =K91-$P$3 -> -363 | Q91: =IF(OR(C91="ARN",C91="SDP"),MID(E91,4,7),MID(E91,4,6)) -> CN1-58
B92: 4 | C92: CN1 | D92: 59 | E92: GM-CN1-59_Sistema_CFTV | F92: GM-CN1-59_CCTV System | G92: ENGENHARIA ELÉTRICA | H92: X | I92: X | J92: 45462 | K92: =J92+1096 -> 46558 | L92: Publicado | M92: =IF(O92="","",IF(O92>1095,"Vencido",IF(O92>910,"Alerta",IF(O92>820,"Alerta",IF(O92>730,"Alerta",IF(O92>=0,"Em dia","Vencido")))))) -> Alerta | O92: =$O$4-J92 -> 736 | P92: =K92-$P$3 -> 360 | Q92: =IF(OR(C92="ARN",C92="SDP"),MID(E92,4,7),MID(E92,4,6)) -> CN1-59
B93: 4 | C93: CN1 | D93: 60 | E93: GM-CN1-60_Sistema anti incêndio | F93: GM-CN1-60_Firefighting System | G93: ENGENHARIA MECÂNICA | H93: X | I93: X | J93: 44819 | K93: =J93+1096 -> 45915 | L93: Publicado | M93: =IF(O93="","",IF(O93>1095,"Vencido",IF(O93>910,"Alerta",IF(O93>820,"Alerta",IF(O93>730,"Alerta",IF(O93>=0,"Em dia","Vencido")))))) -> Vencido | O93: =$O$4-J93 -> 1379 | P93: =K93-$P$3 -> -283 | Q93: =IF(OR(C93="ARN",C93="SDP"),MID(E93,4,7),MID(E93,4,6)) -> CN1-60
B94: 4 | C94: CN1 | D94: 61 | E94: GM-CN1-61_Comporta de vertedouro | F94: GM-CN1-61_Spillway Gate | G94: ENGENHARIA MECÂNICA | H94: X | I94: X | J94: 44926 | K94: =J94+1096 -> 46022 | L94: Publicado | M94: =IF(O94="","",IF(O94>1095,"Vencido",IF(O94>910,"Alerta",IF(O94>820,"Alerta",IF(O94>730,"Alerta",IF(O94>=0,"Em dia","Vencido")))))) -> Vencido | O94: =$O$4-J94 -> 1272 | P94: =K94-$P$3 -> -176 | Q94: =IF(OR(C94="ARN",C94="SDP"),MID(E94,4,7),MID(E94,4,6)) -> CN1-61
B95: 4 | C95: CN1 | D95: 62 | E95: GM-CN1-62_Comporta de emergência | F95: GM-CN1-62_Emergency Gate | G95: ENGENHARIA MECÂNICA | H95: X | I95: X | J95: 44926 | K95: =J95+1096 -> 46022 | L95: Publicado | M95: =IF(O95="","",IF(O95>1095,"Vencido",IF(O95>910,"Alerta",IF(O95>820,"Alerta",IF(O95>730,"Alerta",IF(O95>=0,"Em dia","Vencido")))))) -> Vencido | O95: =$O$4-J95 -> 1272 | P95: =K95-$P$3 -> -176 | Q95: =IF(OR(C95="ARN",C95="SDP"),MID(E95,4,7),MID(E95,4,6)) -> CN1-62
B96: 4 | C96: CN1 | D96: 65 | E96: GM-CN1-65_Comporta de emergência Sistema hidráulico | F96: GM-CN1-65_Hydraulic Hoist (emergency） | G96: ENGENHARIA MECÂNICA | H96: X | I96: X | J96: 45202 | K96: =J96+1096 -> 46298 | L96: Publicado | M96: =IF(O96="","",IF(O96>1095,"Vencido",IF(O96>910,"Alerta",IF(O96>820,"Alerta",IF(O96>730,"Alerta",IF(O96>=0,"Em dia","Vencido")))))) -> Alerta | O96: =$O$4-J96 -> 996 | P96: =K96-$P$3 -> 100 | Q96: =IF(OR(C96="ARN",C96="SDP"),MID(E96,4,7),MID(E96,4,6)) -> CN1-65
B97: 4 | C97: CN1 | D97: 65 | E97: GM-CN1-65_Comporta vertedor Sistema hidráulico | F97: GM-CN1-65_Hydraulic Hoist (spillway） | G97: ENGENHARIA MECÂNICA | H97: X | I97: X | J97: 45202 | K97: =J97+1096 -> 46298 | L97: Publicado | M97: =IF(O97="","",IF(O97>1095,"Vencido",IF(O97>910,"Alerta",IF(O97>820,"Alerta",IF(O97>730,"Alerta",IF(O97>=0,"Em dia","Vencido")))))) -> Alerta | O97: =$O$4-J97 -> 996 | P97: =K97-$P$3 -> 100 | Q97: =IF(OR(C97="ARN",C97="SDP"),MID(E97,4,7),MID(E97,4,6)) -> CN1-65
B98: 4 | C98: CN1 | D98: 71 | E98: GM-CN1-71_Instrução de Manutenção Preditiva (MDM) | F98: GM-CN1-71_Predictive Maintenance System (MDM) | G98: ENGENHARIA CONFIABILIDADE E PERFORMANCE | H98: X | I98: X | J98: 45202 | K98: =J98+1096 -> 46298 | L98: Publicado | M98: =IF(O98="","",IF(O98>1095,"Vencido",IF(O98>910,"Alerta",IF(O98>820,"Alerta",IF(O98>730,"Alerta",IF(O98>=0,"Em dia","Vencido")))))) -> Alerta | O98: =$O$4-J98 -> 996 | P98: =K98-$P$3 -> 100 | Q98: =IF(OR(C98="ARN",C98="SDP"),MID(E98,4,7),MID(E98,4,6)) -> CN1-71
... B102: 4 | C102: CN1 | D102: 63 | E102: GM-CN1-63_Pórtico de jusante | F102: GM-CN1-63_Downstream Gantry Crane | G102: ENGENHARIA MECÂNICA | H102: X | I102: X | J102: 44838 | K102: =J102+1096 -> 45934 | L102: Publicado | M102: =IF(O102="","",IF(O102>1095,"Vencido",IF(O102>910,"Alerta",IF(O102>820,"Alerta",IF(O102>730,"Alerta",IF(O102>=0,"Em dia","Vencido")))))) -> Vencido | O102: =$O$4-J102 -> 1360 | P102: =K102-$P$3 -> -264 | Q102: =IF(OR(C102="ARN",C102="SDP"),MID(E102,4,7),MID(E102,4,6)) -> CN1-63
B103: 4 | C103: CN1 | D103: 86 | E103: GM-CN1-86_Sistema de cloro pastilha | F103: GM-CN1-86_Tablet chlorine system | G103: ENGENHARIA MECÂNICA | H103: X | J103: 45274 | K103: =J103+1096 -> 46370 | L103: Publicado | M103: =IF(O103="","",IF(O103>1095,"Vencido",IF(O103>910,"Alerta",IF(O103>820,"Alerta",IF(O103>730,"Alerta",IF(O103>=0,"Em dia","Vencido")))))) -> Alerta | O103: =$O$4-J103 -> 924 | P103: =K103-$P$3 -> 172 | Q103: =IF(OR(C103="ARN",C103="SDP"),MID(E103,4,7),MID(E103,4,6)) -> CN1-86
B104: 5 | C104: CN2 | D104: 0 | E104: GM-CN2-00_Atividades antes e depois da MPP | F104: GM-CN2-00_Activities before and after MPP | G104: ENGENHARIA | H104: X | J104: 45202 | K104: =J104+1096 -> 46298 | L104: Publicado | M104: =IF(O104="","",IF(O104>1095,"Vencido",IF(O104>910,"Alerta",IF(O104>820,"Alerta",IF(O104>730,"Alerta",IF(O104>=0,"Em dia","Vencido")))))) -> Alerta | O104: =$O$4-J104 -> 996 | P104: =K104-$P$3 -> 100 | Q104: =IF(OR(C104="ARN",C104="SDP"),MID(E104,4,7),MID(E104,4,6)) -> CN2-00
B105: 5 | C105: CN2 | D105: 1 | E105: GM-CN2-01_Turbina e equipamentos auxiliares | F105: GM-CN2-01_Turbine and its Auxiliary Equipment | G105: ENGENHARIA MECÂNICA | H105: X | I105: X | J105: 44739 | K105: =J105+1096 -> 45835 | L105: Publicado | M105: =IF(O105="","",IF(O105>1095,"Vencido",IF(O105>910,"Alerta",IF(O105>820,"Alerta",IF(O105>730,"Alerta",IF(O105>=0,"Em dia","Vencido")))))) -> Vencido | O105: =$O$4-J105 -> 1459 | P105: =K105-$P$3 -> -363 | Q105: =IF(OR(C105="ARN",C105="SDP"),MID(E105,4,7),MID(E105,4,6)) -> CN2-01
B106: 5 | C106: CN2 | D106: 2 | E106: GM-CN2-02_Parte Mecanica Gerador e auxiliares | F106: GM-CN2-02_Generator Mechanical Part and Its Auxiliary Equipment | G106: ENGENHARIA MECÂNICA | H106: X | I106: X | J106: 44739 | K106: =J106+1096 -> 45835 | L106: Publicado | M106: =IF(O106="","",IF(O106>1095,"Vencido",IF(O106>910,"Alerta",IF(O106>820,"Alerta",IF(O106>730,"Alerta",IF(O106>=0,"Em dia","Vencido")))))) -> Vencido | O106: =$O$4-J106 -> 1459 | P106: =K106-$P$3 -> -363 | Q106: =IF(OR(C106="ARN",C106="SDP"),MID(E106,4,7),MID(E106,4,6)) -> CN2-02
B107: 5 | C107: CN2 | D107: 3 | E107: GM-CN2-03_Gerador-Parte elétrica | F107: GM-CN2-03_Generator-Electric parts | G107: ENGENHARIA ELÉTRICA | H107: X | I107: X | J107: 45506 | K107: =J107+1096 -> 46602 | L107: Publicado | M107: =IF(O107="","",IF(O107>1095,"Vencido",IF(O107>910,"Alerta",IF(O107>820,"Alerta",IF(O107>730,"Alerta",IF(O107>=0,"Em dia","Vencido")))))) -> Em dia | O107: =$O$4-J107 -> 692 | P107: =K107-$P$3 -> 404 | Q107: =IF(OR(C107="ARN",C107="SDP"),MID(E107,4,7),MID(E107,4,6)) -> CN2-03
B108: 5 | C108: CN2 | D108: 4 | E108: GM-CN2-04_Sistemas Auxiliares da Unidade Geradora | F108: GM-CN2-04_Generating Unit Auxiliary Control System | G108: ENGENHARIA ELÉTRICA | H108: X | I108: X | J108: 46107 | K108: =J108+1096 -> 47203 | L108: Publicado | M108: =IF(O108="","",IF(O108>1095,"Vencido",IF(O108>910,"Alerta",IF(O108>820,"Alerta",IF(O108>730,"Alerta",IF(O108>=0,"Em dia","Vencido")))))) -> Em dia | O108: =$O$4-J108 -> 91 | P108: =K108-$P$3 -> 1005 | Q108: =IF(OR(C108="ARN",C108="SDP"),MID(E108,4,7),MID(E108,4,6)) -> CN2-04
B109: 5 | C109: CN2 | D109: 5 | E109: GM-CN2-05_Barramento de Saída do Gerador e Seus Acessórios | F109: GM-CN2-05_Generator Output Buses and Its Accessories | G109: ENGENHARIA ELÉTRICA | H109: X | I109: X | J109: 46107 | K109: =J109+1096 -> 47203 | L109: Publicado | M109: =IF(O109="","",IF(O109>1095,"Vencido",IF(O109>910,"Alerta",IF(O109>820,"Alerta",IF(O109>730,"Alerta",IF(O109>=0,"Em dia","Vencido")))))) -> Em dia | O109: =$O$4-J109 -> 91 | P109: =K109-$P$3 -> 1005 | Q109: =IF(OR(C109="ARN",C109="SDP"),MID(E109,4,7),MID(E109,4,6)) -> CN2-05
B110: 5 | C110: CN2 | D110: 6 | E110: GM-CN2-06_Transformador Elevador | F110: GM-CN2-06_Step-up Transformer | G110: ENGENHARIA ELÉTRICA | H110: X | I110: X | J110: 46107 | K110: =J110+1096 -> 47203 | L110: Publicado | M110: =IF(O110="","",IF(O110>1095,"Vencido",IF(O110>910,"Alerta",IF(O110>820,"Alerta",IF(O110>730,"Alerta",IF(O110>=0,"Em dia","Vencido")))))) -> Em dia | O110: =$O$4-J110 -> 91 | P110: =K110-$P$3 -> 1005 | Q110: =IF(OR(C110="ARN",C110="SDP"),MID(E110,4,7),MID(E110,4,6)) -> CN2-06
B111: 5 | C111: CN2 | D111: 7 | E111: GM-CN2-07_Transformadores a Seco | F111: GM-CN2-07_Dry-type Transformer | G111: ENGENHARIA ELÉTRICA | H111: X | I111: X | J111: 45959 | K111: =J111+1096 -> 47055 | L111: Publicado | M111: =IF(O111="","",IF(O111>1095,"Vencido",IF(O111>910,"Alerta",IF(O111>820,"Alerta",IF(O111>730,"Alerta",IF(O111>=0,"Em dia","Vencido")))))) -> Em dia | O111: =$O$4-J111 -> 239 | P111: =K111-$P$3 -> 857 | Q111: =IF(OR(C111="ARN",C111="SDP"),MID(E111,4,7),MID(E111,4,6)) -> CN2-07
B112: 5 | C112: CN2 | D112: 8 | E112: GM-CN2-08_Equipamentos de Alta Tensão | F112: GM-CN2-08_High Voltage Equipment | G112: ENGENHARIA ELÉTRICA | H112: X | I112: X | J112: 45645 | K112: =J112+1096 -> 46741 | L112: Publicado | M112: =IF(O112="","",IF(O112>1095,"Vencido",IF(O112>910,"Alerta",IF(O112>820,"Alerta",IF(O112>730,"Alerta",IF(O112>=0,"Em dia","Vencido")))))) -> Em dia | O112: =$O$4-J112 -> 553 | P112: =K112-$P$3 -> 543 | Q112: =IF(OR(C112="ARN",C112="SDP"),MID(E112,4,7),MID(E112,4,6)) -> CN2-08
B113: 5 | C113: CN2 | D113: 9 | E113: GM-CN2-09_Painéis de Média Tensão | F113: GM-CN2-09_Medium Voltage Switch Cabinet | G113: ENGENHARIA ELÉTRICA | H113: X | I113: X | J113: 45959 | K113: =J113+1096 -> 47055 | L113: Publicado | M113: =IF(O113="","",IF(O113>1095,"Vencido",IF(O113>910,"Alerta",IF(O113>820,"Alerta",IF(O113>730,"Alerta",IF(O113>=0,"Em dia","Vencido")))))) -> Em dia | O113: =$O$4-J113 -> 239 | P113: =K113-$P$3 -> 857 | Q113: =IF(OR(C113="ARN",C113="SDP"),MID(E113,4,7),MID(E113,4,6)) -> CN2-09
B114: 5 | C114: CN2 | D114: 10 | E114: GM-CN2-10_Painéis de Baixa Tensão | F114: GM-CN2-10_Low Voltage Switch Cabinet | G114: ENGENHARIA ELÉTRICA | H114: X | I114: X | J114: 45959 | K114: =J114+1096 -> 47055 | L114: Publicado | M114: =IF(O114="","",IF(O114>1095,"Vencido",IF(O114>910,"Alerta",IF(O114>820,"Alerta",IF(O114>730,"Alerta",IF(O114>=0,"Em dia","Vencido")))))) -> Em dia | O114: =$O$4-J114 -> 239 | P114: =K114-$P$3 -> 857 | Q114: =IF(OR(C114="ARN",C114="SDP"),MID(E114,4,7),MID(E114,4,6)) -> CN2-10
B115: 5 | C115: CN2 | D115: 11 | E115: GM-CN2-11_Cabos de Potência até 35kV | F115: GM-CN2-11_Power Cable Up to 35kV | G115: ENGENHARIA ELÉTRICA | H115: X | I115: X | J115: 46107 | K115: =J115+1096 -> 47203 | L115: Publicado | M115: =IF(O115="","",IF(O115>1095,"Vencido",IF(O115>910,"Alerta",IF(O115>820,"Alerta",IF(O115>730,"Alerta",IF(O115>=0,"Em dia","Vencido")))))) -> Em dia | O115: =$O$4-J115 -> 91 | P115: =K115-$P$3 -> 1005 | Q115: =IF(OR(C115="ARN",C115="SDP"),MID(E115,4,7),MID(E115,4,6)) -> CN2-11
B116: 5 | C116: CN2 | D116: 12 | E116: GM-CN2-12_Estação de Operação | F116: GM-CN2-12_Host Computer | G116: ENGENHARIA ELÉTRICA | H116: X | I116: X | J116: 46107 | K116: =J116+1096 -> 47203 | L116: Publicado | M116: =IF(O116="","",IF(O116>1095,"Vencido",IF(O116>910,"Alerta",IF(O116>820,"Alerta",IF(O116>730,"Alerta",IF(O116>=0,"Em dia","Vencido")))))) -> Em dia | O116: =$O$4-J116 -> 91 | P116: =K116-$P$3 -> 1005 | Q116: =IF(OR(C116="ARN",C116="SDP"),MID(E116,4,7),MID(E116,4,6)) -> CN2-12
... B133: 5 | C133: CN2 | D133: 33 | E133: GM-CN2-33_Elevador | F133: GM-CN2-33_Elevator | G133: ENGENHARIA MECÂNICA | H133: X | I133: X | J133: 44739 | K133: =J133+1096 -> 45835 | L133: Publicado | M133: =IF(O133="","",IF(O133>1095,"Vencido",IF(O133>910,"Alerta",IF(O133>820,"Alerta",IF(O133>730,"Alerta",IF(O133>=0,"Em dia","Vencido")))))) -> Vencido | O133: =$O$4-J133 -> 1459 | P133: =K133-$P$3 -> -363 | Q133: =IF(OR(C133="ARN",C133="SDP"),MID(E133,4,7),MID(E133,4,6)) -> CN2-33
B134: 5 | C134: CN2 | D134: 40 | E134: GM-CN2-40_Sistema de iluminação e pontos de tomada | F134: GM-CN2-40_Lighting system and outlet points | G134: ENGENHARIA ELÉTRICA | H134: X | J134: 45202 | K134: =J134+1096 -> 46298 | L134: Publicado | M134: =IF(O134="","",IF(O134>1095,"Vencido",IF(O134>910,"Alerta",IF(O134>820,"Alerta",IF(O134>730,"Alerta",IF(O134>=0,"Em dia","Vencido")))))) -> Alerta | O134: =$O$4-J134 -> 996 | P134: =K134-$P$3 -> 100 | Q134: =IF(OR(C134="ARN",C134="SDP"),MID(E134,4,7),MID(E134,4,6)) -> CN2-40
B135: 5 | C135: CN2 | D135: 41 | E135: GM-CN2-41_Sistema Proteção Descargas Atmosféricas (SPDA) | F135: GM-CN2-41_Lightning protection system | G135: ENGENHARIA ELÉTRICA | H135: X | J135: 45202 | K135: =J135+1096 -> 46298 | L135: Publicado | M135: =IF(O135="","",IF(O135>1095,"Vencido",IF(O135>910,"Alerta",IF(O135>820,"Alerta",IF(O135>730,"Alerta",IF(O135>=0,"Em dia","Vencido")))))) -> Alerta | O135: =$O$4-J135 -> 996 | P135: =K135-$P$3 -> 100 | Q135: =IF(OR(C135="ARN",C135="SDP"),MID(E135,4,7),MID(E135,4,6)) -> CN2-41
B136: 5 | C136: CN2 | D136: 51 | E136: GM-CN2-51_Transformadores imersos a oleo ate 35kV | F136: GM-CN2-51_Oil-immersed Transformer up to 35kV | G136: ENGENHARIA ELÉTRICA | H136: X | I136: X | J136: 45959 | K136: =J136+1096 -> 47055 | L136: Publicado | M136: =IF(O136="","",IF(O136>1095,"Vencido",IF(O136>910,"Alerta",IF(O136>820,"Alerta",IF(O136>730,"Alerta",IF(O136>=0,"Em dia","Vencido")))))) -> Em dia | O136: =$O$4-J136 -> 239 | P136: =K136-$P$3 -> 857 | Q136: =IF(OR(C136="ARN",C136="SDP"),MID(E136,4,7),MID(E136,4,6)) -> CN2-51
B137: 5 | C137: CN2 | D137: 53 | E137: GM-CN2-53_Linha de transmissão aérea | F137: GM-CN2-53_Overhead Transmission Line | G137: ENGENHARIA ELÉTRICA | H137: X | I137: X | J137: 45743 | K137: =J137+1096 -> 46839 | L137: Publicado | M137: =IF(O137="","",IF(O137>1095,"Vencido",IF(O137>910,"Alerta",IF(O137>820,"Alerta",IF(O137>730,"Alerta",IF(O137>=0,"Em dia","Vencido")))))) -> Em dia | O137: =$O$4-J137 -> 455 | P137: =K137-$P$3 -> 641 | Q137: =IF(OR(C137="ARN",C137="SDP"),MID(E137,4,7),MID(E137,4,6)) -> CN2-53
B138: 5 | C138: CN2 | D138: 56 | E138: GM-CN2-56_Proteção de Barras | F138: GM-CN2-56_Busbar Protection | G138: ENGENHARIA ELÉTRICA | H138: X | I138: X | J138: 46107 | K138: =J138+1096 -> 47203 | L138: Publicado | M138: =IF(O138="","",IF(O138>1095,"Vencido",IF(O138>910,"Alerta",IF(O138>820,"Alerta",IF(O138>730,"Alerta",IF(O138>=0,"Em dia","Vencido")))))) -> Em dia | O138: =$O$4-J138 -> 91 | P138: =K138-$P$3 -> 1005 | Q138: =IF(OR(C138="ARN",C138="SDP"),MID(E138,4,7),MID(E138,4,6)) -> CN2-56
B139: 5 | C139: CN2 | D139: 57 | E139: GM-CN2-57_Proteção de Linha de Transmissão | F139: GM-CN2-57_Transmission line protection | G139: ENGENHARIA ELÉTRICA | H139: X | I139: X | J139: 46107 | K139: =J139+1096 -> 47203 | L139: Publicado | M139: =IF(O139="","",IF(O139>1095,"Vencido",IF(O139>910,"Alerta",IF(O139>820,"Alerta",IF(O139>730,"Alerta",IF(O139>=0,"Em dia","Vencido")))))) -> Em dia | O139: =$O$4-J139 -> 91 | P139: =K139-$P$3 -> 1005 | Q139: =IF(OR(C139="ARN",C139="SDP"),MID(E139,4,7),MID(E139,4,6)) -> CN2-57
B140: 5 | C140: CN2 | D140: 58 | E140: GM-CN2-58_Sistema de ventilação | F140: GM-CN2-58_Ventilation System | G140: ENGENHARIA MECÂNICA | H140: X | I140: X | J140: 44739 | K140: =J140+1096 -> 45835 | L140: Publicado | M140: =IF(O140="","",IF(O140>1095,"Vencido",IF(O140>910,"Alerta",IF(O140>820,"Alerta",IF(O140>730,"Alerta",IF(O140>=0,"Em dia","Vencido")))))) -> Vencido | O140: =$O$4-J140 -> 1459 | P140: =K140-$P$3 -> -363 | Q140: =IF(OR(C140="ARN",C140="SDP"),MID(E140,4,7),MID(E140,4,6)) -> CN2-58
B141: 5 | C141: CN2 | D141: 59 | E141: GM-CN2-59_Sistema_CFTV | F141: GM-CN2-59_CCTV System | G141: ENGENHARIA ELÉTRICA | H141: X | I141: X | J141: 45462 | K141: =J141+1096 -> 46558 | L141: Publicado | M141: =IF(O141="","",IF(O141>1095,"Vencido",IF(O141>910,"Alerta",IF(O141>820,"Alerta",IF(O141>730,"Alerta",IF(O141>=0,"Em dia","Vencido")))))) -> Alerta | O141: =$O$4-J141 -> 736 | P141: =K141-$P$3 -> 360 | Q141: =IF(OR(C141="ARN",C141="SDP"),MID(E141,4,7),MID(E141,4,6)) -> CN2-59
B142: 5 | C142: CN2 | D142: 60 | E142: GM-CN2-60_Sistema anti incêndio | F142: GM-CN2-60_Firefighting System | G142: ENGENHARIA MECÂNICA | H142: X | I142: X | J142: 44819 | K142: =J142+1096 -> 45915 | L142: Publicado | M142: =IF(O142="","",IF(O142>1095,"Vencido",IF(O142>910,"Alerta",IF(O142>820,"Alerta",IF(O142>730,"Alerta",IF(O142>=0,"Em dia","Vencido")))))) -> Vencido | O142: =$O$4-J142 -> 1379 | P142: =K142-$P$3 -> -283 | Q142: =IF(OR(C142="ARN",C142="SDP"),MID(E142,4,7),MID(E142,4,6)) -> CN2-60
B143: 5 | C143: CN2 | D143: 61 | E143: GM-CN2-61_Comporta de vertedouro | F143: GM-CN2-61_Spillway Gate | G143: ENGENHARIA MECÂNICA | H143: X | I143: X | J143: 44926 | K143: =J143+1096 -> 46022 | L143: Publicado | M143: =IF(O143="","",IF(O143>1095,"Vencido",IF(O143>910,"Alerta",IF(O143>820,"Alerta",IF(O143>730,"Alerta",IF(O143>=0,"Em dia","Vencido")))))) -> Vencido | O143: =$O$4-J143 -> 1272 | P143: =K143-$P$3 -> -176 | Q143: =IF(OR(C143="ARN",C143="SDP"),MID(E143,4,7),MID(E143,4,6)) -> CN2-61
B144: 5 | C144: CN2 | D144: 62 | E144: GM-CN2-62_Comporta de emergência | F144: GM-CN2-62_Emergency Gate | G144: ENGENHARIA MECÂNICA | H144: X | I144: X | J144: 44926 | K144: =J144+1096 -> 46022 | L144: Publicado | M144: =IF(O144="","",IF(O144>1095,"Vencido",IF(O144>910,"Alerta",IF(O144>820,"Alerta",IF(O144>730,"Alerta",IF(O144>=0,"Em dia","Vencido")))))) -> Vencido | O144: =$O$4-J144 -> 1272 | P144: =K144-$P$3 -> -176 | Q144: =IF(OR(C144="ARN",C144="SDP"),MID(E144,4,7),MID(E144,4,6)) -> CN2-62
B145: 5 | C145: CN2 | D145: 65 | E145: GM-CN2-65_Comporta de emergência Sistema hidráulico | F145: GM-CN2-65_Hydraulic Hoist (emergency） | G145: ENGENHARIA MECÂNICA | H145: X | I145: X | J145: 45202 | K145: =J145+1096 -> 46298 | L145: Publicado | M145: =IF(O145="","",IF(O145>1095,"Vencido",IF(O145>910,"Alerta",IF(O145>820,"Alerta",IF(O145>730,"Alerta",IF(O145>=0,"Em dia","Vencido")))))) -> Alerta | O145: =$O$4-J145 -> 996 | P145: =K145-$P$3 -> 100 | Q145: =IF(OR(C145="ARN",C145="SDP"),MID(E145,4,7),MID(E145,4,6)) -> CN2-65
B146: 5 | C146: CN2 | D146: 65 | E146: GM-CN2-65_Comporta vertedor Sistema hidráulico | F146: GM-CN2-65_Hydraulic Hoist (spillway） | G146: ENGENHARIA MECÂNICA | H146: X | I146: X | J146: 45202 | K146: =J146+1096 -> 46298 | L146: Publicado | M146: =IF(O146="","",IF(O146>1095,"Vencido",IF(O146>910,"Alerta",IF(O146>820,"Alerta",IF(O146>730,"Alerta",IF(O146>=0,"Em dia","Vencido")))))) -> Alerta | O146: =$O$4-J146 -> 996 | P146: =K146-$P$3 -> 100 | Q146: =IF(OR(C146="ARN",C146="SDP"),MID(E146,4,7),MID(E146,4,6)) -> CN2-65
B147: 5 | C147: CN2 | D147: 71 | E147: GM-CN2-71_Instrução de Manutenção Preditiva (MDM) | F147: GM-CN2-71_Predictive Maintenance System (MDM) | G147: ENGENHARIA CONFIABILIDADE E PERFORMANCE | H147: X | I147: X | J147: 45202 | K147: =J147+1096 -> 46298 | L147: Publicado | M147: =IF(O147="","",IF(O147>1095,"Vencido",IF(O147>910,"Alerta",IF(O147>820,"Alerta",IF(O147>730,"Alerta",IF(O147>=0,"Em dia","Vencido")))))) -> Alerta | O147: =$O$4-J147 -> 996 | P147: =K147-$P$3 -> 100 | Q147: =IF(OR(C147="ARN",C147="SDP"),MID(E147,4,7),MID(E147,4,6)) -> CN2-71
... B151: 5 | C151: CN2 | D151: 63 | E151: GM-CN2-63_Pórtico de jusante | F151: GM-CN2-63_Downstream Gantry Crane | G151: ENGENHARIA MECÂNICA | H151: X | I151: X | J151: 44838 | K151: =J151+1096 -> 45934 | L151: Publicado | M151: =IF(O151="","",IF(O151>1095,"Vencido",IF(O151>910,"Alerta",IF(O151>820,"Alerta",IF(O151>730,"Alerta",IF(O151>=0,"Em dia","Vencido")))))) -> Vencido | O151: =$O$4-J151 -> 1360 | P151: =K151-$P$3 -> -264 | Q151: =IF(OR(C151="ARN",C151="SDP"),MID(E151,4,7),MID(E151,4,6)) -> CN2-63
B152: 5 | C152: CN2 | D152: 86 | E152: GM-CN2-86_Sistema de cloro pastilha | F152: GM-CN2-86_Tablet chlorine system | G152: ENGENHARIA MECÂNICA | H152: X | J152: 45274 | K152: =J152+1096 -> 46370 | L152: Publicado | M152: =IF(O152="","",IF(O152>1095,"Vencido",IF(O152>910,"Alerta",IF(O152>820,"Alerta",IF(O152>730,"Alerta",IF(O152>=0,"Em dia","Vencido")))))) -> Alerta | O152: =$O$4-J152 -> 924 | P152: =K152-$P$3 -> 172 | Q152: =IF(OR(C152="ARN",C152="SDP"),MID(E152,4,7),MID(E152,4,6)) -> CN2-86
B153: 6 | C153: CPV | D153: 0 | E153: GM-CPV-00_Atividades antes e depois da MPP | F153: GM-CPV-00_Activities before and after MPP | G153: ENGENHARIA | H153: X | J153: 45202 | K153: =J153+1096 -> 46298 | L153: Publicado | M153: =IF(O153="","",IF(O153>1095,"Vencido",IF(O153>910,"Alerta",IF(O153>820,"Alerta",IF(O153>730,"Alerta",IF(O153>=0,"Em dia","Vencido")))))) -> Alerta | O153: =$O$4-J153 -> 996 | P153: =K153-$P$3 -> 100 | Q153: =IF(OR(C153="ARN",C153="SDP"),MID(E153,4,7),MID(E153,4,6)) -> CPV-00
B154: 6 | C154: CPV | D154: 1 | E154: GM-CPV-01_Guia de Manutenção da Turbina e seus equipamentos auxiliares | F154: GM-CPV-01_Turbine and its Auxiliary Equipment | G154: ENGENHARIA MECÂNICA | H154: X | I154: X | J154: 44739 | K154: =J154+1096 -> 45835 | L154: Publicado | M154: =IF(O154="","",IF(O154>1095,"Vencido",IF(O154>910,"Alerta",IF(O154>820,"Alerta",IF(O154>730,"Alerta",IF(O154>=0,"Em dia","Vencido")))))) -> Vencido | O154: =$O$4-J154 -> 1459 | P154: =K154-$P$3 -> -363 | Q154: =IF(OR(C154="ARN",C154="SDP"),MID(E154,4,7),MID(E154,4,6)) -> CPV-01
...

Sheet MM
B2: MM - MANUAIS DE MANUTENÇÃO (MAINTENANCE MANUAL)
N4: =COUNTIF(N5:N1525,"X") -> 482 | P4: =TODAY() -> 46198
B5: UHE | C5: UHE | D5: Nº EQUIP | E5: SUB ITEM | F5: CÓDIGO | G5: DESCRIÇÃO | H5: DESCRIÇÃO COMPLETA | I5: Observação | J5: Area | K5: Data Publicação | L5: Data Vencimento | M5: Status | N5: Por.
B6: 0 | C6: UHE | D6: 18 | E6: 1 | F6: MM-UHE-018.01 | G6: Regulador Integrado Velocidade e Tensao - RTVX G2 | H6: =(F6)&" - "&(G6) -> MM-UHE-018.01 - Regulador Integrado Velocidade e Tensao - RTVX G2 | I6: Manual Sistema de Excitação | J6: =VLOOKUP(D6,GM!$D$4:$G$1637,4,3)&" e "&C6 -> ENGENHARIA ELÉTRICA e UHE | K6: 45274 | L6: =K6+1096 -> 46370 | M6: Publicado | N6: x | O6: =IF(Q6="","",IF(Q6>1095,"Vencido",IF(Q6>910,"Alerta",IF(Q6>820,"Alerta",IF(Q6>730,"Alerta",IF(Q6>=0,"Em dia","Vencido")))))) -> Alerta | Q6: =$P$4-K6 -> 924
B7: 1 | C7: JUR | D7: 0 | E7: 2 | F7: MM-JUR-000.02 | G7: Procedimentos Execução Mergulho Profissional | H7: =(F7)&" - "&(G7) -> MM-JUR-000.02 - Procedimentos Execução Mergulho Profissional | I7: Manual Atividades antes e depois da MPP | J7: =VLOOKUP(D7,GM!$D$4:$G$1637,4,3)&" e "&C7 -> ENGENHARIA e JUR | K7: 44063 | L7: =K7+1096 -> 45159 | M7: Publicado | N7: x | O7: =IF(Q7="","",IF(Q7>1095,"Vencido",IF(Q7>910,"Alerta",IF(Q7>820,"Alerta",IF(Q7>730,"Alerta",IF(Q7>=0,"Em dia","Vencido")))))) -> Vencido | Q7: =$P$4-K7 -> 2135
B8: 1 | C8: JUR | D8: 1 | E8: 2 | F8: MM-JUR-001.02 | G8: Procedimentos Para Ajustes de Verticalidade e Mancais | H8: =(F8)&" - "&(G8) -> MM-JUR-001.02 - Procedimentos Para Ajustes de Verticalidade e Mancais | I8: Manual Turbina | J8: =VLOOKUP(D8,GM!$D$4:$G$1637,4,3)&" e "&C8 -> ENGENHARIA MECÂNICA e JUR | K8: 44053 | L8: =K8+1096 -> 45149 | M8: Publicado | N8: x | O8: =IF(Q8="","",IF(Q8>1095,"Vencido",IF(Q8>910,"Alerta",IF(Q8>820,"Alerta",IF(Q8>730,"Alerta",IF(Q8>=0,"Em dia","Vencido")))))) -> Vencido | Q8: =$P$4-K8 -> 2145
B9: 1 | C9: JUR | D9: 1 | E9: 25 | F9: MM-JUR-001.25 | G9: Plano de Lubrificação da Turbina | H9: =(F9)&" - "&(G9) -> MM-JUR-001.25 - Plano de Lubrificação da Turbina | I9: Manual Turbina | J9: =VLOOKUP(D9,GM!$D$4:$G$1637,4,3)&" e "&C9 -> ENGENHARIA MECÂNICA e JUR | K9: 44063 | L9: =K9+1096 -> 45159 | M9: Publicado | N9: x | O9: =IF(Q9="","",IF(Q9>1095,"Vencido",IF(Q9>910,"Alerta",IF(Q9>820,"Alerta",IF(Q9>730,"Alerta",IF(Q9>=0,"Em dia","Vencido")))))) -> Vencido | Q9: =$P$4-K9 -> 2135
B10: 1 | C10: JUR | D10: 6 | E10: 1 | F10: MM-JUR-006.00 | G10: Coleta de Amostras de Óleo Isolante | H10: =(F10)&" - "&(G10) -> MM-JUR-006.00 - Coleta de Amostras de Óleo Isolante | I10: Manual Transformador Elevador | J10: =VLOOKUP(D10,GM!$D$4:$G$1637,4,3)&" e "&C10 -> ENGENHARIA ELÉTRICA e JUR | K10: 45743 | L10: =K10+1096 -> 46839 | M10: Publicado | N10: x | O10: =IF(Q10="","",IF(Q10>1095,"Vencido",IF(Q10>910,"Alerta",IF(Q10>820,"Alerta",IF(Q10>730,"Alerta",IF(Q10>=0,"Em dia","Vencido")))))) -> Em dia | Q10: =$P$4-K10 -> 455
B11: 1 | C11: JUR | D11: 20 | E11: 6 | F11: MM-JUR-020.06 | G11: Plano de Lubrificação do RV | H11: =(F11)&" - "&(G11) -> MM-JUR-020.06 - Plano de Lubrificação do RV | I11: Manual Regulador de Velocidade - Parte Mecânica | J11: =VLOOKUP(D11,GM!$D$4:$G$1637,4,3)&" e "&C11 -> ENGENHARIA MECÂNICA e JUR | K11: 44071 | L11: =K11+1096 -> 45167 | M11: Publicado | N11: x | O11: =IF(Q11="","",IF(Q11>1095,"Vencido",IF(Q11>910,"Alerta",IF(Q11>820,"Alerta",IF(Q11>730,"Alerta",IF(Q11>=0,"Em dia","Vencido")))))) -> Vencido | Q11: =$P$4-K11 -> 2127
B12: 1 | C12: JUR | D12: 22 | E12: 3 | F12: MM-JUR-022.03 | G12: Plano de Lubrificação dos Compressores | H12: =(F12)&" - "&(G12) -> MM-JUR-022.03 - Plano de Lubrificação dos Compressores | I12: Manual Compressores | J12: =VLOOKUP(D12,GM!$D$4:$G$1637,4,3)&" e "&C12 -> ENGENHARIA MECÂNICA e JUR | K12: 44071 | L12: =K12+1096 -> 45167 | M12: Publicado | N12: x | O12: =IF(Q12="","",IF(Q12>1095,"Vencido",IF(Q12>910,"Alerta",IF(Q12>820,"Alerta",IF(Q12>730,"Alerta",IF(Q12>=0,"Em dia","Vencido")))))) -> Vencido | Q12: =$P$4-K12 -> 2127
B13: 1 | C13: JUR | D13: 23 | E13: 3 | F13: MM-JUR-023.03 | G13: Plano de Lubrificação do sistema de Refrigeração | H13: =(F13)&" - "&(G13) -> MM-JUR-023.03 - Plano de Lubrificação do sistema de Refrigeração | I13: Manual Sistema de água de refrigeração | J13: =VLOOKUP(D13,GM!$D$4:$G$1637,4,3)&" e "&C13 -> ENGENHARIA MECÂNICA e JUR | K13: 44071 | L13: =K13+1096 -> 45167 | M13: Publicado | N13: x | O13: =IF(Q13="","",IF(Q13>1095,"Vencido",IF(Q13>910,"Alerta",IF(Q13>820,"Alerta",IF(Q13>730,"Alerta",IF(Q13>=0,"Em dia","Vencido")))))) -> Vencido | Q13: =$P$4-K13 -> 2127
B14: 1 | C14: JUR | D14: 24 | E14: 1 | F14: MM-JUR-024.01 | G14: Procedimento Para Reabastecimento dos GAE | H14: =(F14)&" - "&(G14) -> MM-JUR-024.01 - Procedimento Para Reabastecimento dos GAE | I14: Manual Gerador Diesel | J14: =VLOOKUP(D14,GM!$D$4:$G$1637,4,3)&" e "&C14 -> ENGENHARIA MECÂNICA e JUR | K14: 44062 | L14: =K14+1096 -> 45158 | M14: Publicado | N14: x | O14: =IF(Q14="","",IF(Q14>1095,"Vencido",IF(Q14>910,"Alerta",IF(Q14>820,"Alerta",IF(Q14>730,"Alerta",IF(Q14>=0,"Em dia","Vencido")))))) -> Vencido | Q14: =$P$4-K14 -> 2136
B15: 1 | C15: JUR | D15: 24 | E15: 4 | F15: MM-JUR-024.04 | G15: Plano de Lubrificação do GAE | H15: =(F15)&" - "&(G15) -> MM-JUR-024.04 - Plano de Lubrificação do GAE | I15: Manual Gerador Diesel | J15: =VLOOKUP(D15,GM!$D$4:$G$1637,4,3)&" e "&C15 -> ENGENHARIA MECÂNICA e JUR | K15: 44071 | L15: =K15+1096 -> 45167 | M15: Publicado | N15: x | O15: =IF(Q15="","",IF(Q15>1095,"Vencido",IF(Q15>910,"Alerta",IF(Q15>820,"Alerta",IF(Q15>730,"Alerta",IF(Q15>=0,"Em dia","Vencido")))))) -> Vencido | Q15: =$P$4-K15 -> 2127
B16: 1 | C16: JUR | D16: 26 | E16: 7 | F16: MM-JUR-026.07 | G16: Plano de Lubrificação do Sistema Drenagem e Esg | H16: =(F16)&" - "&(G16) -> MM-JUR-026.07 - Plano de Lubrificação do Sistema Drenagem e Esg | I16: Manual Sistema de drenagem e esgotamento | J16: =VLOOKUP(D16,GM!$D$4:$G$1637,4,3)&" e "&C16 -> ENGENHARIA MECÂNICA e JUR | K16: 44071 | L16: =K16+1096 -> 45167 | M16: Publicado | N16: x | O16: =IF(Q16="","",IF(Q16>1095,"Vencido",IF(Q16>910,"Alerta",IF(Q16>820,"Alerta",IF(Q16>730,"Alerta",IF(Q16>=0,"Em dia","Vencido")))))) -> Vencido | Q16: =$P$4-K16 -> 2127
B17: 1 | C17: JUR | D17: 28 | E17: 2 | F17: MM-JUR-028.02 | G17: Procedimento Manuseio Comportas de Manutenção | H17: =(F17)&" - "&(G17) -> MM-JUR-028.02 - Procedimento Manuseio Comportas de Manutenção | I17: Manual Comporta de Manutenção | J17: =VLOOKUP(D17,GM!$D$4:$G$1637,4,3)&" e "&C17 -> ENGENHARIA MECÂNICA e JUR | K17: 44062 | L17: =K17+1096 -> 45158 | M17: Publicado | N17: x | O17: =IF(Q17="","",IF(Q17>1095,"Vencido",IF(Q17>910,"Alerta",IF(Q17>820,"Alerta",IF(Q17>730,"Alerta",IF(Q17>=0,"Em dia","Vencido")))))) -> Vencido | Q17: =$P$4-K17 -> 2136
... B52: 3 | C52: SAG | D52: 3 | E52: 2 | F52: MM-SAG-003.02 | G52: Manutenção Preventiva Periódica Tipo MPP2 no Gerador | H52: =(F52)&" - "&(G52) -> MM-SAG-003.02 - Manutenção Preventiva Periódica Tipo MPP2 no Gerador | I52: Gerador-Parte elétrica | J52: =VLOOKUP(D52,GM!$D$4:$G$1637,4,3)&" e "&C52 -> ENGENHARIA ELÉTRICA e SAG | K52: 45791 | L52: =K52+1096 -> 46887 | M52: Publicado | N52: x | O52: =IF(Q52="","",IF(Q52>1095,"Vencido",IF(Q52>910,"Alerta",IF(Q52>820,"Alerta",IF(Q52>730,"Alerta",IF(Q52>=0,"Em dia","Vencido")))))) -> Em dia | Q52: =$P$4-K52 -> 407
B53: 3 | C53: SAG | D53: 4 | E53: 0 | F53: MM-SAG-004.00 | G53: Manutenção Preventiva Periódica Tipo 0 no Sistemas Auxiliares da Unidade Geradora | H53: =(F53)&" - "&(G53) -> MM-SAG-004.00 - Manutenção Preventiva Periódica Tipo 0 no Sistemas Auxiliares da Unidade Geradora | I53: Sistemas Auxiliares da Unidade Geradora | J53: =VLOOKUP(D53,GM!$D$4:$G$1637,4,3)&" e "&C53 -> ENGENHARIA ELÉTRICA e SAG | M53: Desenvolvimento | O53: =IF(Q53="","",IF(Q53>1095,"Vencido",IF(Q53>910,"Alerta",IF(Q53>820,"Alerta",IF(Q53>730,"Alerta",IF(Q53>=0,"Em dia","Vencido")))))) -> Vencido | Q53: =$P$4-K53 -> 46198
B54: 3 | C54: SAG | D54: 4 | E54: 0 | F54: MM-SAG-004.01 | G54: Manutenção Preventiva Periódica Tipo 1 no Sistemas Auxiliares da Unidade Geradora | H54: =(F54)&" - "&(G54) -> MM-SAG-004.01 - Manutenção Preventiva Periódica Tipo 1 no Sistemas Auxiliares da Unidade Geradora | I54: Sistemas Auxiliares da Unidade Geradora | J54: =VLOOKUP(D54,GM!$D$4:$G$1637,4,3)&" e "&C54 -> ENGENHARIA ELÉTRICA e SAG | M54: Desenvolvimento | O54: =IF(Q54="","",IF(Q54>1095,"Vencido",IF(Q54>910,"Alerta",IF(Q54>820,"Alerta",IF(Q54>730,"Alerta",IF(Q54>=0,"Em dia","Vencido")))))) -> Vencido | Q54: =$P$4-K54 -> 46198
B55: 3 | C55: SAG | D55: 4 | E55: 0 | F55: MM-SAG-004.02 | G55: Manutenção Preventiva Periódica Tipo 2 no Sistemas Auxiliares da Unidade Geradora | H55: =(F55)&" - "&(G55) -> MM-SAG-004.02 - Manutenção Preventiva Periódica Tipo 2 no Sistemas Auxiliares da Unidade Geradora | I55: Sistemas Auxiliares da Unidade Geradora | J55: =VLOOKUP(D55,GM!$D$4:$G$1637,4,3)&" e "&C55 -> ENGENHARIA ELÉTRICA e SAG | M55: Desenvolvimento | O55: =IF(Q55="","",IF(Q55>1095,"Vencido",IF(Q55>910,"Alerta",IF(Q55>820,"Alerta",IF(Q55>730,"Alerta",IF(Q55>=0,"Em dia","Vencido")))))) -> Vencido | Q55: =$P$4-K55 -> 46198
B56: 3 | C56: SAG | D56: 6 | E56: 0 | F56: MM-SAG-006.00 | G56: Coleta de Amostras de Óleo Isolante | H56: =(F56)&" - "&(G56) -> MM-SAG-006.00 - Coleta de Amostras de Óleo Isolante | I56: Transformador Elevador | J56: =VLOOKUP(D56,GM!$D$4:$G$1637,4,3)&" e "&C56 -> ENGENHARIA ELÉTRICA e SAG | K56: 45743 | L56: =K56+1096 -> 46839 | M56: Publicado | N56: x | O56: =IF(Q56="","",IF(Q56>1095,"Vencido",IF(Q56>910,"Alerta",IF(Q56>820,"Alerta",IF(Q56>730,"Alerta",IF(Q56>=0,"Em dia","Vencido")))))) -> Em dia | Q56: =$P$4-K56 -> 455
B57: 3 | C57: SAG | D57: 13 | E57: 3 | F57: MM-SAG-013.03 | G57: Intervenção nos Controladores Lógicos Programáveis Siemens | H57: =(F57)&" - "&(G57) -> MM-SAG-013.03 - Intervenção nos Controladores Lógicos Programáveis Siemens | I57: Gerador-Parte elétrica | J57: =VLOOKUP(D57,GM!$D$4:$G$1637,4,3)&" e "&C57 -> ENGENHARIA ELÉTRICA e SAG | K57: 45791 | L57: =K57+1096 -> 46887 | M57: Publicado | N57: x | O57: =IF(Q57="","",IF(Q57>1095,"Vencido",IF(Q57>910,"Alerta",IF(Q57>820,"Alerta",IF(Q57>730,"Alerta",IF(Q57>=0,"Em dia","Vencido")))))) -> Em dia | Q57: =$P$4-K57 -> 407
B58: 3 | C58: SAG | D58: 15 | E58: 1 | F58: MM-SAG-015.01 | G58: Comunicação Relés Proteção SIPROTEC 4 e 5 | H58: =(F58)&" - "&(G58) -> MM-SAG-015.01 - Comunicação Relés Proteção SIPROTEC 4 e 5 | I58: Proteção da Unidade Geradora | J58: =VLOOKUP(D58,GM!$D$4:$G$1637,4,3)&" e "&C58 -> ENGENHARIA ELÉTRICA e SAG | K58: 45755 | L58: =K58+1096 -> 46851 | M58: Publicado | N58: x | O58: =IF(Q58="","",IF(Q58>1095,"Vencido",IF(Q58>910,"Alerta",IF(Q58>820,"Alerta",IF(Q58>730,"Alerta",IF(Q58>=0,"Em dia","Vencido")))))) -> Em dia | Q58: =$P$4-K58 -> 443
B59: 3 | C59: SAG | D59: 21 | E59: 0 | F59: MM-SAG-021.00 | G59: Manutenção Preventiva Periódica Tipo 0 no Regulador de Velocidade – Partes Elétricas | H59: =(F59)&" - "&(G59) -> MM-SAG-021.00 - Manutenção Preventiva Periódica Tipo 0 no Regulador de Velocidade – Partes Elétricas | I59: Regulador de Velocidade - Parte Elétrica | J59: =VLOOKUP(D59,GM!$D$4:$G$1637,4,3)&" e "&C59 -> ENGENHARIA ELÉTRICA e SAG | M59: Desenvolvimento | O59: =IF(Q59="","",IF(Q59>1095,"Vencido",IF(Q59>910,"Alerta",IF(Q59>820,"Alerta",IF(Q59>730,"Alerta",IF(Q59>=0,"Em dia","Vencido")))))) -> Vencido | Q59: =$P$4-K59 -> 46198
B60: 3 | C60: SAG | D60: 21 | E60: 1 | F60: MM-SAG-021.01 | G60: Manutenção Preventiva Periódica Tipo 1 no Regulador de Velocidade – Partes Elétricas | H60: =(F60)&" - "&(G60) -> MM-SAG-021.01 - Manutenção Preventiva Periódica Tipo 1 no Regulador de Velocidade – Partes Elétricas | I60: Regulador de Velocidade - Parte Elétrica | J60: =VLOOKUP(D60,GM!$D$4:$G$1637,4,3)&" e "&C60 -> ENGENHARIA ELÉTRICA e SAG | M60: Desenvolvimento | O60: =IF(Q60="","",IF(Q60>1095,"Vencido",IF(Q60>910,"Alerta",IF(Q60>820,"Alerta",IF(Q60>730,"Alerta",IF(Q60>=0,"Em dia","Vencido")))))) -> Vencido | Q60: =$P$4-K60 -> 46198
B61: 3 | C61: SAG | D61: 21 | E61: 2 | F61: MM-SAG-021.02 | G61: Manutenção Preventiva Periódica Tipo 2 no Regulador de Velocidade – Partes Elétricas | H61: =(F61)&" - "&(G61) -> MM-SAG-021.02 - Manutenção Preventiva Periódica Tipo 2 no Regulador de Velocidade – Partes Elétricas | I61: Regulador de Velocidade - Parte Elétrica | J61: =VLOOKUP(D61,GM!$D$4:$G$1637,4,3)&" e "&C61 -> ENGENHARIA ELÉTRICA e SAG | M61: Desenvolvimento | O61: =IF(Q61="","",IF(Q61>1095,"Vencido",IF(Q61>910,"Alerta",IF(Q61>820,"Alerta",IF(Q61>730,"Alerta",IF(Q61>=0,"Em dia","Vencido")))))) -> Vencido | Q61: =$P$4-K61 -> 46198
B62: 3 | C62: SAG | D62: 22 | E62: 3 | F62: MM-SAG-022.03 | G62: Plano de Lubrificação dos Compressores | H62: =(F62)&" - "&(G62) -> MM-SAG-022.03 - Plano de Lubrificação dos Compressores | I62: Manual Compressores | J62: =VLOOKUP(D62,GM!$D$4:$G$1637,4,3)&" e "&C62 -> ENGENHARIA MECÂNICA e SAG | K62: 44083 | L62: =K62+1096 -> 45179 | M62: Publicado | N62: x | O62: =IF(Q62="","",IF(Q62>1095,"Vencido",IF(Q62>910,"Alerta",IF(Q62>820,"Alerta",IF(Q62>730,"Alerta",IF(Q62>=0,"Em dia","Vencido")))))) -> Vencido | Q62: =$P$4-K62 -> 2115
B63: 3 | C63: SAG | D63: 23 | E63: 3 | F63: MM-SAG-023.03 | G63: Plano de Lubrificação do sistema de Refrigeração | H63: =(F63)&" - "&(G63) -> MM-SAG-023.03 - Plano de Lubrificação do sistema de Refrigeração | I63: Manual Sistema de água de refrigeração | J63: =VLOOKUP(D63,GM!$D$4:$G$1637,4,3)&" e "&C63 -> ENGENHARIA MECÂNICA e SAG | K63: 44083 | L63: =K63+1096 -> 45179 | M63: Publicado | N63: x | O63: =IF(Q63="","",IF(Q63>1095,"Vencido",IF(Q63>910,"Alerta",IF(Q63>820,"Alerta",IF(Q63>730,"Alerta",IF(Q63>=0,"Em dia","Vencido")))))) -> Vencido | Q63: =$P$4-K63 -> 2115
B64: 3 | C64: SAG | D64: 24 | E64: 1 | F64: MM-SAG-024.01 | G64: Procedimento Para Reabastecimento dos GAE | H64: =(F64)&" - "&(G64) -> MM-SAG-024.01 - Procedimento Para Reabastecimento dos GAE | I64: Manual Gerador Diesel | J64: =VLOOKUP(D64,GM!$D$4:$G$1637,4,3)&" e "&C64 -> ENGENHARIA MECÂNICA e SAG | K64: 44062 | L64: =K64+1096 -> 45158 | M64: Publicado | N64: x | O64: =IF(Q64="","",IF(Q64>1095,"Vencido",IF(Q64>910,"Alerta",IF(Q64>820,"Alerta",IF(Q64>730,"Alerta",IF(Q64>=0,"Em dia","Vencido")))))) -> Vencido | Q64: =$P$4-K64 -> 2136
B65: 3 | C65: SAG | D65: 24 | E65: 4 | F65: MM-SAG-024.04 | G65: Plano de Lubrificação do GAE | H65: =(F65)&" - "&(G65) -> MM-SAG-024.04 - Plano de Lubrificação do GAE | I65: Manual Gerador Diesel | J65: =VLOOKUP(D65,GM!$D$4:$G$1637,4,3)&" e "&C65 -> ENGENHARIA MECÂNICA e SAG | K65: 44083 | L65: =K65+1096 -> 45179 | M65: Publicado | N65: x | O65: =IF(Q65="","",IF(Q65>1095,"Vencido",IF(Q65>910,"Alerta",IF(Q65>820,"Alerta",IF(Q65>730,"Alerta",IF(Q65>=0,"Em dia","Vencido")))))) -> Vencido | Q65: =$P$4-K65 -> 2115
B66: 3 | C66: SAG | D66: 26 | E66: 0 | F66: MM-SAG-026.00 | G66: Sistema de Drenagem - MCP0 | H66: =(F66)&" - "&(G66) -> MM-SAG-026.00 - Sistema de Drenagem - MCP0 | I66: Manual Sistema de drenagem e esgotamento | J66: =VLOOKUP(D66,GM!$D$4:$G$1637,4,3)&" e "&C66 -> ENGENHARIA MECÂNICA e SAG | M66: Desenvolvimento | O66: =IF(Q66="","",IF(Q66>1095,"Vencido",IF(Q66>910,"Alerta",IF(Q66>820,"Alerta",IF(Q66>730,"Alerta",IF(Q66>=0,"Em dia","Vencido")))))) -> Vencido | Q66: =$P$4-K66 -> 46198
B67: 3 | C67: SAG | D67: 26 | E67: 1 | F67: MM-SAG-026.01 | G67: Sistema de Drenagem - MCP1 | H67: =(F67)&" - "&(G67) -> MM-SAG-026.01 - Sistema de Drenagem - MCP1 | I67: Manual Sistema de drenagem e esgotamento | J67: =VLOOKUP(D67,GM!$D$4:$G$1637,4,3)&" e "&C67 -> ENGENHARIA MECÂNICA e SAG | M67: Desenvolvimento | O67: =IF(Q67="","",IF(Q67>1095,"Vencido",IF(Q67>910,"Alerta",IF(Q67>820,"Alerta",IF(Q67>730,"Alerta",IF(Q67>=0,"Em dia","Vencido")))))) -> Vencido | Q67: =$P$4-K67 -> 46198
B68: 3 | C68: SAG | D68: 26 | E68: 7 | F68: MM-SAG-026.07 | G68: Plano de Lubrificação do Sistema Drenagem e Esg | H68: =(F68)&" - "&(G68) -> MM-SAG-026.07 - Plano de Lubrificação do Sistema Drenagem e Esg | I68: Manual Sistema de drenagem e esgotamento | J68: =VLOOKUP(D68,GM!$D$4:$G$1637,4,3)&" e "&C68 -> ENGENHARIA MECÂNICA e SAG | K68: 44083 | L68: =K68+1096 -> 45179 | M68: Publicado | N68: x | O68: =IF(Q68="","",IF(Q68>1095,"Vencido",IF(Q68>910,"Alerta",IF(Q68>820,"Alerta",IF(Q68>730,"Alerta",IF(Q68>=0,"Em dia","Vencido")))))) -> Vencido | Q68: =$P$4-K68 -> 2115
B69: 3 | C69: SAG | D69: 28 | E69: 2 | F69: MM-SAG-028.02 | G69: Procedimento Manuseio Comportas de Manutenção | H69: =(F69)&" - "&(G69) -> MM-SAG-028.02 - Procedimento Manuseio Comportas de Manutenção | I69: Manual Comporta de Manutenção | J69: =VLOOKUP(D69,GM!$D$4:$G$1637,4,3)&" e "&C69 -> ENGENHARIA MECÂNICA e SAG | K69: 44062 | L69: =K69+1096 -> 45158 | M69: Publicado | N69: x | O69: =IF(Q69="","",IF(Q69>1095,"Vencido",IF(Q69>910,"Alerta",IF(Q69>820,"Alerta",IF(Q69>730,"Alerta",IF(Q69>=0,"Em dia","Vencido")))))) -> Vencido | Q69: =$P$4-K69 -> 2136
B70: 3 | C70: SAG | D70: 30 | E70: 0 | F70: MM-SAG-030.00 | G70: Manutençao Preventiva Pórtico 50T MCP0) | H70: =(F70)&" - "&(G70) -> MM-SAG-030.00 - Manutençao Preventiva Pórtico 50T MCP0) | I70: Manual Pórtico Montante | J70: =VLOOKUP(D70,GM!$D$4:$G$1637,4,3)&" e "&C70 -> ENGENHARIA MECÂNICA e SAG | M70: Desenvolvimento | O70: =IF(Q70="","",IF(Q70>1095,"Vencido",IF(Q70>910,"Alerta",IF(Q70>820,"Alerta",IF(Q70>730,"Alerta",IF(Q70>=0,"Em dia","Vencido")))))) -> Vencido | Q70: =$P$4-K70 -> 46198
B71: 3 | C71: SAG | D71: 30 | E71: 1 | F71: MM-SAG-030.01 | G71: Plano de Lubrificação do Pórtico Montante | H71: =(F71)&" - "&(G71) -> MM-SAG-030.01 - Plano de Lubrificação do Pórtico Montante | I71: Manual Pórtico Montante | J71: =VLOOKUP(D71,GM!$D$4:$G$1637,4,3)&" e "&C71 -> ENGENHARIA MECÂNICA e SAG | K71: 44083 | L71: =K71+1096 -> 45179 | M71: Publicado | N71: x | O71: =IF(Q71="","",IF(Q71>1095,"Vencido",IF(Q71>910,"Alerta",IF(Q71>820,"Alerta",IF(Q71>730,"Alerta",IF(Q71>=0,"Em dia","Vencido")))))) -> Vencido | Q71: =$P$4-K71 -> 2115
B72: 3 | C72: SAG | D72: 30 | E72: 2 | F72: MM-SAG-030.02 | G72: Manutenção Preventiva Pórtico 50T (MCP1) | H72: =(F72)&" - "&(G72) -> MM-SAG-030.02 - Manutenção Preventiva Pórtico 50T (MCP1) | I72: Manual Pórtico Montante | J72: =VLOOKUP(D72,GM!$D$4:$G$1637,4,3)&" e "&C72 -> ENGENHARIA MECÂNICA e SAG | M72: Desenvolvimento | O72: =IF(Q72="","",IF(Q72>1095,"Vencido",IF(Q72>910,"Alerta",IF(Q72>820,"Alerta",IF(Q72>730,"Alerta",IF(Q72>=0,"Em dia","Vencido")))))) -> Vencido | Q72: =$P$4-K72 -> 46198
B73: 3 | C73: SAG | D73: 30 | E73: 3 | F73: MM-SAG-030.03 | G73: Manutençao Preventiva Pórtico 12T (MCP0) | H73: =(F73)&" - "&(G73) -> MM-SAG-030.03 - Manutençao Preventiva Pórtico 12T (MCP0) | I73: Manual Pórtico Montante | J73: =VLOOKUP(D73,GM!$D$4:$G$1637,4,3)&" e "&C73 -> ENGENHARIA MECÂNICA e SAG | M73: Desenvolvimento | O73: =IF(Q73="","",IF(Q73>1095,"Vencido",IF(Q73>910,"Alerta",IF(Q73>820,"Alerta",IF(Q73>730,"Alerta",IF(Q73>=0,"Em dia","Vencido")))))) -> Vencido | Q73: =$P$4-K73 -> 46198
B74: 3 | C74: SAG | D74: 30 | E74: 4 | F74: MM-SAG-030.04 | G74: Manutençao Preventiva Pórtico 12T (MCP1) | H74: =(F74)&" - "&(G74) -> MM-SAG-030.04 - Manutençao Preventiva Pórtico 12T (MCP1) | I74: Manual Pórtico Montante | J74: =VLOOKUP(D74,GM!$D$4:$G$1637,4,3)&" e "&C74 -> ENGENHARIA MECÂNICA e SAG | M74: Desenvolvimento | O74: =IF(Q74="","",IF(Q74>1095,"Vencido",IF(Q74>910,"Alerta",IF(Q74>820,"Alerta",IF(Q74>730,"Alerta",IF(Q74>=0,"Em dia","Vencido")))))) -> Vencido | Q74: =$P$4-K74 -> 46198
B75: 3 | C75: SAG | D75: 31 | E75: 0 | F75: MM-SAG-031.00 | G75: Manutenção Preventiva Ponte Rolante 136_23T (MCP0) | H75: =(F75)&" - "&(G75) -> MM-SAG-031.00 - Manutenção Preventiva Ponte Rolante 136_23T (MCP0) | I75: Ponte Rolante Auxiliar | J75: =VLOOKUP(D75,GM!$D$4:$G$1637,4,3)&" e "&C75 -> ENGENHARIA MECÂNICA e SAG | M75: Desenvolvimento | O75: =IF(Q75="","",IF(Q75>1095,"Vencido",IF(Q75>910,"Alerta",IF(Q75>820,"Alerta",IF(Q75>730,"Alerta",IF(Q75>=0,"Em dia","Vencido")))))) -> Vencido | Q75: =$P$4-K75 -> 46198
B76: 3 | C76: SAG | D76: 31 | E76: 1 | F76: MM-SAG-031.01 | G76: Manutenção Preventiva Ponte Rolante 136_23T (MCP1) | H76: =(F76)&" - "&(G76) -> MM-SAG-031.01 - Manutenção Preventiva Ponte Rolante 136_23T (MCP1) | I76: Ponte Rolante Auxiliar | J76: =VLOOKUP(D76,GM!$D$4:$G$1637,4,3)&" e "&C76 -> ENGENHARIA MECÂNICA e SAG | M76: Desenvolvimento | O76: =IF(Q76="","",IF(Q76>1095,"Vencido",IF(Q76>910,"Alerta",IF(Q76>820,"Alerta",IF(Q76>730,"Alerta",IF(Q76>=0,"Em dia","Vencido")))))) -> Vencido | Q76: =$P$4-K76 -> 46198
B77: 3 | C77: SAG | D77: 31 | E77: 21 | F77: MM-SAG-031.21 | G77: Plano de Lubrificação da Ponte Rolante | H77: =(F77)&" - "&(G77) -> MM-SAG-031.21 - Plano de Lubrificação da Ponte Rolante | I77: Manual Ponte Rolante Princip | J77: =VLOOKUP(D77,GM!$D$4:$G$1637,4,3)&" e "&C77 -> ENGENHARIA MECÂNICA e SAG | K77: 44083 | L77: =K77+1096 -> 45179 | M77: Publicado | N77: x | O77: =IF(Q77="","",IF(Q77>1095,"Vencido",IF(Q77>910,"Alerta",IF(Q77>820,"Alerta",IF(Q77>730,"Alerta",IF(Q77>=0,"Em dia","Vencido")))))) -> Vencido | Q77: =$P$4-K77 -> 2115
B78: 3 | C78: SAG | D78: 33 | E78: 0 | F78: MM-SAG-033.00 | G78: MCP0 Elevador | H78: =(F78)&" - "&(G78) -> MM-SAG-033.00 - MCP0 Elevador | I78: Manual Elevador | J78: =VLOOKUP(D78,GM!$D$4:$G$1637,4,3)&" e "&C78 -> ENGENHARIA MECÂNICA e SAG | M78: Desenvolvimento | O78: =IF(Q78="","",IF(Q78>1095,"Vencido",IF(Q78>910,"Alerta",IF(Q78>820,"Alerta",IF(Q78>730,"Alerta",IF(Q78>=0,"Em dia","Vencido")))))) -> Vencido | Q78: =$P$4-K78 -> 46198
B79: 3 | C79: SAG | D79: 33 | E79: 1 | F79: MM-SAG-033.01 | G79: Plano de Lubrificação do Elevador | H79: =(F79)&" - "&(G79) -> MM-SAG-033.01 - Plano de Lubrificação do Elevador | I79: Manual Elevador | J79: =VLOOKUP(D79,GM!$D$4:$G$1637,4,3)&" e "&C79 -> ENGENHARIA MECÂNICA e SAG | K79: 44083 | L79: =K79+1096 -> 45179 | M79: Publicado | N79: x | O79: =IF(Q79="","",IF(Q79>1095,"Vencido",IF(Q79>910,"Alerta",IF(Q79>820,"Alerta",IF(Q79>730,"Alerta",IF(Q79>=0,"Em dia","Vencido")))))) -> Vencido | Q79: =$P$4-K79 -> 2115
B80: 3 | C80: SAG | D80: 41 | E80: 0 | F80: MM-SAG-041.00 | G80: Manutenção Preventiva SPDA - Escopo 2 | H80: =(F80)&" - "&(G80) -> MM-SAG-041.00 - Manutenção Preventiva SPDA - Escopo 2 | I80: Sistema Proteção Descargas Atmosféricas (SPDA) | J80: =VLOOKUP(D80,GM!$D$4:$G$1637,4,3)&" e "&C80 -> ENGENHARIA ELÉTRICA e SAG | K80: 45819 | L80: =K80+1096 -> 46915 | M80: Publicado | N80: x | O80: =IF(Q80="","",IF(Q80>1095,"Vencido",IF(Q80>910,"Alerta",IF(Q80>820,"Alerta",IF(Q80>730,"Alerta",IF(Q80>=0,"Em dia","Vencido")))))) -> Em dia | Q80: =$P$4-K80 -> 379
B81: 3 | C81: SAG | D81: 41 | E81: 1 | F81: MM-SAG-041.01 | G81: Manutenção Preventiva SPDA - Escopo 1 | H81: =(F81)&" - "&(G81) -> MM-SAG-041.01 - Manutenção Preventiva SPDA - Escopo 1 | I81: Sistema Proteção Descargas Atmosféricas (SPDA) | J81: =VLOOKUP(D81,GM!$D$4:$G$1637,4,3)&" e "&C81 -> ENGENHARIA ELÉTRICA e SAG | K81: 45819 | L81: =K81+1096 -> 46915 | M81: Publicado | N81: x | O81: =IF(Q81="","",IF(Q81>1095,"Vencido",IF(Q81>910,"Alerta",IF(Q81>820,"Alerta",IF(Q81>730,"Alerta",IF(Q81>=0,"Em dia","Vencido")))))) -> Em dia | Q81: =$P$4-K81 -> 379
B82: 3 | C82: SAG | D82: 58 | E82: 2 | F82: MM-SAG-058.02 | G82: Plano de Lubrificação Sistema Ventilação | H82: =(F82)&" - "&(G82) -> MM-SAG-058.02 - Plano de Lubrificação Sistema Ventilação | I82: Manual Ventilação | J82: =VLOOKUP(D82,GM!$D$4:$G$1637,4,3)&" e "&C82 -> ENGENHARIA MECÂNICA e SAG | K82: 44083 | L82: =K82+1096 -> 45179 | M82: Publicado | N82: x | O82: =IF(Q82="","",IF(Q82>1095,"Vencido",IF(Q82>910,"Alerta",IF(Q82>820,"Alerta",IF(Q82>730,"Alerta",IF(Q82>=0,"Em dia","Vencido")))))) -> Vencido | Q82: =$P$4-K82 -> 2115
B83: 3 | C83: SAG | D83: 60 | E83: 2 | F83: MM-SAG-060.02 | G83: Manual de Manutenção sistema LGE | H83: =(F83)&" - "&(G83) -> MM-SAG-060.02 - Manual de Manutenção sistema LGE | I83: Manual Sistema de Combate a Incêndio | J83: =VLOOKUP(D83,GM!$D$4:$G$1637,4,3)&" e "&C83 -> ENGENHARIA MECÂNICA e SAG | K83: 44063 | L83: =K83+1096 -> 45159 | M83: Publicado | N83: x | O83: =IF(Q83="","",IF(Q83>1095,"Vencido",IF(Q83>910,"Alerta",IF(Q83>820,"Alerta",IF(Q83>730,"Alerta",IF(Q83>=0,"Em dia","Vencido")))))) -> Vencido | Q83: =$P$4-K83 -> 2135
B84: 3 | C84: SAG | D84: 63 | E84: 0 | F84: MM-SAG-063.00 | G84: Manutençao Preventiva Pórtico 25T (MCP0) | H84: =(F84)&" - "&(G84) -> MM-SAG-063.00 - Manutençao Preventiva Pórtico 25T (MCP0) | I84: Manual Pórtico Jusante | J84: =VLOOKUP(D84,GM!$D$4:$G$1637,4,3)&" e "&C84 -> ENGENHARIA MECÂNICA e SAG | M84: Desenvolvimento | O84: =IF(Q84="","",IF(Q84>1095,"Vencido",IF(Q84>910,"Alerta",IF(Q84>820,"Alerta",IF(Q84>730,"Alerta",IF(Q84>=0,"Em dia","Vencido")))))) -> Vencido | Q84: =$P$4-K84 -> 46198
B85: 3 | C85: SAG | D85: 63 | E85: 1 | F85: MM-SAG-063.01 | G85: Plano de Lubrificação do Pórtico Jusante | H85: =(F85)&" - "&(G85) -> MM-SAG-063.01 - Plano de Lubrificação do Pórtico Jusante | I85: Manual Pórtico Jusante | J85: =VLOOKUP(D85,GM!$D$4:$G$1637,4,3)&" e "&C85 -> ENGENHARIA MECÂNICA e SAG | K85: 44083 | L85: =K85+1096 -> 45179 | M85: Publicado | N85: x | O85: =IF(Q85="","",IF(Q85>1095,"Vencido",IF(Q85>910,"Alerta",IF(Q85>820,"Alerta",IF(Q85>730,"Alerta",IF(Q85>=0,"Em dia","Vencido")))))) -> Vencido | Q85: =$P$4-K85 -> 2115
B86: 3 | C86: SAG | D86: 63 | E86: 2 | F86: MM-SAG-063.02 | G86: Manutençao Preventiva Pórtico 25T (MCP1) | H86: =(F86)&" - "&(G86) -> MM-SAG-063.02 - Manutençao Preventiva Pórtico 25T (MCP1) | I86: Manual Pórtico Jusante | J86: =VLOOKUP(D86,GM!$D$4:$G$1637,4,3)&" e "&C86 -> ENGENHARIA MECÂNICA e SAG | M86: Desenvolvimento | O86: =IF(Q86="","",IF(Q86>1095,"Vencido",IF(Q86>910,"Alerta",IF(Q86>820,"Alerta",IF(Q86>730,"Alerta",IF(Q86>=0,"Em dia","Vencido")))))) -> Vencido | Q86: =$P$4-K86 -> 46198
B87: 3 | C87: SAG | D87: 65 | E87: 2 | F87: MM-SAG-065.02 | G87: Plano de Lubrificação Central Hidrau do VS | H87: =(F87)&" - "&(G87) -> MM-SAG-065.02 - Plano de Lubrificação Central Hidrau do VS | I87: Manual Unidade Hidráulica da Comporta de Vertedouro | J87: =VLOOKUP(D87,GM!$D$4:$G$1637,4,3)&" e "&C87 -> ENGENHARIA MECÂNICA e SAG | K87: 44083 | L87: =K87+1096 -> 45179 | M87: Publicado | N87: x | O87: =IF(Q87="","",IF(Q87>1095,"Vencido",IF(Q87>910,"Alerta",IF(Q87>820,"Alerta",IF(Q87>730,"Alerta",IF(Q87>=0,"Em dia","Vencido")))))) -> Vencido | Q87: =$P$4-K87 -> 2115
B88: 3 | C88: SAG | D88: 68 | E88: 1 | F88: MM-SAG-068.01 | G88: Plano de Lubrificação do Limpa Grades | H88: =(F88)&" - "&(G88) -> MM-SAG-068.01 - Plano de Lubrificação do Limpa Grades | I88: Manual Limpa Grades | J88: =VLOOKUP(D88,GM!$D$4:$G$1637,4,3)&" e "&C88 -> ENGENHARIA MECÂNICA e SAG | K88: 44083 | L88: =K88+1096 -> 45179 | M88: Publicado | N88: x | O88: =IF(Q88="","",IF(Q88>1095,"Vencido",IF(Q88>910,"Alerta",IF(Q88>820,"Alerta",IF(Q88>730,"Alerta",IF(Q88>=0,"Em dia","Vencido")))))) -> Vencido | Q88: =$P$4-K88 -> 2115
B89: 4 | C89: CN1 | D89: 0 | E89: 2 | F89: MM-CN1-000.02 | G89: Procedimentos Execução Mergulho Profissional | H89: =(F89)&" - "&(G89) -> MM-CN1-000.02 - Procedimentos Execução Mergulho Profissional | I89: Manual Atividades antes e depois da MPP | J89: =VLOOKUP(D89,GM!$D$4:$G$1637,4,3)&" e "&C89 -> ENGENHARIA e CN1 | K89: 44063 | L89: =K89+1096 -> 45159 | M89: Publicado | N89: x | O89: =IF(Q89="","",IF(Q89>1095,"Vencido",IF(Q89>910,"Alerta",IF(Q89>820,"Alerta",IF(Q89>730,"Alerta",IF(Q89>=0,"Em dia","Vencido")))))) -> Vencido | Q89: =$P$4-K89 -> 2135
B90: 4 | C90: CN1 | D90: 1 | E90: 3 | F90: MM-CN1-001.03 | G90: Procedimento de Desmontagem MGG | H90: =(F90)&" - "&(G90) -> MM-CN1-001.03 - Procedimento de Desmontagem MGG | I90: Manual Turbina | J90: =VLOOKUP(D90,GM!$D$4:$G$1637,4,3)&" e "&C90 -> ENGENHARIA MECÂNICA e CN1 | K90: 44049 | L90: =K90+1096 -> 45145 | M90: Publicado | N90: x | O90: =IF(Q90="","",IF(Q90>1095,"Vencido",IF(Q90>910,"Alerta",IF(Q90>820,"Alerta",IF(Q90>730,"Alerta",IF(Q90>=0,"Em dia","Vencido")))))) -> Vencido | Q90: =$P$4-K90 -> 2149
B91: 4 | C91: CN1 | D91: 1 | E91: 25 | F91: MM-CN1-001.25 | G91: Plano de Lubrificação da Turbina | H91: =(F91)&" - "&(G91) -> MM-CN1-001.25 - Plano de Lubrificação da Turbina | I91: Manual Turbina | J91: =VLOOKUP(D91,GM!$D$4:$G$1637,4,3)&" e "&C91 -> ENGENHARIA MECÂNICA e CN1 | K91: 44064 | L91: =K91+1096 -> 45160 | M91: Publicado | N91: x | O91: =IF(Q91="","",IF(Q91>1095,"Vencido",IF(Q91>910,"Alerta",IF(Q91>820,"Alerta",IF(Q91>730,"Alerta",IF(Q91>=0,"Em dia","Vencido")))))) -> Vencido | Q91: =$P$4-K91 -> 2134
B92: 4 | C92: CN1 | D92: 2 | E92: 1 | F92: MM-CN1-002.01 | G92: Manual de Manutenção do Gerador Parte Mecânica MPP0, 1 e 2 | H92: =(F92)&" - "&(G92) -> MM-CN1-002.01 - Manual de Manutenção do Gerador Parte Mecânica MPP0, 1 e 2 | I92: Gerador-Parte mecanica | J92: =VLOOKUP(D92,GM!$D$4:$G$1637,4,3)&" e "&C92 -> ENGENHARIA MECÂNICA e CN1 | M92: Desenvolvimento | O92: =IF(Q92="","",IF(Q92>1095,"Vencido",IF(Q92>910,"Alerta",IF(Q92>820,"Alerta",IF(Q92>730,"Alerta",IF(Q92>=0,"Em dia","Vencido")))))) -> Vencido | Q92: =$P$4-K92 -> 46198
B93: 4 | C93: CN1 | D93: 3 | E93: 0 | F93: MM-CN1-003.00 | G93: anutenção Preventiva Periódica Tipo MPP0 no Gerador | H93: =(F93)&" - "&(G93) -> MM-CN1-003.00 - anutenção Preventiva Periódica Tipo MPP0 no Gerador | I93: Gerador-Parte elétrica | J93: =VLOOKUP(D93,GM!$D$4:$G$1637,4,3)&" e "&C93 -> ENGENHARIA ELÉTRICA e CN1 | K93: 45791 | L93: =K93+1096 -> 46887 | M93: Publicado | N93: x | O93: =IF(Q93="","",IF(Q93>1095,"Vencido",IF(Q93>910,"Alerta",IF(Q93>820,"Alerta",IF(Q93>730,"Alerta",IF(Q93>=0,"Em dia","Vencido")))))) -> Em dia | Q93: =$P$4-K93 -> 407
B94: 4 | C94: CN1 | D94: 3 | E94: 1 | F94: MM-CN1-003.01 | G94: anutenção Preventiva Periódica Tipo MPP1 no Gerador | H94: =(F94)&" - "&(G94) -> MM-CN1-003.01 - anutenção Preventiva Periódica Tipo MPP1 no Gerador | I94: Gerador-Parte elétrica | J94: =VLOOKUP(D94,GM!$D$4:$G$1637,4,3)&" e "&C94 -> ENGENHARIA ELÉTRICA e CN1 | K94: 45791 | L94: =K94+1096 -> 46887 | M94: Publicado | N94: x | O94: =IF(Q94="","",IF(Q94>1095,"Vencido",IF(Q94>910,"Alerta",IF(Q94>820,"Alerta",IF(Q94>730,"Alerta",IF(Q94>=0,"Em dia","Vencido")))))) -> Em dia | Q94: =$P$4-K94 -> 407
B95: 4 | C95: CN1 | D95: 3 | E95: 2 | F95: MM-CN1-003.02 | G95: anutenção Preventiva Periódica Tipo MPP2 no Gerador | H95: =(F95)&" - "&(G95) -> MM-CN1-003.02 - anutenção Preventiva Periódica Tipo MPP2 no Gerador | I95: Gerador-Parte elétrica | J95: =VLOOKUP(D95,GM!$D$4:$G$1637,4,3)&" e "&C95 -> ENGENHARIA ELÉTRICA e CN1 | K95: 45791 | L95: =K95+1096 -> 46887 | M95: Publicado | N95: x | O95: =IF(Q95="","",IF(Q95>1095,"Vencido",IF(Q95>910,"Alerta",IF(Q95>820,"Alerta",IF(Q95>730,"Alerta",IF(Q95>=0,"Em dia","Vencido")))))) -> Em dia | Q95: =$P$4-K95 -> 407
B96: 4 | C96: CN1 | D96: 3 | E96: 3 | F96: MM-CN1-003.03 | G96: Manutenção Preventiva nos Coletores | H96: =(F96)&" - "&(G96) -> MM-CN1-003.03 - Manutenção Preventiva nos Coletores | I96: Gerador-Parte elétrica | J96: =VLOOKUP(D96,GM!$D$4:$G$1637,4,3)&" e "&C96 -> ENGENHARIA ELÉTRICA e CN1 | K96: 45791 | L96: =K96+1096 -> 46887 | M96: Publicado | N96: x | O96: =IF(Q96="","",IF(Q96>1095,"Vencido",IF(Q96>910,"Alerta",IF(Q96>820,"Alerta",IF(Q96>730,"Alerta",IF(Q96>=0,"Em dia","Vencido")))))) -> Em dia | Q96: =$P$4-K96 -> 407
B97: 4 | C97: CN1 | D97: 4 | E97: 0 | F97: MM-CN1-004.00 | G97: Manutenção Preventiva Periódica Tipo 0 nos Sistemas Auxiliares da Unidade Geradora | H97: =(F97)&" - "&(G97) -> MM-CN1-004.00 - Manutenção Preventiva Periódica Tipo 0 nos Sistemas Auxiliares da Unidade Geradora | I97: Sistemas Auxiliares da Unidade Geradora | J97: =VLOOKUP(D97,GM!$D$4:$G$1637,4,3)&" e "&C97 -> ENGENHARIA ELÉTRICA e CN1 | K97: 45819 | L97: =K97+1096 -> 46915 | M97: Publicado | N97: x | O97: =IF(Q97="","",IF(Q97>1095,"Vencido",IF(Q97>910,"Alerta",IF(Q97>820,"Alerta",IF(Q97>730,"Alerta",IF(Q97>=0,"Em dia","Vencido")))))) -> Em dia | Q97: =$P$4-K97 -> 379
B98: 4 | C98: CN1 | D98: 4 | E98: 1 | F98: MM-CN1-004.01 | G98: Manutenção Preventiva Periódica Tipo 1 nos Sistemas Auxiliares da Unidade Geradora | H98: =(F98)&" - "&(G98) -> MM-CN1-004.01 - Manutenção Preventiva Periódica Tipo 1 nos Sistemas Auxiliares da Unidade Geradora | I98: Sistemas Auxiliares da Unidade Geradora | J98: =VLOOKUP(D98,GM!$D$4:$G$1637,4,3)&" e "&C98 -> ENGENHARIA ELÉTRICA e CN1 | K98: 45819 | L98: =K98+1096 -> 46915 | M98: Publicado | N98: x | O98: =IF(Q98="","",IF(Q98>1095,"Vencido",IF(Q98>910,"Alerta",IF(Q98>820,"Alerta",IF(Q98>730,"Alerta",IF(Q98>=0,"Em dia","Vencido")))))) -> Em dia | Q98: =$P$4-K98 -> 379
B99: 4 | C99: CN1 | D99: 4 | E99: 2 | F99: MM-CN1-004.02 | G99: Manutenção Preventiva Periódica Tipo 2 nos Sistemas Auxiliares da Unidade Geradora | H99: =(F99)&" - "&(G99) -> MM-CN1-004.02 - Manutenção Preventiva Periódica Tipo 2 nos Sistemas Auxiliares da Unidade Geradora | I99: Sistemas Auxiliares da Unidade Geradora | J99: =VLOOKUP(D99,GM!$D$4:$G$1637,4,3)&" e "&C99 -> ENGENHARIA ELÉTRICA e CN1 | K99: 45819 | L99: =K99+1096 -> 46915 | M99: Publicado | N99: x | O99: =IF(Q99="","",IF(Q99>1095,"Vencido",IF(Q99>910,"Alerta",IF(Q99>820,"Alerta",IF(Q99>730,"Alerta",IF(Q99>=0,"Em dia","Vencido")))))) -> Em dia | Q99: =$P$4-K99 -> 379
B100: 4 | C100: CN1 | D100: 6 | E100: 0 | F100: MM-CN1-006.00 | G100: Coleta de Amostras de Óleo Isolante | H100: =(F100)&" - "&(G100) -> MM-CN1-006.00 - Coleta de Amostras de Óleo Isolante | I100: Transformador Elevador | J100: =VLOOKUP(D100,GM!$D$4:$G$1637,4,3)&" e "&C100 -> ENGENHARIA ELÉTRICA e CN1 | K100: 45743 | L100: =K100+1096 -> 46839 | M100: Publicado | N100: x | O100: =IF(Q100="","",IF(Q100>1095,"Vencido",IF(Q100>910,"Alerta",IF(Q100>820,"Alerta",IF(Q100>730,"Alerta",IF(Q100>=0,"Em dia","Vencido")))))) -> Em dia | Q100: =$P$4-K100 -> 455
B101: 4 | C101: CN1 | D101: 19 | E101: 0 | F101: MM-CN1-019.00 | G101: Manutenção Complementar Preventiva Tipo 0 no Sistema de Corrente Contínua | H101: =(F101)&" - "&(G101) -> MM-CN1-019.00 - Manutenção Complementar Preventiva Tipo 0 no Sistema de Corrente Contínua | I101: Sistema de Corrente Contínua | J101: =VLOOKUP(D101,GM!$D$4:$G$1637,4,3)&" e "&C101 -> ENGENHARIA ELÉTRICA e CN1 | K101: 45959 | L101: =K101+1096 -> 47055 | M101: publicado | N101: X | O101: =IF(Q101="","",IF(Q101>1095,"Vencido",IF(Q101>910,"Alerta",IF(Q101>820,"Alerta",IF(Q101>730,"Alerta",IF(Q101>=0,"Em dia","Vencido")))))) -> Em dia | Q101: =$P$4-K101 -> 239
B102: 4 | C102: CN1 | D102: 19 | E102: 1 | F102: MM-CN1-019.01 | G102: Manutenção Complementar Preventiva Tipo 1 no Sistema de Corrente Contínua | H102: =(F102)&" - "&(G102) -> MM-CN1-019.01 - Manutenção Complementar Preventiva Tipo 1 no Sistema de Corrente Contínua | I102: Sistema de Corrente Contínua | J102: =VLOOKUP(D102,GM!$D$4:$G$1637,4,3)&" e "&C102 -> ENGENHARIA ELÉTRICA e CN1 | K102: 45959 | L102: =K102+1096 -> 47055 | M102: publicado | N102: X | O102: =IF(Q102="","",IF(Q102>1095,"Vencido",IF(Q102>910,"Alerta",IF(Q102>820,"Alerta",IF(Q102>730,"Alerta",IF(Q102>=0,"Em dia","Vencido")))))) -> Em dia | Q102: =$P$4-K102 -> 239
B103: 4 | C103: CN1 | D103: 19 | E103: 2 | F103: MM-CN1-019.02 | G103: Manutenção Complementar Preventiva Tipo 2 no Sistema de Corrente Contínua | H103: =(F103)&" - "&(G103) -> MM-CN1-019.02 - Manutenção Complementar Preventiva Tipo 2 no Sistema de Corrente Contínua | I103: Sistema de Corrente Contínua | J103: =VLOOKUP(D103,GM!$D$4:$G$1637,4,3)&" e "&C103 -> ENGENHARIA ELÉTRICA e CN1 | K103: 45959 | L103: =K103+1096 -> 47055 | M103: publicado | N103: X | O103: =IF(Q103="","",IF(Q103>1095,"Vencido",IF(Q103>910,"Alerta",IF(Q103>820,"Alerta",IF(Q103>730,"Alerta",IF(Q103>=0,"Em dia","Vencido")))))) -> Em dia | Q103: =$P$4-K103 -> 239
B104: 4 | C104: CN1 | D104: 20 | E104: 6 | F104: MM-CN1-020.06 | G104: Plano de Lubrificação do RV | H104: =(F104)&" - "&(G104) -> MM-CN1-020.06 - Plano de Lubrificação do RV | I104: Manual Regulador de Velocidade - Parte Mecânica | J104: =VLOOKUP(D104,GM!$D$4:$G$1637,4,3)&" e "&C104 -> ENGENHARIA MECÂNICA e CN1 | K104: 44064 | L104: =K104+1096 -> 45160 | M104: Publicado | N104: x | O104: =IF(Q104="","",IF(Q104>1095,"Vencido",IF(Q104>910,"Alerta",IF(Q104>820,"Alerta",IF(Q104>730,"Alerta",IF(Q104>=0,"Em dia","Vencido")))))) -> Vencido | Q104: =$P$4-K104 -> 2134
... B110: 4 | C110: CN1 | D110: 28 | E110: 2 | F110: MM-CN1-028.02 | G110: Procedimento Manuseio Comportas de Manutenção | H110: =(F110)&" - "&(G110) -> MM-CN1-028.02 - Procedimento Manuseio Comportas de Manutenção | I110: Manual Comporta de Manutenção | J110: =VLOOKUP(D110,GM!$D$4:$G$1637,4,3)&" e "&C110 -> ENGENHARIA MECÂNICA e CN1 | K110: 44062 | L110: =K110+1096 -> 45158 | M110: Publicado | N110: x | O110: =IF(Q110="","",IF(Q110>1095,"Vencido",IF(Q110>910,"Alerta",IF(Q110>820,"Alerta",IF(Q110>730,"Alerta",IF(Q110>=0,"Em dia","Vencido")))))) -> Vencido | Q110: =$P$4-K110 -> 2136
B111: 4 | C111: CN1 | D111: 30 | E111: 0 | F111: MM-CN1-030.00 | G111: Manutenção Preventiva - Pórtico Montante 25-03t. e Limpa Grades (MCP1) | H111: =(F111)&" - "&(G111) -> MM-CN1-030.00 - Manutenção Preventiva - Pórtico Montante 25-03t. e Limpa Grades (MCP1) | I111: Manual Pórtico Montante | J111: =VLOOKUP(D111,GM!$D$4:$G$1637,4,3)&" e "&C111 -> ENGENHARIA MECÂNICA e CN1 | M111: Desenvolvimento | O111: =IF(Q111="","",IF(Q111>1095,"Vencido",IF(Q111>910,"Alerta",IF(Q111>820,"Alerta",IF(Q111>730,"Alerta",IF(Q111>=0,"Em dia","Vencido")))))) -> Vencido | Q111: =$P$4-K111 -> 46198
B112: 4 | C112: CN1 | D112: 30 | E112: 1 | F112: MM-CN1-030.01 | G112: Plano de Lubrificação do Pórtico Montante | H112: =(F112)&" - "&(G112) -> MM-CN1-030.01 - Plano de Lubrificação do Pórtico Montante | I112: Manual Pórtico Montante | J112: =VLOOKUP(D112,GM!$D$4:$G$1637,4,3)&" e "&C112 -> ENGENHARIA MECÂNICA e CN1 | K112: 44064 | L112: =K112+1096 -> 45160 | M112: Publicado | N112: x | O112: =IF(Q112="","",IF(Q112>1095,"Vencido",IF(Q112>910,"Alerta",IF(Q112>820,"Alerta",IF(Q112>730,"Alerta",IF(Q112>=0,"Em dia","Vencido")))))) -> Vencido | Q112: =$P$4-K112 -> 2134
B113: 4 | C113: CN1 | D113: 31 | E113: 21 | F113: MM-CN1-031.21 | G113: Plano de Lubrificação da Ponte Rolante | H113: =(F113)&" - "&(G113) -> MM-CN1-031.21 - Plano de Lubrificação da Ponte Rolante | I113: Manual Ponte Rolante Princip | J113: =VLOOKUP(D113,GM!$D$4:$G$1637,4,3)&" e "&C113 -> ENGENHARIA MECÂNICA e CN1 | K113: 44064 | L113: =K113+1096 -> 45160 | M113: Publicado | N113: x | O113: =IF(Q113="","",IF(Q113>1095,"Vencido",IF(Q113>910,"Alerta",IF(Q113>820,"Alerta",IF(Q113>730,"Alerta",IF(Q113>=0,"Em dia","Vencido")))))) -> Vencido | Q113: =$P$4-K113 -> 2134
B114: 4 | C114: CN1 | D114: 33 | E114: 0 | F114: MM-CN1-033.00 | G114: MCP0 Elevador | H114: =(F114)&" - "&(G114) -> MM-CN1-033.00 - MCP0 Elevador | I114: Elevador | J114: =VLOOKUP(D114,GM!$D$4:$G$1637,4,3)&" e "&C114 -> ENGENHARIA MECÂNICA e CN1 | K114: 45959 | L114: =K114+1096 -> 47055 | M114: Publicado | N114: X | O114: =IF(Q114="","",IF(Q114>1095,"Vencido",IF(Q114>910,"Alerta",IF(Q114>820,"Alerta",IF(Q114>730,"Alerta",IF(Q114>=0,"Em dia","Vencido")))))) -> Em dia | Q114: =$P$4-K114 -> 239
B115: 4 | C115: CN1 | D115: 41 | E115: 0 | F115: MM-CN1-041.00 | G115: Manutenção Preventiva SPDA – Escopo 2 | H115: =(F115)&" - "&(G115) -> MM-CN1-041.00 - Manutenção Preventiva SPDA – Escopo 2 | I115: Sistema Proteção Descargas Atmosféricas (SPDA) | J115: =VLOOKUP(D115,GM!$D$4:$G$1637,4,3)&" e "&C115 -> ENGENHARIA ELÉTRICA e CN1 | K115: 45791 | L115: =K115+1096 -> 46887 | M115: Publicado | N115: x | O115: =IF(Q115="","",IF(Q115>1095,"Vencido",IF(Q115>910,"Alerta",IF(Q115>820,"Alerta",IF(Q115>730,"Alerta",IF(Q115>=0,"Em dia","Vencido")))))) -> Em dia | Q115: =$P$4-K115 -> 407
B116: 4 | C116: CN1 | D116: 41 | E116: 1 | F116: MM-CN1-041.01 | G116: Manutenção Preventiva SPDA – Escopo 1 | H116: =(F116)&" - "&(G116) -> MM-CN1-041.01 - Manutenção Preventiva SPDA – Escopo 1 | I116: Sistema Proteção Descargas Atmosféricas (SPDA) | J116: =VLOOKUP(D116,GM!$D$4:$G$1637,4,3)&" e "&C116 -> ENGENHARIA ELÉTRICA e CN1 | K116: 45791 | L116: =K116+1096 -> 46887 | M116: Publicado | N116: x | O116: =IF(Q116="","",IF(Q116>1095,"Vencido",IF(Q116>910,"Alerta",IF(Q116>820,"Alerta",IF(Q116>730,"Alerta",IF(Q116>=0,"Em dia","Vencido")))))) -> Em dia | Q116: =$P$4-K116 -> 407
B117: 4 | C117: CN1 | D117: 58 | E117: 2 | F117: MM-CN1-058.02 | G117: Plano de Lubrificação Sistema Ventilação | H117: =(F117)&" - "&(G117) -> MM-CN1-058.02 - Plano de Lubrificação Sistema Ventilação | I117: Manual Ventilação | J117: =VLOOKUP(D117,GM!$D$4:$G$1637,4,3)&" e "&C117 -> ENGENHARIA MECÂNICA e CN1 | K117: 44064 | L117: =K117+1096 -> 45160 | M117: Publicado | N117: x | O117: =IF(Q117="","",IF(Q117>1095,"Vencido",IF(Q117>910,"Alerta",IF(Q117>820,"Alerta",IF(Q117>730,"Alerta",IF(Q117>=0,"Em dia","Vencido")))))) -> Vencido | Q117: =$P$4-K117 -> 2134
B118: 4 | C118: CN1 | D118: 60 | E118: 2 | F118: MM-CN1-060.02 | G118: Manual de Manutenção sistema LGE | H118: =(F118)&" - "&(G118) -> MM-CN1-060.02 - Manual de Manutenção sistema LGE | I118: Manual Sistema de Combate a Incêndio | J118: =VLOOKUP(D118,GM!$D$4:$G$1637,4,3)&" e "&C118 -> ENGENHARIA MECÂNICA e CN1 | K118: 44071 | L118: =K118+1096 -> 45167 | M118: Publicado | N118: x | O118: =IF(Q118="","",IF(Q118>1095,"Vencido",IF(Q118>910,"Alerta",IF(Q118>820,"Alerta",IF(Q118>730,"Alerta",IF(Q118>=0,"Em dia","Vencido")))))) -> Vencido | Q118: =$P$4-K118 -> 2127
B119: 4 | C119: CN1 | D119: 63 | E119: 0 | F119: MM-CN1-063.00 | G119: Manutenção Preventiva - Pórtico Jusante 25t (MCP1) | H119: =(F119)&" - "&(G119) -> MM-CN1-063.00 - Manutenção Preventiva - Pórtico Jusante 25t (MCP1) | I119: Manual Pórtico Jusante | J119: =VLOOKUP(D119,GM!$D$4:$G$1637,4,3)&" e "&C119 -> ENGENHARIA MECÂNICA e CN1 | M119: Desenvolvimento | O119: =IF(Q119="","",IF(Q119>1095,"Vencido",IF(Q119>910,"Alerta",IF(Q119>820,"Alerta",IF(Q119>730,"Alerta",IF(Q119>=0,"Em dia","Vencido")))))) -> Vencido | Q119: =$P$4-K119 -> 46198
B120: 4 | C120: CN1 | D120: 63 | E120: 1 | F120: MM-CN1-063.01 | G120: Plano de Lubrificação do Pórtico Jusante | H120: =(F120)&" - "&(G120) -> MM-CN1-063.01 - Plano de Lubrificação do Pórtico Jusante | I120: Manual Pórtico Jusante | J120: =VLOOKUP(D120,GM!$D$4:$G$1637,4,3)&" e "&C120 -> ENGENHARIA MECÂNICA e CN1 | K120: 44064 | L120: =K120+1096 -> 45160 | M120: Publicado | N120: x | O120: =IF(Q120="","",IF(Q120>1095,"Vencido",IF(Q120>910,"Alerta",IF(Q120>820,"Alerta",IF(Q120>730,"Alerta",IF(Q120>=0,"Em dia","Vencido")))))) -> Vencido | Q120: =$P$4-K120 -> 2134
B121: 4 | C121: CN1 | D121: 65 | E121: 1 | F121: MM-CN1-065.01 | G121: Plano de Lubrificação Central Hidrau Comporta Emerg | H121: =(F121)&" - "&(G121) -> MM-CN1-065.01 - Plano de Lubrificação Central Hidrau Comporta Emerg | I121: Manual Unidade Hidráulica da Comporta de Emergência | J121: =VLOOKUP(D121,GM!$D$4:$G$1637,4,3)&" e "&C121 -> ENGENHARIA MECÂNICA e CN1 | K121: 44064 | L121: =K121+1096 -> 45160 | M121: Publicado | N121: x | O121: =IF(Q121="","",IF(Q121>1095,"Vencido",IF(Q121>910,"Alerta",IF(Q121>820,"Alerta",IF(Q121>730,"Alerta",IF(Q121>=0,"Em dia","Vencido")))))) -> Vencido | Q121: =$P$4-K121 -> 2134
B122: 4 | C122: CN1 | D122: 65 | E122: 2 | F122: MM-CN1-065.02 | G122: Plano de Lubrificação Central Hidrau do VS | H122: =(F122)&" - "&(G122) -> MM-CN1-065.02 - Plano de Lubrificação Central Hidrau do VS | I122: Manual Unidade Hidráulica da Comporta de Vertedouro | J122: =VLOOKUP(D122,GM!$D$4:$G$1637,4,3)&" e "&C122 -> ENGENHARIA MECÂNICA e CN1 | K122: 44064 | L122: =K122+1096 -> 45160 | M122: Publicado | N122: x | O122: =IF(Q122="","",IF(Q122>1095,"Vencido",IF(Q122>910,"Alerta",IF(Q122>820,"Alerta",IF(Q122>730,"Alerta",IF(Q122>=0,"Em dia","Vencido")))))) -> Vencido | Q122: =$P$4-K122 -> 2134
B123: 4 | C123: CN1 | D123: 68 | E123: 1 | F123: MM-CN1-068.01 | G123: Plano de Lubrificação do Limpa Grades | H123: =(F123)&" - "&(G123) -> MM-CN1-068.01 - Plano de Lubrificação do Limpa Grades | I123: Manual Limpa Grades | J123: =VLOOKUP(D123,GM!$D$4:$G$1637,4,3)&" e "&C123 -> ENGENHARIA MECÂNICA e CN1 | K123: 44064 | L123: =K123+1096 -> 45160 | M123: Publicado | N123: x | O123: =IF(Q123="","",IF(Q123>1095,"Vencido",IF(Q123>910,"Alerta",IF(Q123>820,"Alerta",IF(Q123>730,"Alerta",IF(Q123>=0,"Em dia","Vencido")))))) -> Vencido | Q123: =$P$4-K123 -> 2134
B124: 4 | C124: CN1 | D124: 84 | E124: 1 | F124: MM-CN1-084.01 | G124: Plano de Lubrificação do Tratamento Esgoto | H124: =(F124)&" - "&(G124) -> MM-CN1-084.01 - Plano de Lubrificação do Tratamento Esgoto | I124: Manual Tratamento de esgoto | J124: =VLOOKUP(D124,GM!$D$4:$G$1637,4,3)&" e "&C124 -> ENGENHARIA MECÂNICA e CN1 | K124: 44064 | L124: =K124+1096 -> 45160 | M124: Publicado | N124: x | O124: =IF(Q124="","",IF(Q124>1095,"Vencido",IF(Q124>910,"Alerta",IF(Q124>820,"Alerta",IF(Q124>730,"Alerta",IF(Q124>=0,"Em dia","Vencido")))))) -> Vencido | Q124: =$P$4-K124 -> 2134
B125: 5 | C125: CN2 | D125: 0 | E125: 2 | F125: MM-CN2-000.02 | G125: Procedimentos Execução Mergulho Profissional | H125: =(F125)&" - "&(G125) -> MM-CN2-000.02 - Procedimentos Execução Mergulho Profissional | I125: Manual Atividades antes e depois da MPP | J125: =VLOOKUP(D125,GM!$D$4:$G$1637,4,3)&" e "&C125 -> ENGENHARIA e CN2 | K125: 44063 | L125: =K125+1096 -> 45159 | M125: Publicado | N125: x | O125: =IF(Q125="","",IF(Q125>1095,"Vencido",IF(Q125>910,"Alerta",IF(Q125>820,"Alerta",IF(Q125>730,"Alerta",IF(Q125>=0,"Em dia","Vencido")))))) -> Vencido | Q125: =$P$4-K125 -> 2135
B126: 5 | C126: CN2 | D126: 1 | E126: 3 | F126: MM-CN2-001.03 | G126: Procedimento de Desmontagem MGG | H126: =(F126)&" - "&(G126) -> MM-CN2-001.03 - Procedimento de Desmontagem MGG | I126: Manual Turbina | J126: =VLOOKUP(D126,GM!$D$4:$G$1637,4,3)&" e "&C126 -> ENGENHARIA MECÂNICA e CN2 | K126: 44049 | L126: =K126+1096 -> 45145 | M126: Publicado | N126: x | O126: =IF(Q126="","",IF(Q126>1095,"Vencido",IF(Q126>910,"Alerta",IF(Q126>820,"Alerta",IF(Q126>730,"Alerta",IF(Q126>=0,"Em dia","Vencido")))))) -> Vencido | Q126: =$P$4-K126 -> 2149
B127: 5 | C127: CN2 | D127: 1 | E127: 25 | F127: MM-CN2-001.25 | G127: Plano de Lubrificação da Turbina | H127: =(F127)&" - "&(G127) -> MM-CN2-001.25 - Plano de Lubrificação da Turbina | I127: Manual Turbina | J127: =VLOOKUP(D127,GM!$D$4:$G$1637,4,3)&" e "&C127 -> ENGENHARIA MECÂNICA e CN2 | K127: 44064 | L127: =K127+1096 -> 45160 | M127: Publicado | N127: x | O127: =IF(Q127="","",IF(Q127>1095,"Vencido",IF(Q127>910,"Alerta",IF(Q127>820,"Alerta",IF(Q127>730,"Alerta",IF(Q127>=0,"Em dia","Vencido")))))) -> Vencido | Q127: =$P$4-K127 -> 2134
B128: 5 | C128: CN2 | D128: 2 | E128: 1 | F128: MM-CN2-002.01 | G128: Manual de Manutenção do Gerador Parte Mecânica MPP0, 1 e 2 | H128: =(F128)&" - "&(G128) -> MM-CN2-002.01 - Manual de Manutenção do Gerador Parte Mecânica MPP0, 1 e 2 | I128: Gerador-Parte mecanica | J128: =VLOOKUP(D128,GM!$D$4:$G$1637,4,3)&" e "&C128 -> ENGENHARIA MECÂNICA e CN2 | M128: Desenvolvimento | O128: =IF(Q128="","",IF(Q128>1095,"Vencido",IF(Q128>910,"Alerta",IF(Q128>820,"Alerta",IF(Q128>730,"Alerta",IF(Q128>=0,"Em dia","Vencido")))))) -> Vencido | Q128: =$P$4-K128 -> 46198
B129: 5 | C129: CN2 | D129: 2 | E129: 16 | F129: MM-CN2-002.16 | G129: Plano de Lubrificação do Gerador | H129: =(F129)&" - "&(G129) -> MM-CN2-002.16 - Plano de Lubrificação do Gerador | I129: Manual Gerador-Parte mecânica | J129: =VLOOKUP(D129,GM!$D$4:$G$1637,4,3)&" e "&C129 -> ENGENHARIA MECÂNICA e CN2 | K129: 44064 | L129: =K129+1096 -> 45160 | M129: Publicado | N129: x | O129: =IF(Q129="","",IF(Q129>1095,"Vencido",IF(Q129>910,"Alerta",IF(Q129>820,"Alerta",IF(Q129>730,"Alerta",IF(Q129>=0,"Em dia","Vencido")))))) -> Vencido | Q129: =$P$4-K129 -> 2134
B130: 5 | C130: CN2 | D130: 3 | E130: 0 | F130: MM-CN2-003.00 | G130: anutenção Preventiva Periódica Tipo MPP0 no Gerador | H130: =(F130)&" - "&(G130) -> MM-CN2-003.00 - anutenção Preventiva Periódica Tipo MPP0 no Gerador | I130: Gerador-Parte elétrica | J130: =VLOOKUP(D130,GM!$D$4:$G$1637,4,3)&" e "&C130 -> ENGENHARIA ELÉTRICA e CN2 | K130: 45791 | L130: =K130+1096 -> 46887 | M130: Publicado | N130: x | O130: =IF(Q130="","",IF(Q130>1095,"Vencido",IF(Q130>910,"Alerta",IF(Q130>820,"Alerta",IF(Q130>730,"Alerta",IF(Q130>=0,"Em dia","Vencido")))))) -> Em dia | Q130: =$P$4-K130 -> 407
B131: 5 | C131: CN2 | D131: 3 | E131: 1 | F131: MM-CN2-003.01 | G131: anutenção Preventiva Periódica Tipo MPP1 no Gerador | H131: =(F131)&" - "&(G131) -> MM-CN2-003.01 - anutenção Preventiva Periódica Tipo MPP1 no Gerador | I131: Gerador-Parte elétrica | J131: =VLOOKUP(D131,GM!$D$4:$G$1637,4,3)&" e "&C131 -> ENGENHARIA ELÉTRICA e CN2 | K131: 45791 | L131: =K131+1096 -> 46887 | M131: Publicado | N131: x | O131: =IF(Q131="","",IF(Q131>1095,"Vencido",IF(Q131>910,"Alerta",IF(Q131>820,"Alerta",IF(Q131>730,"Alerta",IF(Q131>=0,"Em dia","Vencido")))))) -> Em dia | Q131: =$P$4-K131 -> 407
B132: 5 | C132: CN2 | D132: 3 | E132: 2 | F132: MM-CN2-003.02 | G132: anutenção Preventiva Periódica Tipo MPP2 no Gerador | H132: =(F132)&" - "&(G132) -> MM-CN2-003.02 - anutenção Preventiva Periódica Tipo MPP2 no Gerador | I132: Gerador-Parte elétrica | J132: =VLOOKUP(D132,GM!$D$4:$G$1637,4,3)&" e "&C132 -> ENGENHARIA ELÉTRICA e CN2 | K132: 45791 | L132: =K132+1096 -> 46887 | M132: Publicado | N132: x | O132: =IF(Q132="","",IF(Q132>1095,"Vencido",IF(Q132>910,"Alerta",IF(Q132>820,"Alerta",IF(Q132>730,"Alerta",IF(Q132>=0,"Em dia","Vencido")))))) -> Em dia | Q132: =$P$4-K132 -> 407
B133: 5 | C133: CN2 | D133: 3 | E133: 3 | F133: MM-CN2-003.03 | G133: Manutenção Preventiva nos Coletores | H133: =(F133)&" - "&(G133) -> MM-CN2-003.03 - Manutenção Preventiva nos Coletores | I133: Gerador-Parte elétrica | J133: =VLOOKUP(D133,GM!$D$4:$G$1637,4,3)&" e "&C133 -> ENGENHARIA ELÉTRICA e CN2 | K133: 45791 | L133: =K133+1096 -> 46887 | M133: Publicado | N133: x | O133: =IF(Q133="","",IF(Q133>1095,"Vencido",IF(Q133>910,"Alerta",IF(Q133>820,"Alerta",IF(Q133>730,"Alerta",IF(Q133>=0,"Em dia","Vencido")))))) -> Em dia | Q133: =$P$4-K133 -> 407
B134: 5 | C134: CN2 | D134: 4 | E134: 0 | F134: MM-CN2-004.00 | G134: Manutenção Preventiva Periódica Tipo 0 nos Sistemas Auxiliares da Unidade Geradora | H134: =(F134)&" - "&(G134) -> MM-CN2-004.00 - Manutenção Preventiva Periódica Tipo 0 nos Sistemas Auxiliares da Unidade Geradora | I134: Sistemas Auxiliares da Unidade Geradora | J134: =VLOOKUP(D134,GM!$D$4:$G$1637,4,3)&" e "&C134 -> ENGENHARIA ELÉTRICA e CN2 | K134: 45819 | L134: =K134+1096 -> 46915 | M134: Publicado | N134: x | O134: =IF(Q134="","",IF(Q134>1095,"Vencido",IF(Q134>910,"Alerta",IF(Q134>820,"Alerta",IF(Q134>730,"Alerta",IF(Q134>=0,"Em dia","Vencido")))))) -> Em dia | Q134: =$P$4-K134 -> 379
B135: 5 | C135: CN2 | D135: 4 | E135: 1 | F135: MM-CN2-004.01 | G135: Manutenção Preventiva Periódica Tipo 1 nos Sistemas Auxiliares da Unidade Geradora | H135: =(F135)&" - "&(G135) -> MM-CN2-004.01 - Manutenção Preventiva Periódica Tipo 1 nos Sistemas Auxiliares da Unidade Geradora | I135: Sistemas Auxiliares da Unidade Geradora | J135: =VLOOKUP(D135,GM!$D$4:$G$1637,4,3)&" e "&C135 -> ENGENHARIA ELÉTRICA e CN2 | K135: 45819 | L135: =K135+1096 -> 46915 | M135: Publicado | N135: x | O135: =IF(Q135="","",IF(Q135>1095,"Vencido",IF(Q135>910,"Alerta",IF(Q135>820,"Alerta",IF(Q135>730,"Alerta",IF(Q135>=0,"Em dia","Vencido")))))) -> Em dia | Q135: =$P$4-K135 -> 379
B136: 5 | C136: CN2 | D136: 4 | E136: 2 | F136: MM-CN2-004.02 | G136: Manutenção Preventiva Periódica Tipo 2 nos Sistemas Auxiliares da Unidade Geradora | H136: =(F136)&" - "&(G136) -> MM-CN2-004.02 - Manutenção Preventiva Periódica Tipo 2 nos Sistemas Auxiliares da Unidade Geradora | I136: Sistemas Auxiliares da Unidade Geradora | J136: =VLOOKUP(D136,GM!$D$4:$G$1637,4,3)&" e "&C136 -> ENGENHARIA ELÉTRICA e CN2 | K136: 45819 | L136: =K136+1096 -> 46915 | M136: Publicado | N136: x | O136: =IF(Q136="","",IF(Q136>1095,"Vencido",IF(Q136>910,"Alerta",IF(Q136>820,"Alerta",IF(Q136>730,"Alerta",IF(Q136>=0,"Em dia","Vencido")))))) -> Em dia | Q136: =$P$4-K136 -> 379
B137: 5 | C137: CN2 | D137: 6 | E137: 0 | F137: MM-CN2-006.00 | G137: Coleta de Amostras de Óleo Isolante | H137: =(F137)&" - "&(G137) -> MM-CN2-006.00 - Coleta de Amostras de Óleo Isolante | I137: Transformador Elevador | J137: =VLOOKUP(D137,GM!$D$4:$G$1637,4,3)&" e "&C137 -> ENGENHARIA ELÉTRICA e CN2 | K137: 45743 | L137: =K137+1096 -> 46839 | M137: Publicado | N137: x | O137: =IF(Q137="","",IF(Q137>1095,"Vencido",IF(Q137>910,"Alerta",IF(Q137>820,"Alerta",IF(Q137>730,"Alerta",IF(Q137>=0,"Em dia","Vencido")))))) -> Em dia | Q137: =$P$4-K137 -> 455
B138: 5 | C138: CN2 | D138: 19 | E138: 0 | F138: MM-CN2-019.00 | G138: Manutenção Complementar Preventiva Tipo 0 no Sistema de Corrente Contínua | H138: =(F138)&" - "&(G138) -> MM-CN2-019.00 - Manutenção Complementar Preventiva Tipo 0 no Sistema de Corrente Contínua | I138: Sistema de Corrente Contínua | J138: =VLOOKUP(D138,GM!$D$4:$G$1637,4,3)&" e "&C138 -> ENGENHARIA ELÉTRICA e CN2 | K138: 45959 | L138: =K138+1096 -> 47055 | M138: Publicado | N138: X | O138: =IF(Q138="","",IF(Q138>1095,"Vencido",IF(Q138>910,"Alerta",IF(Q138>820,"Alerta",IF(Q138>730,"Alerta",IF(Q138>=0,"Em dia","Vencido")))))) -> Em dia | Q138: =$P$4-K138 -> 239
B139: 5 | C139: CN2 | D139: 19 | E139: 1 | F139: MM-CN2-019.01 | G139: Manutenção Complementar Preventiva Tipo 1 no Sistema de Corrente Contínua | H139: =(F139)&" - "&(G139) -> MM-CN2-019.01 - Manutenção Complementar Preventiva Tipo 1 no Sistema de Corrente Contínua | I139: Sistema de Corrente Contínua | J139: =VLOOKUP(D139,GM!$D$4:$G$1637,4,3)&" e "&C139 -> ENGENHARIA ELÉTRICA e CN2 | K139: 45959 | L139: =K139+1096 -> 47055 | M139: Publicado | N139: X | O139: =IF(Q139="","",IF(Q139>1095,"Vencido",IF(Q139>910,"Alerta",IF(Q139>820,"Alerta",IF(Q139>730,"Alerta",IF(Q139>=0,"Em dia","Vencido")))))) -> Em dia | Q139: =$P$4-K139 -> 239
B140: 5 | C140: CN2 | D140: 19 | E140: 2 | F140: MM-CN2-019.02 | G140: Manutenção Complementar Preventiva Tipo 2 no Sistema de Corrente Contínua | H140: =(F140)&" - "&(G140) -> MM-CN2-019.02 - Manutenção Complementar Preventiva Tipo 2 no Sistema de Corrente Contínua | I140: Sistema de Corrente Contínua | J140: =VLOOKUP(D140,GM!$D$4:$G$1637,4,3)&" e "&C140 -> ENGENHARIA ELÉTRICA e CN2 | K140: 45959 | L140: =K140+1096 -> 47055 | M140: Publicado | N140: X | O140: =IF(Q140="","",IF(Q140>1095,"Vencido",IF(Q140>910,"Alerta",IF(Q140>820,"Alerta",IF(Q140>730,"Alerta",IF(Q140>=0,"Em dia","Vencido")))))) -> Em dia | Q140: =$P$4-K140 -> 239
... B149: 5 | C149: CN2 | D149: 28 | E149: 2 | F149: MM-CN2-028.02 | G149: Procedimento Manuseio Comportas de Manutenção | H149: =(F149)&" - "&(G149) -> MM-CN2-028.02 - Procedimento Manuseio Comportas de Manutenção | I149: Manual Comporta de Manutenção | J149: =VLOOKUP(D149,GM!$D$4:$G$1637,4,3)&" e "&C149 -> ENGENHARIA MECÂNICA e CN2 | K149: 44062 | L149: =K149+1096 -> 45158 | M149: Publicado | N149: x | O149: =IF(Q149="","",IF(Q149>1095,"Vencido",IF(Q149>910,"Alerta",IF(Q149>820,"Alerta",IF(Q149>730,"Alerta",IF(Q149>=0,"Em dia","Vencido")))))) -> Vencido | Q149: =$P$4-K149 -> 2136
...

Sheet IO
B2: IO - INSTRUÇÕES DE OPERAÇÃO (OPERATION INSTRUCTION)
F3: =COUNTIF(F4:F300,"X") -> 84 | G3: =COUNTIF(G4:G300,"X") -> 69
B4: TIPO/TYPE | C4: NUMERO / NUMBER | D4: DESCRIÇÃO | E4: DESCRIPTION | F4: Por. | G4: Ing. | I4: Status
B5: Instruções de operação local | C5: IO-UHE-001 | D5: Operação Local das Instalações | E5: Local Operation of Installations | F5: X | H5: 13//10/2022 | I5: Publicado
B6: Instruções de operação local | C6: IO-UFV-001 | D6: Operação Local das Instalações | E6: Local Operation of Installations | F6: X | G6: X | H6: 45499 | I6: Publicado
B7: Instruções de operação local | C7: IO-UHE-002 | D7: Troca de turno das usinas | F7: X | H7: 45098 | I7: Publicado
B8: Instruções de operação local | C8: IO-UHE-003 | D8: Gestão de inspeção rotineira | E8: Routine Inspection Management | F8: X | G8: X | H8: 45462 | I8: Publicado
B9: Instruções de operação local | C9: IO-UHE-004 | D9: Aterramento Temporário | E9: Temporary Grounding | F9: X | G9: X | H9: 45743 | I9: Publicado
B10: Instruções de operação local | C10: IO-UEE-004 | D10: Aterramento Temporário | E10: Temporary Grounding | F10: X | G10: X | H10: 45743 | I10: Publicado
B11: Instruções de operação local | C11: IO-UFV-004 | D11: Aterramento Temporário | E11: Temporary Grounding | F11: X | G11: X | H11: 45462 | I11: Publicado
B12: Instruções de operação sistêmica | C12: IO.UEE.001 | D12: Operação Local das Instalações | E12: Local operation | F12: X | G12: X | H12: 45775 | I12: Publicado
B13: Instruções de operação sistêmica | C13: IO.COG.100 | D13: Gestão de Normas de Operação | I13: Cancelada
B14: Instruções de operação sistêmica | C14: IO-EO-101 | D14: Intervenção em planta solar fotovoltaica | E14: Intervention in solar photovoltaic and wind instalation | F14: X | G14: X | H14: 45743 | I14: Publicado
B15: Instruções de operação sistêmica | C15: IO.EO.102 | D15: Intervenção em Equipamentos ou Instalação_V01 | F15: X | H15: 44882 | I15: Publicado
B16: Instruções de operação sistêmica | C16: IO.COG.103 | D16: Controle Hidráulico de Reservatórios | F16: X | H16: 44067 | I16: Publicado
B17: Instruções de operação sistêmica | C17: IO.EO.104 | D17: Solicitação de Intervenção | E17: Intervention Request | F17: X | G17: X | H17: 45462 | I17: Publicado
B18: Instruções de operação sistêmica | C18: IO.EO.105 | D18: Comunicação de Voz na Operação | E18: Voice Communication in Operation | F18: X | G18: X | H18: 45499 | I18: Publicado
B19: Instruções de operação sistêmica | C19: IO.EO.106 | D19: Compensador Síncrono | E19: Synchronous Compensator | F19: X | G19: X | H19: 45743 | I19: Publicado
B20: Instruções de operação sistêmica | C20: IO.COG.107 | D20: Eclusagem | I20: Cancelada
B21: Instruções de operação sistêmica | C21: IO-EO-108 | D21: Investigação, caracterização e tratamento de falha humana.pdf | F21: X | H21: 44774 | I21: Publicado
B22: Instruções de operação sistêmica | C22: IO.EO.109 | D22: Telecheia e Comunicação Externa | E22: Emergency hotline for flood | F22: X | G22: X | H22: 45743 | I22: Publicado
B23: Instruções de operação sistêmica | C23: IO-EO-110 | D23: Telecomando ou Operação Remota de Usina.pdf | F23: X | H23: 44914 | I23: Publicado
B24: Instruções de operação sistêmica | C24: IO.EO.111 | D24: Manobras para Ensaios de Operação e Treinamento de Técnicos de Produção | E24: Maneuvers for operation tests and training of production technicians | F24: X | G24: X | H24: 45743 | I24: Publicado
B25: Instruções de operação sistêmica | C25: IO.COG.113 | D25: Atuação de Proteção de Transformadores | I25: Cancelada
B26: Instruções de operação sistêmica | C26: IO.COG.114 | D26: Informação de Ocorrência | I26: Cancelada
B27: Instruções de operação sistêmica | C27: IO.COG.115 | D27: Identificação de Negativo ou Positivo à Terra | I27: Cancelada
B28: Instruções de operação sistêmica | C28: IO.COG.116 | D28: Comissionamento de Equipamento e Instalação | I28: Cancelada
B29: Instruções de operação sistêmica | C29: IO.COG.117 | D29: Identificação de Cubículos e Painéis | I29: Cancelada
B30: Instruções de operação sistêmica | C30: IO.EO.119 | D30: Diagrama e Esquema de Operação | E30: Diagram and Operation Scheme | F30: X | G30: X | H30: 45743 | I30: Publicado
B31: Instruções de operação sistêmica | C31: IO.EO.120 | D31: Treinamento e Desenvolvimento de Técnico de Operação do Sistema e Técnico de Produ | E31: Training and Development | F31: X | G31: X | H31: 45656 | I31: Publicado
B32: Instruções de operação sistêmica | C32: IO.COG.121 | D32: Atividades de Pós-Operação nas Usinas | I32: Cancelada
B33: Instruções de operação sistêmica | C33: IO.EO.123 | D33: Boletim Informativo de Vazões - BIV | E33: Flow Rate Information Bulletin | F33: X | G33: X | H33: 45743 | I33: Publicado
B34: Instruções de operação sistêmica | C34: IO.COG.124 | D34: Elaboração do Relatório GIO | I34: Cancelada
B35: Instruções de operação sistêmica | C35: IO.EO.125 | D35: Inspeção nos Órgãos de Descarga | E35: Inspection of Discharge Devices | F35: X | G35: X | H35: 45743 | I35: Publicado
B36: Instruções de operação sistêmica | C36: IO.COG.126 | D36: Inspeção na Eclusa | I36: Cancelada
B37: Instruções de operação sistêmica | C37: IO-EO-127 | D37: Auditoria nos processos de operação.pdf | E37: Audit in operation processes | F37: X | G37: X | H37: 44914 | I37: Publicado
B38: Instruções de operação sistêmica | C38: IO.EO.128 | D38: Atualização dos Manuais SOSEm | E38: SOSEm Manuals Update | F38: X | G38: X | H38: 45743 | I38: Publicado
B39: Instruções de operação sistêmica | C39: IO-EO-129 | D39: Livro de Ocorrências.pdf | E39: Occurrence Book | F39: X | G39: X | H39: 45743 | I39: Publicado
B40: Instruções de operação sistêmica | C40: IO.EO.130 | D40: Programação e Realização de Visitas nas Usinas | E40: Programming and Conducting Visits to Plants | F40: X | G40: X | H40: 45656 | I40: Publicado
B41: Instruções de operação sistêmica | C41: IO-EO-131 | D41: Operação por Teleassistência da UHE Jurumirim.pdf | F41: X | H41: 44914 | I41: Publicado
B42: Instruções de operação sistêmica | C42: IO.EO.132 | D42: Operação Remota UHE CHV | E42: Teleassistance operation of the Chavantes hydroelectric power plant | F42: X | G42: X | H42: 45792 | I42: Publicado
B43: Instruções de operação sistêmica | C43: IO.EO.133 | D43: Operação Remota UHE SAG | E43: Remote Operation - HPP Salto Grande | F43: X | G43: X | H43: 45743 | I43: Publicado
B44: Instruções de operação sistêmica | C44: IO-EO-134 | D44: Operação por Teleassistência das UHEs CNO I e II.pdf | F44: X | H44: 45098 | I44: Publicado
B45: Instruções de operação sistêmica | C45: IO.EO.135 | D45: Operação Remota UHE CPV | E45: Operation by Teleassistance of the Capivara HPP | F45: X | G45: X | H45: 45792 | I45: Publicado
B46: Instruções de operação sistêmica | C46: IO.EO.136 | D46: Operação Remota UHE TAQ | E46: Remote Operation HPP Taquaruçu | F46: X | G46: X | H46: 45743 | I46: Publicado
B47: Instruções de operação sistêmica | C47: IO.EO.137 | D47: Operação Remota UHE ROS | E47: Remote Operationção HPP Rosana | F47: X | G47: X | H47: 45743 | I47: Publicado
B48: Instruções de operação sistêmica | C48: IO.EO.138 | D48: Operação Remota PCHs PLM e RET | E48: Remote Operation SHPs Palmeiras e Retiro | F48: X | G48: X | H48: 45743 | I48: Publicado
B49: Instruções de operação sistêmica | C49: IO.COG.139 | D49: Controle Serviço Auxiliar CA e CC - UHEs e PCHs da Rio Paranapanema Energia | I49: Cancelada
B50: Instruções de operação sistêmica | C50: IO.COG.140 | D50: Controle Despacho Geração de Energia | E50: Control and Dispatch of Power Generation | I50: Cancelada
B51: Instruções de operação sistêmica | C51: IO.COG.141 | D51: Acesso e Dowload Programa Diário Operação - PDO | I51: Cancelada
B52: Instruções de operação sistêmica | C52: IO.COG.142 | D52: Análise Balanço Hidráulico | I52: Cancelada
B53: Instruções de operação sistêmica | C53: IO.COG.143 | D53: Apuração Energia Vertida Turbinável | I53: Cancelada
B54: Instruções de operação sistêmica | C54: IO.COG.144 | D54: Check List COG | I54: Cancelada
B55: Instruções de operação sistêmica | C55: IO.COG.145 | D55: Diretrizes Área Planejamento Operação | I55: Cancelada
B56: Instruções de operação sistêmica | C56: IO-EO-146 | D56: Manual de Operação Spectrum Power 5.6 Siemens - SSC-COG.pdf | I56: Cancelada
B57: Instruções de operação sistêmica | C57: IO.COG.146 | D57: Manual Operação Sistema Spectrum Power 5.3 Siemens - COG Paranapanema | I57: Cancelada
B58: Instruções de operação sistêmica | C58: IO.EO.147 | D58: Lançamento Dados SISOP | E58: SISOP Data Release | F58: X | G58: X | H58: 45656 | I58: Publicado
B59: Instruções de operação sistêmica | C59: IO.COG.148 | D59: Processos de Liberação e Normalização | I59: Cancelada
B60: Instruções de operação sistêmica | C60: IO-EO-149 | D60: SSC-COG Anomalias.pdf | I60: Cancelada
B61: Instruções de operação sistêmica | C61: IO.COG.149 | D61: SSC-COG Anomalias | I61: Cancelada
B62: Instruções de operação sistêmica | C62: IO.COG.150 | D62: Procedimento Acesso Sala Servidor | I62: Cancelada
B63: Instruções de operação sistêmica | C63: IO.COG.151 | D63: Solicitação de Serviços de TI | I63: Cancelada
B64: Instruções de operação sistêmica | C64: IO.COG.152 | D64: Teste Potência Máxima UHE's | I64: Cancelada
B65: Instruções de operação sistêmica | C65: IO.EO.153 | D65: Contingências em Disjuntores de Grupo | E65: Contingencies in Group Circuit Breakers | F65: X | G65: X | H65: 45743 | I65: Publicado
B66: Instruções de operação sistêmica | C66: IO.EO.154 | D66: Curva Capabilidade UG's | E66: UG Capability Curve | F66: X | G66: X | H66: 45743 | I66: Publicado
B67: Instruções de operação sistêmica | C67: IO.COG.155 | D67: Despacho Ótimo UG's | I67: Cancelada
B68: Instruções de operação sistêmica | C68: IO.COG.156 | D68: Faixa Operativa Unidades Geradoras | I68: Cancelada
B69: Instruções de operação sistêmica | C69: IO.COG.157 | D69: Hidrologia Verificações | I69: Cancelada
B70: Instruções de operação sistêmica | C70: IO.COG.158 | D70: Informações Meteorológicas Anomalias | I70: Cancelada
B71: Instruções de operação sistêmica | C71: IO.COG.159 | D71: Inspeção à Jusante Vertedor UHE Capivara | I71: Cancelada
B72: Instruções de operação sistêmica | C72: IO.EO.160 | D72: Interrupção Sistema Comunicação Devido Interferência Solar | E72: Communication System Interruption Due to Solar Interference | F72: X | G72: X | H72: 45743 | I72: Publicado
B73: Instruções de operação sistêmica | C73: IO.COG.161 | D73: Manobras Vertedores UHEs e PCHs | I73: Cancelada
B74: Instruções de operação sistêmica | C74: IO.COG.162 | D74: PRE COG | I74: Cancelada
B75: Instruções de operação sistêmica | C75: IO.COG.163 | D75: Processo Despacho Operação | I75: Cancelada
B76: Instruções de operação sistêmica | C76: IO.EO.164 | D76: Restrição Geração UGs | E76: Generation Restriction in Installations and Ugs | F76: X | G76: X | H76: 45743 | I76: Publicado
B77: Instruções de operação sistêmica | C77: IO.COG.165 | D77: Simulador Hydroexpert | I77: Cancelada
B78: Instruções de operação sistêmica | C78: IO.COG.166 | D78: SSC COG Colocação de TAG | I78: Cancelada
B79: Instruções de operação sistêmica | C79: IO.COG.167 | D79: SSC COG Modo Operação Facilidades | I79: Cancelada
B80: Instruções de operação sistêmica | C80: IO.COG.169 | D80: Manutenção Dados Rede Telemétrica PI ou SISOP | I80: Cancelada
B81: Instruções de operação sistêmica | C81: IO.EO.170 | D81: Transposição Plantas Aquáticas | E81: Aquatic Plant Transposition | F81: X | G81: X | H81: 45743 | I81: Publicado
B82: Instruções de operação sistêmica | C82: IO.COG.171 | D82: Tratativas COSR-SE | I82: Cancelada
B83: Instruções de operação sistêmica | C83: IO.COG.172 | D83: Recomposição UHE JUR | I83: Cancelada
B84: Instruções de operação sistêmica | C84: IO.COG.173 | D84: Recomposição UHE CHV | I84: Cancelada
B85: Instruções de operação sistêmica | C85: IO.EO.174 | D85: Recomposição UHE SAG | E85: Recomposition of the HPP Salto Grande | F85: X | G85: X | H85: 45743 | I85: Publicado
B86: Instruções de operação sistêmica | C86: IO.EO.175 | D86: Recomposição UHE CN2 | E86: Recomposition of the HPP Canoas 2 | F86: X | G86: X | H86: 45743 | I86: Publicado
B87: Instruções de operação sistêmica | C87: IO.EO.176 | D87: Recomposição UHE CN1 | E87: Recomposition of the HPP Canoas 1 | F87: X | G87: X | H87: 45656 | I87: Publicado
B88: Instruções de operação sistêmica | C88: IO.COG.177 | D88: Recomposição UHE CPV | I88: Cancelada
B89: Instruções de operação sistêmica | C89: IO.COG.178 | D89: Recomposição UHE TAQ | I89: Cancelada
B90: Instruções de operação sistêmica | C90: IO.COG.179 | D90: Recomposição UHE ROS | I90: Cancelada
B91: Instruções de operação sistêmica | C91: IO.EO.180 | D91: Operação Via COG Alternativo do Paranapanema | E91: Real-time operation via COG CTG Brazil Alternative | F91: X | G91: X | H91: 45743 | I91: Publicado
B92: Instruções de operação sistêmica | C92: IO.COG.181 | D92: Dados Geração Verificada Horária | I92: Cancelada
B93: Instruções de operação sistêmica | C93: IO.COG.182 | D93: Profissionais Credenciados a Receber AES | I93: Cancelada
B94: Instruções de operação sistêmica | C94: IO.EO.183 | D94: Programa PRIMO | E94: PRIMO Program | F94: X | G94: X | H94: 45743 | I94: Publicado
B95: Instruções de operação sistêmica | C95: IO.COG.184 | D95: Relatório Diário da Operação a partir do SISOP | I95: Cancelada
B96: Instruções de operação sistêmica | C96: IO.COG.185 | D96: Solicitação de SGI | I96: Cancelada
B97: Instruções de operação sistêmica | C97: IO-EO-186 | D97: Comunicação de Ocorrências para a CTGI.pdf | F97: X | H97: 44914 | I97: Publicado
B98: Instruções de operação sistêmica | C98: IO.COG.187 | D98: Sistema de Supervisão e Comando do COG Paranapanema | I98: Cancelada
B99: Instruções de operação sistêmica | C99: IO.EO.188 | D99: Partida de UG parada em DCO nas UHE Canoas I e II | E99: UG startup in HPPs Canoas I and II | F99: X | G99: X | H99: 45743 | I99: Publicado
B100: Instruções de operação sistêmica | C100: IO.COG.190 | D100: Troca de turno dos COGs | I100: Cancelada
B101: Instruções de operação sistêmica | C101: IO.EO.191 | D101: Teleassistance Operation - UEE Serra da Palmeira | E101: Operação por Teleassistência da UEE Serra da Palmeira | F101: X | G101: X | H101: 45799 | I101: Publicado
...

Sheet GO
B2: GO - GUIA DE OPERAÇÃO (OPERATION GUIDE)
G3: =COUNTIF(G4:G929,"X") -> 212 | H3: =COUNTIF(H4:H929,"X") -> 83
B4: N UHE/HPP | C4: UHE/HPP | D4: NUMERO / NUMBER | E4: DESCRIÇÃO | F4: DESCRIPTION | G4: Por. | H4: Ing. | J4: Status
B5: 1 | C5: JUR | D5: 10 | E5: Guia de Operação - Alarmes e Providências.pdf | F5: Alarms and Actions | G5: X | H5: X | I5: 45462 | J5: Publicado
B6: 1 | C6: JUR | D6: 20 | E6: Guia de Operação - Partida e Parada de UG | G6: X | I6: 45839 | J6: Publicado
B7: 1 | C7: JUR | D7: 30 | E7: GO-JUR-030 - Guia de Operação do Gerador Auxiliar de Emergência - GAE | F7: Auxiliary emergency generator - GAE | G7: X | H7: X | I7: 45839 | J7: Publicado
B8: 1 | C8: JUR | D8: 40 | E8: Contingências em Tubulações de Água_UHE JUR | G8: X | I8: 44067 | J8: Publicado
B9: 1 | C9: JUR | D9: 50 | E9: Operação em Seccionadoras de 230 Kv | G9: X | I9: 44067 | J9: Publicado
B10: 1 | C10: JUR | D10: 70 | E10: Guia de Operação - Inspeção Rotineira | F10: Routine Inspection | G10: X | H10: X | I10: 45462 | J10: Publicado
B11: 1 | C11: JUR | D11: 320 | E11: Serviços que podem ser realizados sem AES | F11: Services that can be performed without AES | G11: X | H11: X | I11: 45743 | J11: Publicado
B12: 1 | C12: JUR | D12: 330 | E12: Sinalização e Isolamento de Área | G12: X | I12: 45314 | J12: Publicado
B13: 2 | C13: CHV | D13: 10 | E13: Guia de Operação de Alarmes e Providências | F13: Alarms and Actions | G13: X | H13: X | I13: 45792 | J13: Publicado
C14: CHV | D14: 20 | E14: Guia de Operação - Partida e Parada de Ugs | F14: Starting And Stopping Of Power Unit | G14: X | H14: X | I14: 45839 | J14: Publicado
B15: 2 | C15: CHV | D15: 30 | E15: Guia de Operação do Gerador Auxiliar de Emergência | F15: Auxiliary Emergency Generator - GAE | G15: X | H15: X | I15: 45839 | J15: Publicado
B16: 2 | C16: CHV | D16: 40 | E16: Contingências em Tubulações de Água_UHE CHV | G16: X | I16: 44067 | J16: Publicado
B17: 2 | C17: CHV | D17: 50 | E17: Operação em Seccionadoras de 88 e 230 kV | G17: X | I17: 44067 | J17: Publicado
B18: 2 | C18: CHV | D18: 70 | E18: Guia de Operação - Inspeção Rotineira | F18: Routine Inspection | G18: X | H18: X | I18: 45792 | J18: Publicado
B19: 2 | C19: CHV | D19: 320 | E19: Serviços que podem ser realizados sem AES | F19: Services that can be performed without AES | G19: X | H19: X | I19: 45743 | J19: Publicado
B20: 2 | C20: CHV | D20: 330 | E20: Sinalização e Isolamento de Área | G20: X | I20: 44973 | J20: Publicado
B21: 3 | C21: SAG | D21: 10.07 | E21: Guia de Operação - Sinalizações e Providências do Sistema PAE | F21: PAE system Alarms and Actions | G21: X | H21: X | I21: 45462 | J21: Publicado
B22: 3 | C22: SAG | D22: 30 | E22: Guia de Operação do Gerador Auxiliar de Emergência - GAE | F22: Guide Operation Auxiliary Emergency Generator - GAE | G22: X | H22: X | I22: 45839 | J22: Publicado
B23: 3 | C23: SAG | D23: 40 | E23: Contingências em Tubulações de Água_UHE SAG | G23: X | I23: 44067 | J23: Publicado
B24: 3 | C24: SAG | D24: 50 | E24: Operação em Seccionadoras de 88 kV | G24: X | I24: 44067 | J24: Publicado
B25: 3 | C25: SAG | D25: 70 | E25: GO-SAG-070 - Guia de Operação - Inspeção Rotineira.pdf | F25: Routine Inspection | G25: X | H25: X | I25: 44067 | J25: Publicado
B26: 3 | C26: SAG | D26: 80 | E26: GO-SAG-080 - Guia de Operação - Subestação 88 kV.pdf | G26: X | I26: 45225 | J26: Publicado
B27: 3 | C27: SAG | D27: 320 | E27: Serviços que podem ser realizados sem AES | F27: Services that can be performed without AES | G27: X | H27: X | I27: 45743 | J27: Publicado
B28: 3 | C28: SAG | D28: 330 | E28: GO-SAG-330_V.00 - Sinalização e Isolamento de Área.pdf | G28: X | I28: 44973 | J28: Publicado
B29: 4 | C29: CN1 | D29: 10 | E29: Guia de Operação de Alarmes e Providências | F29: Alarms and Actions | G29: X | H29: X | I29: 45462 | J29: Publicado
B30: 4 | C30: CN1 | D30: 30 | E30: Guia de Operação do Gerador Auxiliar de Emergência | F30: Auxiliary Emergency Generator - GAE | G30: X | H30: X | I30: 45839 | J30: Publicado
B31: 4 | C31: CN1 | D31: 40 | E31: Contingências em Tubulações de Água_UHE CN1 | G31: X | I31: 44067 | J31: Publicado
B32: 4 | C32: CN1 | D32: 50 | E32: Operação em Seccionadoras de 88 kV | G32: X | I32: 44067 | J32: Publicado
B33: 4 | C33: CN1 | D33: 70 | E33: Guia de Operação - Inspeção Rotineira | F33: Routine Inspection | G33: X | H33: X | I33: 45462 | J33: Publicado
B34: 4 | C34: CN1 | D34: 320 | E34: Serviços que podem ser realizados sem AES | F34: Services that can be performed without AES | G34: X | H34: X | I34: 45743 | J34: Publicado
B35: 4 | C35: CN1 | D35: 330 | E35: Sinalização e Isolamento de Área | G35: X | I35: 45008 | J35: Publicado
B36: 5 | C36: CN2 | D36: 10 | E36: Guia de Operação de Alarmes e Providências | F36: Alarms and Actions | G36: X | H36: X | I36: 45462 | J36: Publicado
B37: 5 | C37: CN2 | D37: 30 | E37: Guia de Operação do Gerador Auxiliar de Emergência | F37: Auxiliary Emergency Generator - GAE | G37: X | H37: X | I37: 45839 | J37: Publicado
B38: 5 | C38: CN2 | D38: 40 | E38: Contingências em Tubulações de Água_UHE CN2 | G38: X | I38: 44067 | J38: Publicado
B39: 5 | C39: CN2 | D39: 50 | E39: Operação em Seccionadoras de 88 kV | G39: X | I39: 44067 | J39: Publicado
B40: 5 | C40: CN2 | D40: 70 | E40: Guia de Operação - Inspeção Rotineira | F40: Routine Inspection | G40: X | H40: X | I40: 45462 | J40: Publicado
B41: 5 | C41: CN2 | D41: 320 | E41: Serviços que podem ser realizados sem AES | F41: Services that can be performed without AES | G41: X | H41: X | I41: 45743 | J41: Publicado
B42: 5 | C42: CN2 | D42: 330 | E42: Sinalização e Isolamento de Área | G42: X | I42: 45008 | J42: Publicado
B43: 6 | C43: CPV | D43: 10 | E43: Guia de Operação - Alarmes e Providências | F43: Alarms and Actions | G43: X | H43: X | I43: 45792 | J43: Publicado
B44: 6 | C44: CPV | D44: 20 | E44: Guia de Operação - Partida e Parada de UG's | G44: X | I44: 44067 | J44: Publicado
B45: 6 | C45: CPV | D45: 40 | E45: Guia de Operação - Contingências em Tubulações de Água | G45: X | I45: 44067 | J45: Publicado
B46: 6 | C46: CPV | D46: 50 | E46: Guia de Operação - Manobras em Seccionadoras | G46: X | I46: 44067 | J46: Publicado
B47: 6 | C47: CPV | D47: 60 | E47: Guia de Operação - Recomposição pós desligamento geral da Usina ou blecaute | G47: X | I47: 44067 | J47: Publicado
B48: 6 | C48: CPV | D48: 70 | E48: Guia de Operação - Inspeção Rotineira | F48: Routine Inspection | G48: X | H48: X | I48: 45792 | J48: Publicado
B49: 6 | C49: CPV | D49: 320 | E49: Serviços que podem ser realizados sem AES | F49: Services that can be performed without AES | G49: X | H49: X | I49: 45716 | J49: Publicado
B50: 6 | C50: CPV | D50: 330 | E50: Sinalização e Isolamento de Área | G50: X | I50: 44931 | J50: Publicado
B51: 7 | C51: GAR | D51: 10 | E51: Guia de Operação de Alarmes e Providências | F51: Alarms and Actions | G51: X | H51: X | I51: 45462 | J51: Publicado
B52: 7 | C52: GAR | D52: 70 | E52: Guia de Operação - Inspeção Rotineira.pdf | F52: Routine Inspection | G52: X | H52: X | I52: 45462 | J52: Publicado
B53: 7 | C53: GAR | D53: 320 | E53: Serviços que podem ser realizados sem AES | F53: Services that can be performed without AES | G53: X | H53: X | I53: 45716 | J53: Publicado
B54: 7 | C54: GAR | D54: 330 | E54: Sinalização e Isolamento de Área | F54: Signage and area isolation | G54: X | H54: X | I54: 45839 | J54: Publicado
B55: 8 | C55: ILS | D55: 010.01 | E55: GO-ILS-010.01 - Guia de operação de alarmes e providências - UG01 - 1º Grau.pdf | G55: X | I55: 44067 | J55: Publicado
B56: 8 | C56: ILS | D56: 010.02 | E56: GO-ILS-010.02 - Guia de operação de alarmes e providências - UG02 - 1º Grau.pdf | G56: X | I56: 44067 | J56: Publicado
B57: 8 | C57: ILS | D57: 010.04 | E57: GO-ILS-010.04 - Guia de operação de alarmes e providências - UG04 - 1º Grau.pdf | G57: X | I57: 44067 | J57: Publicado
B58: 8 | C58: ILS | D58: 010.05 | E58: GO-ILS-010.05 - Guia de operação de alarmes e providências - UG05 - 1º Grau.pdf | G58: X | I58: 44067 | J58: Publicado
B59: 8 | C59: ILS | D59: 010.06 | E59: GO-ILS-010.06 - Guia de operação de alarmes e providências - UG06 - 1º Grau.pdf | G59: X | I59: 44067 | J59: Publicado
B60: 8 | C60: ILS | D60: 010.08 | E60: GO-ILS-010.08 - Guia de operação de alarmes e providências - UG08 - 1º Grau.pdf | G60: X | I60: 44067 | J60: Publicado
B61: 8 | C61: ILS | D61: 010.10 | E61: GO-ILS-010.10 - Guia de operação de alarmes e providências - UG10 - 1º Grau.pdf | G61: X | I61: 44067 | J61: Publicado
B62: 8 | C62: ILS | D62: 010.11 | E62: GO-ILS-010.11 - Guia de operação de alarmes e providências - UG11 - 1º Grau.pdf | G62: X | I62: 44067 | J62: Publicado
B63: 8 | C63: ILS | D63: 010.12 | E63: GO-ILS-010.12 - Guia de operação de alarmes e providências - UG12 - 1º Grau.pdf | G63: X | I63: 44067 | J63: Publicado
B64: 8 | C64: ILS | D64: 010.13 | E64: GO-ILS-010.13 - Guia de operação de alarmes e providências - UG13 - 1º Grau.pdf | G64: X | I64: 44067 | J64: Publicado
B65: 8 | C65: ILS | D65: 010.14 | E65: GO-ILS-010.14 - Guia de operação de alarmes e providências - UG14 - 1º Grau.pdf | G65: X | I65: 44067 | J65: Publicado
B66: 8 | C66: ILS | D66: 010.15 | E66: GO-ILS-010.15 - Guia de operação de alarmes e providências - UG15 - 1º Grau.pdf | G66: X | I66: 44067 | J66: Publicado
... B86: 8 | C86: ILS | D86: 010.39 | E86: GO-ILS-010.39 - Guia de operação de alarmes e providências - UG19 - 2º Grau.pdf | G86: X | I86: 44067 | J86: Publicado
